Workbook
Name kappaP1: '24h-Colombia'!$D$14
Name kappaP1: '24h-ESPAÑA'!$G$23
Name kappaP1: 'Tarifas España 2024'!$G$23
Name kappaP2: '24h-Colombia'!$D$15
Name kappaP2: '24h-ESPAÑA'!$G$24
Name kappaP2: 'Tarifas España 2024'!$G$24
Name kappaP3: '24h-Colombia'!$D$16
Name kappaP3: '24h-ESPAÑA'!$G$25
Name kappaP3: 'Tarifas España 2024'!$G$25

Sheet 24h-Colombia
G1: P | I1: Q | L1: Penalización por
D2: CU | F2: USD/MWh | G2: kW | H2: Fc | I2: kVAr | J2: fp | K2: Pago P | L2: Reactiva Q | U2: Gams Syntax
C3: 1 | D3: ='Tarifas Colombia 2024'!$Q$16 -> 0.19042896 | F3: =D3*1000 -> 190.42896 | G3: =Industria!T3 -> 31.307452 | H3: =Industria!U3 -> 0.13538863 | I3: =Industria!V3 -> 27.875151 | J3: =COS(ATAN(I3/G3)) -> 0.74686056 | K3: =G3*D3 -> 5.9618455 | L3: =IF((I3-G3/2)*15*106/4005>0,(I3-G3/2)*15*106/4005,0) -> 4.8519514 | V3: cu | W3: Plu | X3: Ppvu | Y3: lambda | AB3: lambda
C4: 2 | D4: 0.19042896 | F4: =D4*1000 -> 190.42896 | G4: =Industria!T4 -> 20.898959 | H4: =Industria!U4 -> 0.090377249 | I4: =Industria!V4 -> 22.371534 | J4: =COS(ATAN(I4/G4)) -> 0.68264743 | K4: =G4*D4 -> 3.979767 | L4: =IF((I4-G4/2)*15*106/4005>0,(I4-G4/2)*15*106/4005,0) -> 4.7331004 | U4: t1 | V4: =D3 -> 0.19042896 | W4: =H3 -> 0.13538863 | X4: =#REF! -> #REF! | Y4: {='Precios Bolsa Colombia 2024'!A3:A26} -> 0.15860415 | AB4: ='Precios Bolsa Colombia 2024'!Q$29 -> 0.15443928
C5: 3 | D5: 0.19042896 | F5: =D5*1000 -> 190.42896 | G5: =Industria!T5 -> 17.653808 | H5: =Industria!U5 -> 0.076343641 | I5: =Industria!V5 -> 20.669616 | J5: =COS(ATAN(I5/G5)) -> 0.64945418 | K5: =G5*D5 -> 3.3617963 | L5: =IF((I5-G5/2)*15*106/4005>0,(I5-G5/2)*15*106/4005,0) -> 4.7016011 | U5: t2 | V5: =D4 -> 0.19042896 | W5: =H4 -> 0.090377249 | X5: =#REF! -> #REF! | Y5: 0.12171982 | AB5: ='Precios Bolsa Colombia 2024'!Q$29 -> 0.15443928
C6: 4 | D6: 0.19042896 | F6: =D6*1000 -> 190.42896 | G6: =Industria!T6 -> 17.394959 | H6: =Industria!U6 -> 0.075224251 | I6: =Industria!V6 -> 20.802712 | J6: =COS(ATAN(I6/G6)) -> 0.64147549 | K6: =G6*D6 -> 3.3125039 | L6: =IF((I6-G6/2)*15*106/4005>0,(I6-G6/2)*15*106/4005,0) -> 4.8058228 | U6: t3 | V6: =D5 -> 0.19042896 | W6: =H5 -> 0.076343641 | X6: =#REF! -> #REF! | Y6: 0.11909825 | AB6: ='Precios Bolsa Colombia 2024'!Q$29 -> 0.15443928
C7: 5 | D7: 0.19042896 | F7: =D7*1000 -> 190.42896 | G7: =Industria!T7 -> 17.182986 | H7: =Industria!U7 -> 0.074307579 | I7: =Industria!V7 -> 20.762822 | J7: =COS(ATAN(I7/G7)) -> 0.63756686 | K7: =G7*D7 -> 3.2721382 | L7: =IF((I7-G7/2)*15*106/4005>0,(I7-G7/2)*15*106/4005,0) -> 4.8320631 | U7: t4 | V7: =D6 -> 0.19042896 | W7: =H6 -> 0.075224251 | X7: =#REF! -> #REF! | Y7: 0.1160119 | AB7: ='Precios Bolsa Colombia 2024'!Q$29 -> 0.15443928
C8: 6 | D8: 0.19042896 | F8: =D8*1000 -> 190.42896 | G8: =Industria!T8 -> 16.905041 | H8: =Industria!U8 -> 0.073105609 | I8: =Industria!V8 -> 20.711205 | J8: =COS(ATAN(I8/G8)) -> 0.63233013 | K8: =G8*D8 -> 3.2192094 | L8: =IF((I8-G8/2)*15*106/4005>0,(I8-G8/2)*15*106/4005,0) -> 4.8667438 | U8: t5 | V8: =D7 -> 0.19042896 | W8: =H7 -> 0.074307579 | X8: =#REF! -> #REF! | Y8: 0.1184893 | AB8: ='Precios Bolsa Colombia 2024'!Q$29 -> 0.15443928
C9: 7 | D9: 0.19042896 | F9: =D9*1000 -> 190.42896 | G9: =Industria!T9 -> 16.974548 | H9: =Industria!U9 -> 0.07340619 | I9: =Industria!V9 -> 20.580986 | J9: =COS(ATAN(I9/G9)) -> 0.63627665 | K9: =G9*D9 -> 3.2324455 | L9: =IF((I9-G9/2)*15*106/4005>0,(I9-G9/2)*15*106/4005,0) -> 4.8012491 | U9: t6 | V9: =D8 -> 0.19042896 | W9: =H8 -> 0.073105609 | X9: =#REF! -> #REF! | Y9: 0.12427995 | AB9: ='Precios Bolsa Colombia 2024'!Q$29 -> 0.15443928
C10: 8 | D10: 0.19042896 | F10: =D10*1000 -> 190.42896 | G10: =Industria!T10 -> 19.774932 | H10: =Industria!U10 -> 0.085516409 | I10: =Industria!V10 -> 21.413726 | J10: =COS(ATAN(I10/G10)) -> 0.67843597 | K10: =G10*D10 -> 3.7657196 | L10: =IF((I10-G10/2)*15*106/4005>0,(I10-G10/2)*15*106/4005,0) -> 4.5759685 | U10: t7 | V10: =D9 -> 0.19042896 | W10: =H9 -> 0.07340619 | X10: =#REF! -> #REF! | Y10: 0.12433783 | AB10: ='Precios Bolsa Colombia 2024'!Q$29 -> 0.15443928
C11: 9 | D11: 0.19042896 | F11: =D11*1000 -> 190.42896 | G11: =Industria!T11 -> 204.33975 | H11: =Industria!U11 -> 0.88366434 | I11: =Industria!V11 -> 141.48904 | J11: =COS(ATAN(I11/G11)) -> 0.82214877 | K11: =G11*D11 -> 38.912206 | L11: =IF((I11-G11/2)*15*106/4005>0,(I11-G11/2)*15*106/4005,0) -> 15.609856 | U11: t8 | V11: =D10 -> 0.19042896 | W11: =H10 -> 0.085516409 | X11: =#REF! -> #REF! | Y11: 0.13064242 | AB11: ='Precios Bolsa Colombia 2024'!Q$29 -> 0.15443928
C12: 10 | D12: 0.19042896 | F12: =D12*1000 -> 190.42896 | G12: =Industria!T12 -> 231.24137 | H12: =Industria!U12 -> 1 | I12: =Industria!V12 -> 95.876274 | J12: =COS(ATAN(I12/G12)) -> 0.92374818 | K12: =G12*D12 -> 44.035053 | L12: =IF((I12-G12/2)*15*106/4005>0,(I12-G12/2)*15*106/4005,0) -> 0 | U12: t9 | V12: =D11 -> 0.19042896 | W12: =H11 -> 0.88366434 | X12: =#REF! -> #REF! | Y12: 0.13763512 | AB12: ='Precios Bolsa Colombia 2024'!Q$29 -> 0.15443928
C13: 11 | D13: 0.19042896 | F13: =D13*1000 -> 190.42896 | G13: =Industria!T13 -> 223.66726 | H13: =Industria!U13 -> 0.96724587 | I13: =Industria!V13 -> 91.472521 | J13: =COS(ATAN(I13/G13)) -> 0.92558715 | K13: =G13*D13 -> 42.592723 | L13: =IF((I13-G13/2)*15*106/4005>0,(I13-G13/2)*15*106/4005,0) -> 0 | U13: t10 | V13: =D12 -> 0.19042896 | W13: =H12 -> 1 | X13: =#REF! -> #REF! | Y13: 0.14010958 | AB13: ='Precios Bolsa Colombia 2024'!Q$29 -> 0.15443928
C14: 12 | D14: 0.19042896 | F14: =D14*1000 -> 190.42896 | G14: =Industria!T14 -> 223.47403 | H14: =Industria!U14 -> 0.96641024 | I14: =Industria!V14 -> 126.74858 | J14: =COS(ATAN(I14/G14)) -> 0.86983297 | K14: =G14*D14 -> 42.555926 | L14: =IF((I14-G14/2)*15*106/4005>0,(I14-G14/2)*15*106/4005,0) -> 5.9596462 | U14: t11 | V14: =D13 -> 0.19042896 | W14: =H13 -> 0.96724587 | X14: =#REF! -> #REF! | Y14: 0.14431613 | AB14: ='Precios Bolsa Colombia 2024'!Q$29 -> 0.15443928
C15: 13 | D15: 0.19042896 | F15: =D15*1000 -> 190.42896 | G15: =Industria!T15 -> 28.407397 | H15: =Industria!U15 -> 0.12284738 | I15: =Industria!V15 -> 2.0675616 | J15: =COS(ATAN(I15/G15)) -> 0.99736183 | K15: =G15*D15 -> 5.4095911 | L15: =IF((I15-G15/2)*15*106/4005>0,(I15-G15/2)*15*106/4005,0) -> 0 | U15: t12 | V15: =D14 -> 0.19042896 | W15: =H14 -> 0.96641024 | X15: =#REF! -> #REF! | Y15: 0.14789205 | AB15: ='Precios Bolsa Colombia 2024'!Q$29 -> 0.15443928
C16: 14 | D16: 0.19042896 | F16: =D16*1000 -> 190.42896 | G16: =Industria!T16 -> 206.30877 | H16: =Industria!U16 -> 0.89217932 | I16: =Industria!V16 -> 84.879041 | J16: =COS(ATAN(I16/G16)) -> 0.9247911 | K16: =G16*D16 -> 39.287164 | L16: =IF((I16-G16/2)*15*106/4005>0,(I16-G16/2)*15*106/4005,0) -> 0 | U16: t13 | V16: =D15 -> 0.19042896 | W16: =H15 -> 0.12284738 | X16: =#REF! -> #REF! | Y16: 0.14797283 | AB16: ='Precios Bolsa Colombia 2024'!Q$29 -> 0.15443928
... C26: 24 | D26: 0.19042896 | F26: =D26*1000 -> 190.42896 | G26: =Industria!T26 -> 31.920795 | H26: =Industria!U26 -> 0.13804102 | I26: =Industria!V26 -> 27.457562 | J26: =COS(ATAN(I26/G26)) -> 0.75811852 | K26: =G26*D26 -> 6.0786436 | L26: =IF((I26-G26/2)*15*106/4005>0,(I26-G26/2)*15*106/4005,0) -> 4.5644173 | U26: t23 | V26: =D25 -> 0.19042896 | W26: =H25 -> 0.14488307 | X26: =#REF! -> #REF! | Y26: 0.14000581 | AB26: ='Precios Bolsa Colombia 2024'!Q$29 -> 0.15443928
F27: =SUM(F3:F26)/24 -> 190.42896 | G27: =SUM(G3:G26) -> 2629.1417 | I27: =SUM(I3:I26) -> 1251.3968 | J27: =COS(ATAN(I29/G29)) -> 0.90293721 | K27: =SUM(K3:K26) -> 500.66471 | L27: =SUM(L3:L26) -> 68.335259 | U27: t24 | V27: =D26 -> 0.19042896 | W27: =H26 -> 0.13804102 | X27: =#REF! -> #REF! | Y27: 0.13456529 | AB27: ='Precios Bolsa Colombia 2024'!Q$29 -> 0.15443928
A28: LF | B28: =G27/MAX(G3:G26)/24 -> 0.4737369 | G28: kWh/dia | I28: kWh/dia | K28: USD/DIA | L28: USD/DIA | Y28: =AB4 -> 0.15443928
G29: =G27*365 -> 959636.71 | I29: =I27*365 -> 456759.84
A30: CUpico | B30: ='Tarifas Colombia 2024'!P21 -> 773.6886 | C30: = | D30: =B30/'Tarifas Colombia 2024'!$C$29 -> 0.19342215 | G30: kWh/año | I30: kWh/año
A31: CUnopico | B31: ='Tarifas Colombia 2024'!P22 -> 758.58584 | C31: = | D31: =B31/'Tarifas Colombia 2024'!$C$29 -> 0.18964646 | F31: Plmax= | G31: =G27/(24*B28) -> 231.24137
A33: Wpico | B33: =SUM(G20:G25) -> 656.79123 | D33: kWh
A34: Wnopico | B34: =SUM(G3:G19,G26) -> 1972.3504 | D34: kWh
A35: Wtotal | B35: =B34+B33 -> 2629.1417 | D35: kWh | I35: ENERGIA P comprada | K35: =-K27*365 -> -182742.62 | L35: USD/AÑO
I36: Penalización Q | K36: =-L27*365 -> -24942.37 | L36: USD/AÑO
I37: Total | K37: =SUM(K35:K36) -> -207684.99 | L37: USD/AÑO
I38: POSITIVO significa saldo a favor
I39: NEGATIVO significa saldo a pagar
I40: Costo medio | K40: =-K35/G29 -> 0.19042896 | L40: USD/AÑO

Sheet 24h-ESPAÑA
B1: Periodos Horarios segun esquema de Enero 2024
A2: Peajes o | B2: Tarifas | C2: PotenciaActiva
B3: Peaje+Cargo Pot Eur/kW/año | D3: Pot Contratada kW | E3: Eur/año | G3: Energia activa | H3: Capacidad | I3: Perdidas | X3: Costes de Operación | Y3: ='Tarifas España 2024'!AM7 -> 0.001 | Z3: Eur/kWh
B4: P1 | C4: =AW44 -> 28.791866 | D4: =W104 -> 570 | E4: =-D4*C4 -> -16411.364 | G4: =AW53 -> 0.044778 | H4: =AF62 -> 0.00049 | I4: =AF71 -> 0.067 | S4: Industria Acero | T4: =MAX(D4:D9) -> 570 | V4: kW | X4: Retribucion OM+OS | Y4: ='Tarifas España 2024'!AM8 -> 0.00020949 | Z4: Eur/kWh
B5: P2 | C5: =AX44 -> 15.077643 | D5: =W105 -> 560 | E5: =-D5*C5 -> -8443.4801 | G5: =AX53 -> 0.024986 | H5: =AG62 -> 0.000225 | I5: =AG71 -> 0.068 | S5: Load factor | T5: =SUM(K12:K35)/24/MAX(K12:K35) -> 0.4737369 | X5: Bono Social | Y5: ='Tarifas España 2024'!AM9 -> 0.000358725 | Z5: Eur/kWh
B6: P3 | C6: =AY44 -> 6.55917 | D6: =W106 -> 480 | E6: =-D6*C6 -> -3148.4016 | G6: =AY53 -> 0.011795 | H6: =AH62 -> 0.00015 | I6: =AH71 -> 0.065 | S6: Power factor | T6: =P36 -> 0.90293721 | V6: lag | X6: Tasa Local | Y6: ='Tarifas España 2024'!AM10 -> 0.015 | Z6: Eur/kWh
B7: P4 | C7: =AZ44 -> 5.172085 | D7: =W107 -> 480 | E7: =-D7*C7 -> -2482.6008 | G7: =AZ53 -> 0.006274 | H7: =AI62 -> 0.000113 | I7: =AI71 -> 0.065
B8: P5 | C8: =BA44 -> 1.932805 | D8: =W108 -> 460 | E8: =-D8*C8 -> -889.0903 | G8: =BA53 -> 0.002388 | H8: =AJ62 -> 0.000113 | I8: =AJ71 -> 0.043
B9: P6 | C9: =BB44 -> 0.916088 | D9: =W109 -> 370 | E9: =-D9*C9 -> -338.95256 | G9: =BB53 -> 0.001443 | H9: =AK62 -> 0 | I9: =AK71 -> 0.077
B10: kappa = | C10: =E10/D10 -> -65.165525 | D10: =AVERAGE(D4:D9) -> 486.66667 | E10: =SUM(E4:E9) -> -31713.889 | G10: precios medios | K10: P | M10: Q | N10: psi | O10: psi adjusted | P10: fp
B11: Periodo | C11: Termino Ener | D11: Capacidad | E11: Perdidas | F11: hora | G11: Spot | H11: Restricciones | I11: Procesos OS | J11: Precio | K11: kWh | L11: Fc | M11: kVArh | R11: Pago W Tot
A12: 1 | B12: P6 | C12: =$G$9 -> 0.001443 | D12: =$H$9 -> 0 | E12: 0.077 | F12: 1 | G12: ='Precios Bolsa España 2024'!O4 -> 0.068746795 | H12: ='Precios Bolsa España 2024'!P4 -> 0.0072543014 | I12: ='Precios Bolsa España 2024'!Q4 -> 0.0025313699 | J12: =(G12)*1000 -> 68.746795 | K12: =Industria!T3 -> 31.307452 | L12: =Industria!U3 -> 0.13538863 | M12: =Industria!V3 -> 27.875151 | N12: ='24h-ESPAÑA'!R12/'24h-ESPAÑA'!K12-'24h-ESPAÑA'!J12/1000 -> 0.020202155 | O12: =AVERAGE(N12:N19) -> 0.022820505 | P12: =COS(ATAN(M12/K12)) -> 0.74686056 | Q12: =-K12*(AJ14+O12) -> -2.8667388 | R12: =K12*(C12+(G12+H12+I12+D12+$Y$5+$Y$4)*(1+E12)+$Y$3)*(1+$Y$6) -> 2.784765 | AI12: Gams Syntax
A13: 2 | B13: P6 | C13: =$G$9 -> 0.001443 | D13: =$H$9 -> 0 | E13: =$I$9 -> 0.077 | F13: 2 | G13: ='Precios Bolsa España 2024'!O5 -> 0.064382932 | H13: ='Precios Bolsa España 2024'!P5 -> 0.0081311507 | I13: ='Precios Bolsa España 2024'!Q5 -> 0.0027362192 | J13: =(G13)*1000 -> 64.382932 | K13: =Industria!T4 -> 20.898959 | L13: =Industria!U4 -> 0.090377249 | M13: =Industria!V4 -> 22.371534 | N13: ='24h-ESPAÑA'!R13/'24h-ESPAÑA'!K13-'24h-ESPAÑA'!J13/1000 -> 0.020978104 | O13: =$O$12 -> 0.022820505 | P13: =COS(ATAN(M13/K13)) -> 0.68264743 | Q13: =-K13*(AJ15+O13) -> -1.822461 | R13: =K13*(C13+(G13+H13+I13+D13+$Y$5+$Y$4)*(1+E13)+$Y$3)*(1+$Y$6) -> 1.7839568 | AJ13: lambda | AK13: psi | AL13: Ppvu | AM13: Plu | AN13: Pbmax
A14: 3 | B14: P6 | C14: =$G$9 -> 0.001443 | D14: =$H$9 -> 0 | E14: =$I$9 -> 0.077 | F14: 3 | G14: ='Precios Bolsa España 2024'!O6 -> 0.062238411 | H14: ='Precios Bolsa España 2024'!P6 -> 0.0092259726 | I14: ='Precios Bolsa España 2024'!Q6 -> 0.002448137 | J14: =(G14)*1000 -> 62.238411 | K14: =Industria!T5 -> 17.653808 | L14: =Industria!U5 -> 0.076343641 | M14: =Industria!V5 -> 20.669616 | N14: ='24h-ESPAÑA'!R14/'24h-ESPAÑA'!K14-'24h-ESPAÑA'!J14/1000 -> 0.021660223 | O14: =$O$12 -> 0.022820505 | P14: =COS(ATAN(M14/K14)) -> 0.64945418 | Q14: =-K14*(AJ16+O14) -> -1.5016138 | R14: =K14*(C14+(G14+H14+I14+D14+$Y$5+$Y$4)*(1+E14)+$Y$3)*(1+$Y$6) -> 1.4811304 | AF14: =(AJ14+AK14)*K12 -> 2.8667388 | AI14: t1 | AJ14: =G12 -> 0.068746795 | AK14: =O12 -> 0.022820505 | AL14: =#REF! -> #REF! | AM14: =L12 -> 0.13538863 | AN14: =#REF! -> #REF!
A15: 4 | B15: P6 | C15: =$G$9 -> 0.001443 | D15: =$H$9 -> 0 | E15: =$I$9 -> 0.077 | F15: 4 | G15: ='Precios Bolsa España 2024'!O7 -> 0.060464137 | H15: ='Precios Bolsa España 2024'!P7 -> 0.0097246575 | I15: ='Precios Bolsa España 2024'!Q7 -> 0.0022396712 | J15: =(G15)*1000 -> 60.464137 | K15: =Industria!T6 -> 17.394959 | L15: =Industria!U6 -> 0.075224251 | M15: =Industria!V6 -> 20.802712 | N15: ='24h-ESPAÑA'!R15/'24h-ESPAÑA'!K15-'24h-ESPAÑA'!J15/1000 -> 0.021812195 | O15: =$O$12 -> 0.022820505 | P15: =COS(ATAN(M15/K15)) -> 0.64147549 | Q15: =-K15*(AJ17+O15) -> -1.4487329 | R15: =K15*(C15+(G15+H15+I15+D15+$Y$5+$Y$4)*(1+E15)+$Y$3)*(1+$Y$6) -> 1.4311934 | AF15: =(AJ15+AK15)*K13 -> 1.822461 | AI15: t2 | AJ15: =G13 -> 0.064382932 | AK15: =O13 -> 0.022820505 | AL15: =#REF! -> #REF! | AM15: =L13 -> 0.090377249 | AN15: =#REF! -> #REF!
A16: 5 | B16: P6 | C16: =$G$9 -> 0.001443 | D16: =$H$9 -> 0 | E16: =$I$9 -> 0.077 | F16: 5 | G16: ='Precios Bolsa España 2024'!O8 -> 0.060655534 | H16: ='Precios Bolsa España 2024'!P8 -> 0.0098196438 | I16: ='Precios Bolsa España 2024'!Q8 -> 0.0022953699 | J16: =(G16)*1000 -> 60.655534 | K16: =Industria!T7 -> 17.182986 | L16: =Industria!U7 -> 0.074307579 | M16: =Industria!V7 -> 20.762822 | N16: ='24h-ESPAÑA'!R16/'24h-ESPAÑA'!K16-'24h-ESPAÑA'!J16/1000 -> 0.021994746 | O16: =$O$12 -> 0.022820505 | P16: =COS(ATAN(M16/K16)) -> 0.63756686 | Q16: =-K16*(AJ18+O16) -> -1.4343676 | R16: =K16*(C16+(G16+H16+I16+D16+$Y$5+$Y$4)*(1+E16)+$Y$3)*(1+$Y$6) -> 1.4201786 | AF16: =(AJ16+AK16)*K14 -> 1.5016138 | AI16: t3 | AJ16: =G14 -> 0.062238411 | AK16: =O14 -> 0.022820505 | AL16: =#REF! -> #REF! | AM16: =L14 -> 0.076343641 | AN16: =#REF! -> #REF!
A17: 6 | B17: P6 | C17: =$G$9 -> 0.001443 | D17: =$H$9 -> 0 | E17: =$I$9 -> 0.077 | F17: 6 | G17: ='Precios Bolsa España 2024'!O9 -> 0.065132137 | H17: ='Precios Bolsa España 2024'!P9 -> 0.010057589 | I17: ='Precios Bolsa España 2024'!Q9 -> 0.0025469041 | J17: =(G17)*1000 -> 65.132137 | K17: =Industria!T8 -> 16.905041 | L17: =Industria!U8 -> 0.073105609 | M17: =Industria!V8 -> 20.711205 | N17: ='24h-ESPAÑA'!R17/'24h-ESPAÑA'!K17-'24h-ESPAÑA'!J17/1000 -> 0.022946841 | O17: =$O$12 -> 0.022820505 | P17: =COS(ATAN(M17/K17)) -> 0.63233013 | Q17: =-K17*(AJ19+O17) -> -1.486843 | R17: =K17*(C17+(G17+H17+I17+D17+$Y$5+$Y$4)*(1+E17)+$Y$3)*(1+$Y$6) -> 1.4889787 | AF17: =(AJ17+AK17)*K15 -> 1.4487329 | AI17: t4 | AJ17: =G15 -> 0.060464137 | AK17: =O15 -> 0.022820505 | AL17: =#REF! -> #REF! | AM17: =L15 -> 0.075224251 | AN17: =#REF! -> #REF!
A18: 7 | B18: P6 | C18: =$G$9 -> 0.001443 | D18: =$H$9 -> 0 | E18: =$I$9 -> 0.077 | F18: 7 | G18: ='Precios Bolsa España 2024'!O10 -> 0.073826082 | H18: ='Precios Bolsa España 2024'!P10 -> 0.0099409041 | I18: ='Precios Bolsa España 2024'!Q10 -> 0.0041280822 | J18: =(G18)*1000 -> 73.826082 | K18: =Industria!T9 -> 16.974548 | L18: =Industria!U9 -> 0.07340619 | M18: =Industria!V9 -> 20.580986 | N18: ='24h-ESPAÑA'!R18/'24h-ESPAÑA'!K18-'24h-ESPAÑA'!J18/1000 -> 0.025357643 | O18: =$O$12 -> 0.022820505 | P18: =COS(ATAN(M18/K18)) -> 0.63627665 | Q18: =-K18*(AJ20+O18) -> -1.6405321 | R18: =K18*(C18+(G18+H18+I18+D18+$Y$5+$Y$4)*(1+E18)+$Y$3)*(1+$Y$6) -> 1.6835989 | AF18: =(AJ18+AK18)*K16 -> 1.4343676 | AI18: t5 | AJ18: =G16 -> 0.060655534 | AK18: =O16 -> 0.022820505 | AL18: =#REF! -> #REF! | AM18: =L16 -> 0.074307579 | AN18: =#REF! -> #REF!
A19: 8 | B19: P6 | C19: =$G$9 -> 0.001443 | D19: =$H$9 -> 0 | E19: =$I$9 -> 0.077 | F19: 8 | G19: ='Precios Bolsa España 2024'!O11 -> 0.076148795 | H19: ='Precios Bolsa España 2024'!P11 -> 0.010411233 | I19: ='Precios Bolsa España 2024'!Q11 -> 0.0055221918 | J19: =(G19)*1000 -> 76.148795 | K19: =Industria!T10 -> 19.774932 | L19: =Industria!U10 -> 0.085516409 | M19: =Industria!V10 -> 21.413726 | N19: ='24h-ESPAÑA'!R19/'24h-ESPAÑA'!K19-'24h-ESPAÑA'!J19/1000 -> 0.027612136 | O19: =$O$12 -> 0.022820505 | P19: =COS(ATAN(M19/K19)) -> 0.67843597 | Q19: =-K19*(AJ21+O19) -> -1.9571111 | R19: =K19*(C19+(G19+H19+I19+D19+$Y$5+$Y$4)*(1+E19)+$Y$3)*(1+$Y$6) -> 2.0518653 | AF19: =(AJ19+AK19)*K17 -> 1.486843 | AI19: t6 | AJ19: =G17 -> 0.065132137 | AK19: =O17 -> 0.022820505 | AL19: =#REF! -> #REF! | AM19: =L17 -> 0.073105609 | AN19: =#REF! -> #REF!
A20: 9 | B20: P5 | C20: =$G$8 -> 0.002388 | D20: =$H$8 -> 0.000113 | E20: =$I$8 -> 0.043 | F20: 9 | G20: ='Precios Bolsa España 2024'!O12 -> 0.069382712 | H20: ='Precios Bolsa España 2024'!P12 -> 0.0094291507 | I20: ='Precios Bolsa España 2024'!Q12 -> 0.0059585753 | J20: =(G20)*1000 -> 69.382712 | K20: =Industria!T11 -> 204.33975 | L20: =Industria!U11 -> 0.88366434 | M20: =Industria!V11 -> 141.48904 | N20: ='24h-ESPAÑA'!R20/'24h-ESPAÑA'!K20-'24h-ESPAÑA'!J20/1000 -> 0.024519073 | O20: =AVERAGE($N$20,$N$26:$N$29,$N$34:$N$35) -> 0.021074371 | P20: =COS(ATAN(M20/K20)) -> 0.82214877 | Q20: =-K20*(AJ22+O20) -> -18.483978 | R20: =K20*(C20+(G20+H20+I20+D20+$Y$5+$Y$4)*(1+E20)+$Y$3)*(1+$Y$6) -> 19.187868 | AF20: =(AJ20+AK20)*K18 -> 1.6405321 | AI20: t7 | AJ20: =G18 -> 0.073826082 | AK20: =O18 -> 0.022820505 | AL20: =#REF! -> #REF! | AM20: =L18 -> 0.07340619 | AN20: =#REF! -> #REF!
A21: 10 | B21: P3 | C21: =$G$6 -> 0.011795 | D21: =$H$6 -> 0.00015 | E21: =$I$6 -> 0.065 | F21: 10 | G21: ='Precios Bolsa España 2024'!O13 -> 0.056760082 | H21: ='Precios Bolsa España 2024'!P13 -> 0.0080707671 | I21: ='Precios Bolsa España 2024'!Q13 -> 0.0045372055 | J21: =(G21)*1000 -> 56.760082 | K21: =Industria!T12 -> 231.24137 | L21: =Industria!U12 -> 1 | M21: =Industria!V12 -> 95.876274 | N21: ='24h-ESPAÑA'!R21/'24h-ESPAÑA'!K21-'24h-ESPAÑA'!J21/1000 -> 0.031988348 | O21: =N21 -> 0.031988348 | P21: =COS(ATAN(M21/K21)) -> 0.92374818 | Q21: =-K21*(AJ23+O21) -> -20.522309 | R21: =K21*(C21+(G21+H21+I21+D21+$Y$5+$Y$4)*(1+E21)+$Y$3)*(1+$Y$6) -> 20.522309 | AF21: =(AJ21+AK21)*K19 -> 1.9571111 | AI21: t8 | AJ21: =G19 -> 0.076148795 | AK21: =O19 -> 0.022820505 | AL21: =#REF! -> #REF! | AM21: =L19 -> 0.085516409 | AN21: =#REF! -> #REF!
A22: 11 | B22: P4 | C22: =$G$7 -> 0.006274 | D22: =$H$7 -> 0.000113 | E22: =$I$7 -> 0.065 | F22: 11 | G22: ='Precios Bolsa España 2024'!O14 -> 0.04694937 | H22: ='Precios Bolsa España 2024'!P14 -> 0.0071172055 | I22: ='Precios Bolsa España 2024'!Q14 -> 0.0031848219 | J22: =(G22)*1000 -> 46.94937 | K22: =Industria!T13 -> 223.66726 | L22: =Industria!U13 -> 0.96724587 | M22: =Industria!V13 -> 91.472521 | N22: ='24h-ESPAÑA'!R22/'24h-ESPAÑA'!K22-'24h-ESPAÑA'!J22/1000 -> 0.023057446 | O22: =AVERAGE($N$22:$N$25) -> 0.022190647 | P22: =COS(ATAN(M22/K22)) -> 0.92558715 | Q22: =-K22*(AJ24+O22) -> -15.464358 | R22: =K22*(C22+(G22+H22+I22+D22+$Y$5+$Y$4)*(1+E22)+$Y$3)*(1+$Y$6) -> 15.658233 | AF22: =(AJ22+AK22)*K20 -> 18.483978 | AI22: t9 | AJ22: =G20 -> 0.069382712 | AK22: =O20 -> 0.021074371 | AL22: =#REF! -> #REF! | AM22: =L20 -> 0.88366434 | AN22: =#REF! -> #REF!
A23: 12 | B23: P4 | C23: =$G$7 -> 0.006274 | D23: =$H$7 -> 0.000113 | E23: =$I$7 -> 0.065 | F23: 12 | G23: ='Precios Bolsa España 2024'!O15 -> 0.04184674 | H23: ='Precios Bolsa España 2024'!P15 -> 0.0070680548 | I23: ='Precios Bolsa España 2024'!Q15 -> 0.0025854521 | J23: =(G23)*1000 -> 41.84674 | K23: =Industria!T14 -> 223.47403 | L23: =Industria!U14 -> 0.96641024 | M23: =Industria!V14 -> 126.74858 | N23: ='24h-ESPAÑA'!R23/'24h-ESPAÑA'!K23-'24h-ESPAÑA'!J23/1000 -> 0.021943226 | O23: =AVERAGE($N$22:$N$25) -> 0.022190647 | P23: =COS(ATAN(M23/K23)) -> 0.86983297 | Q23: =-K23*(AJ25+O23) -> -14.310693 | R23: =K23*(C23+(G23+H23+I23+D23+$Y$5+$Y$4)*(1+E23)+$Y$3)*(1+$Y$6) -> 14.2554 | AF23: =(AJ23+AK23)*K21 -> 20.522309 | AI23: t10 | AJ23: =G21 -> 0.056760082 | AK23: =O21 -> 0.031988348 | AL23: =#REF! -> #REF! | AM23: =L21 -> 1 | AN23: =#REF! -> #REF!
A24: 13 | B24: P4 | C24: =$G$7 -> 0.006274 | D24: =$H$7 -> 0.000113 | E24: =$I$7 -> 0.065 | F24: 13 | G24: ='Precios Bolsa España 2024'!O16 -> 0.039593726 | H24: ='Precios Bolsa España 2024'!P16 -> 0.0070899726 | I24: ='Precios Bolsa España 2024'!Q16 -> 0.002544274 | J24: =(G24)*1000 -> 39.593726 | K24: =Industria!T15 -> 28.407397 | L24: =Industria!U15 -> 0.12284738 | M24: =Industria!V15 -> 2.0675616 | N24: ='24h-ESPAÑA'!R24/'24h-ESPAÑA'!K24-'24h-ESPAÑA'!J24/1000 -> 0.021739968 | O24: =AVERAGE($N$22:$N$25) -> 0.022190647 | P24: =COS(ATAN(M24/K24)) -> 0.99736183 | Q24: =-K24*(AJ26+O24) -> -1.7551332 | R24: =K24*(C24+(G24+H24+I24+D24+$Y$5+$Y$4)*(1+E24)+$Y$3)*(1+$Y$6) -> 1.7423306 | AF24: =(AJ24+AK24)*K22 -> 15.464358 | AI24: t11 | AJ24: =G22 -> 0.04694937 | AK24: =O22 -> 0.022190647 | AL24: =#REF! -> #REF! | AM24: =L22 -> 0.96724587 | AN24: =#REF! -> #REF!
A25: 14 | B25: P4 | C25: =$G$7 -> 0.006274 | D25: =$H$7 -> 0.000113 | E25: =$I$7 -> 0.065 | F25: 14 | G25: ='Precios Bolsa España 2024'!O17 -> 0.037885123 | H25: ='Precios Bolsa España 2024'!P17 -> 0.0075278082 | I25: ='Precios Bolsa España 2024'!Q17 -> 0.0024952877 | J25: =(G25)*1000 -> 37.885123 | K25: =Industria!T16 -> 206.30877 | L25: =Industria!U16 -> 0.89217932 | M25: =Industria!V16 -> 84.879041 | N25: ='24h-ESPAÑA'!R25/'24h-ESPAÑA'!K25-'24h-ESPAÑA'!J25/1000 -> 0.02202195 | O25: =AVERAGE($N$22:$N$25) -> 0.022190647 | P25: =COS(ATAN(M25/K25)) -> 0.9247911 | Q25: =-K25*(AJ27+O25) -> -12.394158 | R25: =K25*(C25+(G25+H25+I25+D25+$Y$5+$Y$4)*(1+E25)+$Y$3)*(1+$Y$6) -> 12.359354 | AF25: =(AJ25+AK25)*K23 -> 14.310693 | AI25: t12 | AJ25: =G23 -> 0.04184674 | AK25: =O23 -> 0.022190647 | AL25: =#REF! -> #REF! | AM25: =L23 -> 0.96641024 | AN25: =#REF! -> #REF!
A26: 15 | B26: P5 | C26: =$G$8 -> 0.002388 | D26: =$H$8 -> 0.000113 | E26: =$I$8 -> 0.043 | F26: 15 | G26: ='Precios Bolsa España 2024'!O18 -> 0.036840932 | H26: ='Precios Bolsa España 2024'!P18 -> 0.0075245753 | I26: ='Precios Bolsa España 2024'!Q18 -> 0.0024581096 | J26: =(G26)*1000 -> 36.840932 | K26: =Industria!T17 -> 224.04178 | L26: =Industria!U17 -> 0.96886548 | M26: =Industria!V17 -> 91.807945 | N26: ='24h-ESPAÑA'!R26/'24h-ESPAÑA'!K26-'24h-ESPAÑA'!J26/1000 -> 0.016888641 | O26: =AVERAGE($N$20,$N$26:$N$29,$N$34:$N$35) -> 0.021074371 | P26: =COS(ATAN(M26/K26)) -> 0.92532319 | Q26: =-K26*(AJ28+O26) -> -12.975448 | R26: =K26*(C26+(G26+H26+I26+D26+$Y$5+$Y$4)*(1+E26)+$Y$3)*(1+$Y$6) -> 12.037669 | AF26: =(AJ26+AK26)*K24 -> 1.7551332 | AI26: t13 | AJ26: =G24 -> 0.039593726 | AK26: =O24 -> 0.022190647 | AL26: =#REF! -> #REF! | AM26: =L24 -> 0.12284738 | AN26: =#REF! -> #REF!
A27: 16 | B27: P5 | C27: =$G$8 -> 0.002388 | D27: =$H$8 -> 0.000113 | E27: =$I$8 -> 0.043 | F27: 16 | G27: ='Precios Bolsa España 2024'!O19 -> 0.038253699 | H27: ='Precios Bolsa España 2024'!P19 -> 0.0076432329 | I27: ='Precios Bolsa España 2024'!Q19 -> 0.0030550685 | J27: =(G27)*1000 -> 38.253699 | K27: =Industria!T18 -> 221.80392 | L27: =Industria!U18 -> 0.95918787 | M27: =Industria!V18 -> 91.090274 | N27: ='24h-ESPAÑA'!R27/'24h-ESPAÑA'!K27-'24h-ESPAÑA'!J27/1000 -> 0.017729076 | O27: =AVERAGE($N$20,$N$26:$N$29,$N$34:$N$35) -> 0.021074371 | P27: =COS(ATAN(M27/K27)) -> 0.9250312 | Q27: =-K27*(AJ29+O27) -> -13.159198 | R27: =K27*(C27+(G27+H27+I27+D27+$Y$5+$Y$4)*(1+E27)+$Y$3)*(1+$Y$6) -> 12.417199 | AF27: =(AJ27+AK27)*K25 -> 12.394158 | AI27: t14 | AJ27: =G25 -> 0.037885123 | AK27: =O25 -> 0.022190647 | AL27: =#REF! -> #REF! | AM27: =L25 -> 0.89217932 | AN27: =#REF! -> #REF!
A28: 17 | B28: P5 | C28: =$G$8 -> 0.002388 | D28: =$H$8 -> 0.000113 | E28: =$I$8 -> 0.043 | F28: 17 | G28: ='Precios Bolsa España 2024'!O20 -> 0.046423205 | H28: ='Precios Bolsa España 2024'!P20 -> 0.0078807123 | I28: ='Precios Bolsa España 2024'!Q20 -> 0.0042375616 | J28: =(G28)*1000 -> 46.423205 | K28: =Industria!T19 -> 219.05268 | L28: =Industria!U19 -> 0.94729021 | M28: =Industria!V19 -> 89.880685 | N28: ='24h-ESPAÑA'!R28/'24h-ESPAÑA'!K28-'24h-ESPAÑA'!J28/1000 -> 0.019711424 | O28: =AVERAGE($N$20,$N$26:$N$29,$N$34:$N$35) -> 0.021074371 | P28: =COS(ATAN(M28/K28)) -> 0.92514946 | Q28: =-K28*(AJ30+O28) -> -14.785525 | R28: =K28*(C28+(G28+H28+I28+D28+$Y$5+$Y$4)*(1+E28)+$Y$3)*(1+$Y$6) -> 14.486968 | AF28: =(AJ28+AK28)*K26 -> 12.975448 | AI28: t15 | AJ28: =G26 -> 0.036840932 | AK28: =O26 -> 0.021074371 | AL28: =#REF! -> #REF! | AM28: =L26 -> 0.96886548 | AN28: =#REF! -> #REF!
A29: 18 | B29: P5 | C29: =$G$8 -> 0.002388 | D29: =$H$8 -> 0.000113 | E29: =$I$8 -> 0.043 | F29: 18 | G29: ='Precios Bolsa España 2024'!O21 -> 0.059484767 | H29: ='Precios Bolsa España 2024'!P21 -> 0.008736274 | I29: ='Precios Bolsa España 2024'!Q21 -> 0.0056707671 | J29: =(G29)*1000 -> 59.484767 | K29: =Industria!T20 -> 149.68 | L29: =Industria!U20 -> 0.64728902 | M29: =Industria!V20 -> 43.575068 | N29: ='24h-ESPAÑA'!R29/'24h-ESPAÑA'!K29-'24h-ESPAÑA'!J29/1000 -> 0.022900411 | O29: =AVERAGE($N$20,$N$26:$N$29,$N$34:$N$35) -> 0.021074371 | P29: =COS(ATAN(M29/K29)) -> 0.96014057 | Q29: =-K29*(AJ31+O29) -> -12.058092 | R29: =K29*(C29+(G29+H29+I29+D29+$Y$5+$Y$4)*(1+E29)+$Y$3)*(1+$Y$6) -> 12.331413 | AF29: =(AJ29+AK29)*K27 -> 13.159198 | AI29: t16 | AJ29: =G27 -> 0.038253699 | AK29: =O27 -> 0.021074371 | AL29: =#REF! -> #REF! | AM29: =L27 -> 0.95918787 | AN29: =#REF! -> #REF!
A30: 19 | B30: P1 | C30: =$G$4 -> 0.044778 | D30: =$H$4 -> 0.00049 | E30: =$I$4 -> 0.067 | F30: 19 | G30: ='Precios Bolsa España 2024'!O22 -> 0.076155178 | H30: ='Precios Bolsa España 2024'!P22 -> 0.010724877 | I30: ='Precios Bolsa España 2024'!Q22 -> 0.0059901918 | J30: =(G30)*1000 -> 76.155178 | K30: =Industria!T21 -> 145.21233 | L30: =Industria!U21 -> 0.62796864 | M30: =Industria!V21 -> 64.533123 | N30: ='24h-ESPAÑA'!R30/'24h-ESPAÑA'!K30-'24h-ESPAÑA'!J30/1000 -> 0.072034485 | O30: =N30 -> 0.072034485 | P30: =COS(ATAN(M30/K30)) -> 0.91382484 | Q30: =-K30*(AJ32+O30) -> -21.518966 | R30: =K30*(C30+(G30+H30+I30+D30+$Y$5+$Y$4)*(1+E30)+$Y$3)*(1+$Y$6) -> 21.518966 | AF30: =(AJ30+AK30)*K28 -> 14.785525 | AI30: t17 | AJ30: =G28 -> 0.046423205 | AK30: =O28 -> 0.021074371 | AL30: =#REF! -> #REF! | AM30: =L28 -> 0.94729021 | AN30: =#REF! -> #REF!
A31: 20 | B31: P2 | C31: =$G$5 -> 0.024986 | D31: =$H$7 -> 0.000113 | E31: =$I$7 -> 0.065 | F31: 20 | G31: ='Precios Bolsa España 2024'!O23 -> 0.090286438 | H31: ='Precios Bolsa España 2024'!P23 -> 0.012580219 | I31: ='Precios Bolsa España 2024'!Q23 -> 0.0045248767 | J31: =(G31)*1000 -> 90.286438 | K31: =Industria!T22 -> 152.46567 | L31: =Industria!U22 -> 0.65933562 | M31: =Industria!V22 -> 54.343753 | N31: ='24h-ESPAÑA'!R31/'24h-ESPAÑA'!K31-'24h-ESPAÑA'!J31/1000 -> 0.052913292 | O31: =AVERAGE($N$31:$N$33) -> 0.051218244 | P31: =COS(ATAN(M31/K31)) -> 0.9419536 | Q31: =-K31*(AJ33+O31) -> -21.574606 | R31: =K31*(C31+(G31+H31+I31+D31+$Y$5+$Y$4)*(1+E31)+$Y$3)*(1+$Y$6) -> 21.833043 | AF31: =(AJ31+AK31)*K29 -> 12.058092 | AI31: t18 | AJ31: =G29 -> 0.059484767 | AK31: =O29 -> 0.021074371 | AL31: =#REF! -> #REF! | AM31: =L29 -> 0.64728902 | AN31: =#REF! -> #REF!
A32: 21 | B32: P2 | C32: =$G$5 -> 0.024986 | D32: =$H$7 -> 0.000113 | E32: =$I$7 -> 0.065 | F32: 21 | G32: ='Precios Bolsa España 2024'!O24 -> 0.099023507 | H32: ='Precios Bolsa España 2024'!P24 -> 0.011415753 | I32: ='Precios Bolsa España 2024'!Q24 -> 0.0031109041 | J32: =(G32)*1000 -> 99.023507 | K32: =Industria!T23 -> 134.48767 | L32: =Industria!U23 -> 0.58159001 | M32: =Industria!V23 -> 40.603753 | N32: ='24h-ESPAÑA'!R32/'24h-ESPAÑA'!K32-'24h-ESPAÑA'!J32/1000 -> 0.050833548 | O32: =AVERAGE($N$31:$N$33) -> 0.051218244 | P32: =COS(ATAN(M32/K32)) -> 0.95732042 | Q32: =-K32*(AJ34+O32) -> -20.205663 | R32: =K32*(C32+(G32+H32+I32+D32+$Y$5+$Y$4)*(1+E32)+$Y$3)*(1+$Y$6) -> 20.153926 | AF32: =(AJ32+AK32)*K30 -> 21.518966 | AI32: t19 | AJ32: =G30 -> 0.076155178 | AK32: =O30 -> 0.072034485 | AL32: =#REF! -> #REF! | AM32: =L30 -> 0.62796864 | AN32: =#REF! -> #REF!
A33: 22 | B33: P2 | C33: =$G$5 -> 0.024986 | D33: =$H$7 -> 0.000113 | E33: =$I$7 -> 0.065 | F33: 22 | G33: ='Precios Bolsa España 2024'!O25 -> 0.09037211 | H33: ='Precios Bolsa España 2024'!P25 -> 0.01131526 | I33: ='Precios Bolsa España 2024'!Q25 -> 0.0030031507 | J33: =(G33)*1000 -> 90.37211 | K33: =Industria!T24 -> 41.442603 | L33: =Industria!U24 -> 0.17921794 | M33: =Industria!V24 -> 3.4742192 | N33: ='24h-ESPAÑA'!R33/'24h-ESPAÑA'!K33-'24h-ESPAÑA'!J33/1000 -> 0.049907892 | O33: =AVERAGE($N$31:$N$33) -> 0.051218244 | P33: =COS(ATAN(M33/K33)) -> 0.99650451 | Q33: =-K33*(AJ35+O33) -> -5.8678728 | R33: =K33*(C33+(G33+H33+I33+D33+$Y$5+$Y$4)*(1+E33)+$Y$3)*(1+$Y$6) -> 5.8135684 | AF33: =(AJ33+AK33)*K31 -> 21.574606 | AI33: t20 | AJ33: =G31 -> 0.090286438 | AK33: =O31 -> 0.051218244 | AL33: =#REF! -> #REF! | AM33: =L31 -> 0.65933562 | AN33: =#REF! -> #REF!
A34: 23 | B34: P5 | C34: =$G$8 -> 0.002388 | D34: =$H$8 -> 0.000113 | E34: =$I$8 -> 0.043 | F34: 23 | G34: ='Precios Bolsa España 2024'!O26 -> 0.081188795 | H34: ='Precios Bolsa España 2024'!P26 -> 0.012232575 | I34: ='Precios Bolsa España 2024'!Q26 -> 0.0028552603 | J34: =(G34)*1000 -> 81.188795 | K34: =Industria!T25 -> 33.502959 | L34: =Industria!U25 -> 0.14488307 | M34: =Industria!V25 -> 26.909671 | N34: ='24h-ESPAÑA'!R34/'24h-ESPAÑA'!K34-'24h-ESPAÑA'!J34/1000 -> 0.024893963 | O34: =AVERAGE($N$20,$N$26:$N$29,$N$34:$N$35) -> 0.021074371 | P34: =COS(ATAN(M34/K34)) -> 0.77964924 | Q34: =-K34*(AJ36+O34) -> -3.4261186 | R34: =K34*(C34+(G34+H34+I34+D34+$Y$5+$Y$4)*(1+E34)+$Y$3)*(1+$Y$6) -> 3.5540863 | AF34: =(AJ34+AK34)*K32 -> 20.205663 | AI34: t21 | AJ34: =G32 -> 0.099023507 | AK34: =O32 -> 0.051218244 | AL34: =#REF! -> #REF! | AM34: =L32 -> 0.58159001 | AN34: =#REF! -> #REF!
A35: 24 | B35: P5 | C35: =$G$8 -> 0.002388 | D35: =$H$8 -> 0.000113 | E35: =$I$8 -> 0.043 | F35: 24 | G35: ='Precios Bolsa España 2024'!O27 -> 0.074767233 | H35: ='Precios Bolsa España 2024'!P27 -> 0.0088425753 | I35: ='Precios Bolsa España 2024'!Q27 -> 0.0028075068 | J35: =(G35)*1000 -> 74.767233 | K35: =Industria!T26 -> 31.920795 | L35: =Industria!U26 -> 0.13804102 | M35: =Industria!V26 -> 27.457562 | N35: ='24h-ESPAÑA'!R35/'24h-ESPAÑA'!K35-'24h-ESPAÑA'!J35/1000 -> 0.02087801 | O35: =O27 -> 0.021074371 | P35: =COS(ATAN(M35/K35)) -> 0.75811852 | Q35: =-K35*(AJ37+O35) -> -3.0593402 | R35: =K35*(C35+(G35+H35+I35+D35+$Y$5+$Y$4)*(1+E35)+$Y$3)*(1+$Y$6) -> 3.0530722 | AF35: =(AJ35+AK35)*K33 -> 5.8678728 | AI35: t22 | AJ35: =G33 -> 0.09037211 | AK35: =O33 -> 0.051218244 | AL35: =#REF! -> #REF! | AM35: =L33 -> 0.17921794 | AN35: =#REF! -> #REF!
G36: =SUM(G12:G35)/24 -> 0.063200352 | H36: =SUM(H12:H35)/24 -> 0.0091568527 | I36: =SUM(I12:I35)/24 -> 0.00347779 | J36: =SUM(J12:J35)/24 -> 63.200352 | K36: =SUM(K12:K35) -> 2629.1417 | M36: =SUM(M12:M35) -> 1251.3968 | P36: =COS(ATAN(M36/K36)) -> 0.90293721 | Q36: =SUM(Q12:Q35) -> -225.71986 | R36: =SUM(R12:R35) -> 225.05107 | AF36: =(AJ36+AK36)*K34 -> 3.4261186 | AI36: t23 | AJ36: =G34 -> 0.081188795 | AK36: =O34 -> 0.021074371 | AL36: =#REF! -> #REF! | AM36: =L34 -> 0.14488307 | AN36: =#REF! -> #REF!
G37: Eur/kWh | H37: Eur/kWh | I37: Eur/kWh | J37: Eur/MWh | K37: kWh/dia | M37: kVArh/dia | Q37: Eur/dia | R37: Eur/dia | AF37: =(AJ37+AK37)*K35 -> 3.0593402 | AI37: t24 | AJ37: =G35 -> 0.074767233 | AK37: =O35 -> 0.021074371 | AL37: =#REF! -> #REF! | AM37: =L35 -> 0.13804102 | AN37: =#REF! -> #REF!
K38: =K36*365 -> 959636.71 | Q38: =Q36*365 -> -82387.749 | R38: =R36*365 -> 82143.642 | AF38: =SUM(AF14:AF37)*365 -> 82387.749
K39: kWh/año | Q39: kWh/año | R39: kWh/año
S40: Reactiva P1 | W40: Tarifa 6.1 TD | AE40: Segmento tarifario | AF40: Término de potencia de los cargos (€/kW año) | AM40: Grupo tarifario | AN40: Término de potencia del peaje de transporte y distribución (€/kW año) | AU40: Tarifa de acceso | AW40: Término de potencia (€/kW año)
O41: psi | S41: Ea | T41: =SUM(K21:K25,K30:K33) -> 1386.7071 | V41: kW | W41: Energia Activa | X41: =Q38 -> -82387.749 | Y41: EUR/AÑO | Z41: =X41*1.1 -> -90626.524 | AA41: USD/año | AF41: Periodo 1 | AG41: Periodo 2 | AH41: Periodo 3 | AI41: Periodo 4 | AJ41: Periodo 5 | AK41: Periodo 6 | AN41: Periodo 1 | AO41: Periodo 2 | AP41: Periodo 3 | AQ41: Periodo 4 | AR41: Periodo 5 | AS41: Periodo 6 | AW41: Periodo 1 | AX41: Periodo 2 | AY41: Periodo 3 | AZ41: Periodo 4 | BA41: Periodo 5 | BB41: Periodo 6
J42: fp>.95 | K42: ='Tarifas España 2024'!AE8 -> 0 | L42: Eur/kVARh | N42: p1 | O42: =O30 -> 0.072034485 | S42: Er | T42: =SUM(M21:M25,M30:M33) -> 563.99882 | V42: kVArh | W42: Termino Potencia | X42: =E10 -> -31713.889 | Y42: EUR/AÑO | Z42: =X42*1.1 -> -34885.278 | AA42: USD/año | AE42: 2.0 TD | AF42: ='Tarifas España 2024'!AD42 -> 3.971618 | AG42: ='Tarifas España 2024'!AE42 -> 0.255423 | AH42: ='Tarifas España 2024'!AF42 -> 0 | AI42: ='Tarifas España 2024'!AG42 -> 0 | AJ42: ='Tarifas España 2024'!AH42 -> 0 | AK42: ='Tarifas España 2024'!AI42 -> 0 | AM42: 2.0 TD | AN42: ='Tarifas España 2024'!AL42 -> 22.958932 | AO42: ='Tarifas España 2024'!AM42 -> 0.442165 | AP42: ='Tarifas España 2024'!AN42 -> 0 | AQ42: ='Tarifas España 2024'!AO42 -> 0 | AR42: ='Tarifas España 2024'!AP42 -> 0 | AS42: ='Tarifas España 2024'!AQ42 -> 0 | AT42: 1 | AU42: 2.0 TD | AV42: Baja tensión < 15 kW | AW42: ='Tarifas España 2024'!AU42 -> 26.93055 | AX42: ='Tarifas España 2024'!AV42 -> 0.697588 | AY42: ='Tarifas España 2024'!AW42 -> 0 | AZ42: ='Tarifas España 2024'!AX42 -> 0 | BA42: ='Tarifas España 2024'!AY42 -> 0 | BB42: ='Tarifas España 2024'!AZ42 -> 0
J43: .95<fp<.8 | K43: ='Tarifas España 2024'!AE9 -> 0.041554 | L43: Eur/kVARh | N43: p2 | O43: =O31 -> 0.051218244 | S43: fp | T43: =T41/SQRT(T41^2+T42^2) -> 0.92631532 | W43: Total Energia+Pot | X43: =X42+X41 -> -114101.64 | Y43: EUR/AÑO | Z43: =X43*1.1 -> -125511.8 | AA43: USD/año | AE43: 3.0 TD | AF43: ='Tarifas España 2024'!AD43 -> 4.935064 | AG43: ='Tarifas España 2024'!AE43 -> 2.469687 | AH43: ='Tarifas España 2024'!AF43 -> 1.794284 | AI43: ='Tarifas España 2024'!AG43 -> 1.794284 | AJ43: ='Tarifas España 2024'!AH43 -> 1.794284 | AK43: ='Tarifas España 2024'!AI43 -> 0.822511 | AM43: 3.0 TD | AN43: ='Tarifas España 2024'!AL43 -> 14.723431 | AO43: ='Tarifas España 2024'!AM43 -> 7.781964 | AP43: ='Tarifas España 2024'!AN43 -> 2.468252 | AQ43: ='Tarifas España 2024'!AO43 -> 1.887267 | AR43: ='Tarifas España 2024'!AP43 -> 0.533883 | AS43: ='Tarifas España 2024'!AQ43 -> 0.533883 | AT43: 2 | AU43: 3.0 TD | AV43: Baja tensión > 15 kW | AW43: ='Tarifas España 2024'!AU43 -> 19.658495 | AX43: ='Tarifas España 2024'!AV43 -> 10.251651 | AY43: ='Tarifas España 2024'!AW43 -> 4.262536 | AZ43: ='Tarifas España 2024'!AX43 -> 3.681551 | BA43: ='Tarifas España 2024'!AY43 -> 2.328167 | BB43: ='Tarifas España 2024'!AZ43 -> 1.356394
J44: fp<.8 | K44: ='Tarifas España 2024'!AE10 -> 0.062332 | L44: Eur/kVARh | N44: p3 | O44: =O21 -> 0.031988348 | S44: Exceso de Q | T44: =T42-SQRT((T41/0.95)^2-T41^2) -> 108.21024 | V44: kVArh | W44: Pago por Reactiva | X44: =-T52*365 -> -3178.4351 | Y44: EUR/AÑO | Z44: =X44*1.1 -> -3496.2786 | AA44: USD/año | AE44: 6.1 TD | AF44: ='Tarifas España 2024'!AD44 -> 5.122811 | AG44: ='Tarifas España 2024'!AE44 -> 2.563728 | AH44: ='Tarifas España 2024'!AF44 -> 1.86284 | AI44: ='Tarifas España 2024'!AG44 -> 1.86284 | AJ44: ='Tarifas España 2024'!AH44 -> 1.86284 | AK44: ='Tarifas España 2024'!AI44 -> 0.853802 | AM44: 6.1 TD | AN44: ='Tarifas España 2024'!AL44 -> 23.669055 | AO44: ='Tarifas España 2024'!AM44 -> 12.513915 | AP44: ='Tarifas España 2024'!AN44 -> 4.69633 | AQ44: ='Tarifas España 2024'!AO44 -> 3.309245 | AR44: ='Tarifas España 2024'!AP44 -> 0.069965 | AS44: ='Tarifas España 2024'!AQ44 -> 0.062286 | AT44: 3 | AU44: 6.1 TD | AV44: 1 kV > U > 30 kV | AW44: ='Tarifas España 2024'!AU44 -> 28.791866 | AX44: ='Tarifas España 2024'!AV44 -> 15.077643 | AY44: ='Tarifas España 2024'!AW44 -> 6.55917 | AZ44: ='Tarifas España 2024'!AX44 -> 5.172085 | BA44: ='Tarifas España 2024'!AY44 -> 1.932805 | BB44: ='Tarifas España 2024'!AZ44 -> 0.916088
N45: p4 | O45: =O24 -> 0.022190647 | S45: Pago R P1 | T45: =T44*K43 -> 4.4965684 | V45: Euro/dia | Z45: =X45*1.1 -> 0 | AA45: USD/año | AE45: 6.2 TD | AF45: ='Tarifas España 2024'!AD45 -> 3.008289 | AG45: ='Tarifas España 2024'!AE45 -> 1.505746 | AH45: ='Tarifas España 2024'!AF45 -> 1.093923 | AI45: ='Tarifas España 2024'!AG45 -> 1.093923 | AJ45: ='Tarifas España 2024'!AH45 -> 1.093923 | AK45: ='Tarifas España 2024'!AI45 -> 0.501382 | AM45: 6.2 TD | AN45: ='Tarifas España 2024'!AL45 -> 16.620368 | AO45: ='Tarifas España 2024'!AM45 -> 9.426053 | AP45: ='Tarifas España 2024'!AN45 -> 2.481516 | AQ45: ='Tarifas España 2024'!AO45 -> 1.512028 | AR45: ='Tarifas España 2024'!AP45 -> 0.059278 | AS45: ='Tarifas España 2024'!AQ45 -> 0.052654 | AT45: 4 | AU45: 6.2 TD | AV45: 30 kV > U > 72 kV | AW45: ='Tarifas España 2024'!AU45 -> 19.628657 | AX45: ='Tarifas España 2024'!AV45 -> 10.931799 | AY45: ='Tarifas España 2024'!AW45 -> 3.575439 | AZ45: ='Tarifas España 2024'!AX45 -> 2.605951 | BA45: ='Tarifas España 2024'!AY45 -> 1.153201 | BB45: ='Tarifas España 2024'!AZ45 -> 0.554036
N46: p5 | O46: =O20 -> 0.021074371 | S46: Reactiva P2 | W46: Factura Anual | X46: =X44+X43 -> -117280.07 | Y46: EUR/AÑO | Z46: =X46*1.1 -> -129008.08 | AA46: USD/año | AE46: 6.3 TD | AF46: ='Tarifas España 2024'!AD46 -> 2.408681 | AG46: ='Tarifas España 2024'!AE46 -> 1.205367 | AH46: ='Tarifas España 2024'!AF46 -> 0.875748 | AI46: ='Tarifas España 2024'!AG46 -> 0.875748 | AJ46: ='Tarifas España 2024'!AH46 -> 0.875748 | AK46: ='Tarifas España 2024'!AI46 -> 0.401447 | AM46: 6.3 TD | AN46: ='Tarifas España 2024'!AL46 -> 10.791377 | AO46: ='Tarifas España 2024'!AM46 -> 6.502236 | AP46: ='Tarifas España 2024'!AN46 -> 2.118318 | AQ46: ='Tarifas España 2024'!AO46 -> 1.380541 | AR46: ='Tarifas España 2024'!AP46 -> 0.045332 | AS46: ='Tarifas España 2024'!AQ46 -> 0.039905 | AT46: 5 | AU46: 6.3 TD | AV46: 72 kV > U > 145 kV | AW46: ='Tarifas España 2024'!AU46 -> 13.200058 | AX46: ='Tarifas España 2024'!AV46 -> 7.707603 | AY46: ='Tarifas España 2024'!AW46 -> 2.994066 | AZ46: ='Tarifas España 2024'!AX46 -> 2.256289 | BA46: ='Tarifas España 2024'!AY46 -> 0.92108 | BB46: ='Tarifas España 2024'!AZ46 -> 0.441352
N47: p6 | O47: =O19 -> 0.022820505 | S47: Ea | T47: =SUM(K21,K26:K29,K34:K35) -> 1111.2435 | V47: kW | X47: =X46*1.1 -> -129008.08 | Y47: USD/kWh | AA47: POSITIVO significa saldo a favor | AE47: 6.4 TD | AF47: ='Tarifas España 2024'!AD47 -> 1.178247 | AG47: ='Tarifas España 2024'!AE47 -> 0.589615 | AH47: ='Tarifas España 2024'!AF47 -> 0.428453 | AI47: ='Tarifas España 2024'!AG47 -> 0.428453 | AJ47: ='Tarifas España 2024'!AH47 -> 0.428453 | AK47: ='Tarifas España 2024'!AI47 -> 0.196374 | AM47: 6.4 TD | AN47: ='Tarifas España 2024'!AL47 -> 6.590215 | AO47: ='Tarifas España 2024'!AM47 -> 3.93998 | AP47: ='Tarifas España 2024'!AN47 -> 0.956817 | AQ47: ='Tarifas España 2024'!AO47 -> 0.665081 | AR47: ='Tarifas España 2024'!AP47 -> 0.019779 | AS47: ='Tarifas España 2024'!AQ47 -> 0.013181 | AT47: 6 | AU47: 6.4 TD | AV47: U > 145 kV | AW47: ='Tarifas España 2024'!AU47 -> 7.768462 | AX47: ='Tarifas España 2024'!AV47 -> 4.529595 | AY47: ='Tarifas España 2024'!AW47 -> 1.38527 | AZ47: ='Tarifas España 2024'!AX47 -> 1.093534 | BA47: ='Tarifas España 2024'!AY47 -> 0.448232 | BB47: ='Tarifas España 2024'!AZ47 -> 0.209555
S48: Er | T48: =SUM(M21,M26:M29,M34:M35) -> 466.59748 | V48: kVArh | AA48: NEGATIVO significa saldo a pagar
F49: https://www.boe.es/diario_boe/txt.php?id=BOE-A-2024-26218 | S49: fp | T49: =T47/SQRT(T47^2+T48^2) -> 0.92201907 | W49: Costo medio | X49: =X43/K38 -> -0.11890087 | Y49: EUR/kWh | AE49: Segmento tarifario | AF49: Término de energía de los cargos (€/kWh) | AM49: Grupo tarifario | AN49: Término de energía del peaje de transporte y distribución (€/kWh) | AU49: Tarifa de acceso | AW49: Término de energía (€/kWh)
S50: Exceso de Q | T50: =T48-SQRT((T47/0.95)^2-T47^2) -> 101.3494 | V50: kVArh | X50: =X49*1.1 -> -0.13079096 | Y50: USD/kWh | AF50: Periodo 1 | AG50: Periodo 2 | AH50: Periodo 3 | AI50: Periodo 4 | AJ50: Periodo 5 | AK50: Periodo 6 | AN50: Periodo 1 | AO50: Periodo 2 | AP50: Periodo 3 | AQ50: Periodo 4 | AR50: Periodo 5 | AS50: Periodo 6 | AW50: Periodo 1 | AX50: Periodo 2 | AY50: Periodo 3 | AZ50: Periodo 4 | BA50: Periodo 5 | BB50: Periodo 6
S51: Pago R P2 | T51: =T50*$K$43 -> 4.211473 | V51: Euro/dia | AE51: 2.0 TD | AF51: ='Tarifas España 2024'!AD51 -> 0.058305 | AG51: ='Tarifas España 2024'!AE51 -> 0.011661 | AH51: ='Tarifas España 2024'!AF51 -> 0.002915 | AI51: ='Tarifas España 2024'!AG51 -> 0 | AJ51: ='Tarifas España 2024'!AH51 -> 0 | AK51: ='Tarifas España 2024'!AI51 -> 0 | AM51: 2.0 TD | AN51: ='Tarifas España 2024'!AL51 -> 0.034234 | AO51: ='Tarifas España 2024'!AM51 -> 0.01654 | AP51: ='Tarifas España 2024'!AN51 -> 7.9e-05 | AQ51: ='Tarifas España 2024'!AO51 -> 0 | AR51: ='Tarifas España 2024'!AP51 -> 0 | AS51: ='Tarifas España 2024'!AQ51 -> 0 | AT51: 1 | AU51: 2.0 TD | AV51: Baja tensión < 15 kW | AW51: ='Tarifas España 2024'!AU51 -> 0.092539 | AX51: ='Tarifas España 2024'!AV51 -> 0.028201 | AY51: ='Tarifas España 2024'!AW51 -> 0.002994 | AZ51: ='Tarifas España 2024'!AX51 -> 0 | BA51: ='Tarifas España 2024'!AY51 -> 0 | BB51: ='Tarifas España 2024'!AZ51 -> 0
S52: Total R | T52: =T51+T45 -> 8.7080414 | V52: Euro/dia | AE52: 3.0 TD | AF52: ='Tarifas España 2024'!AD52 -> 0.032503 | AG52: ='Tarifas España 2024'!AE52 -> 0.024066 | AH52: ='Tarifas España 2024'!AF52 -> 0.013001 | AI52: ='Tarifas España 2024'!AG52 -> 0.006501 | AJ52: ='Tarifas España 2024'!AH52 -> 0.004167 | AK52: ='Tarifas España 2024'!AI52 -> 0.0026 | AM52: 3.0 TD | AN52: ='Tarifas España 2024'!AL52 -> 0.028528 | AO52: ='Tarifas España 2024'!AM52 -> 0.012343 | AP52: ='Tarifas España 2024'!AN52 -> 0.004673 | AQ52: ='Tarifas España 2024'!AO52 -> 0.002682 | AR52: ='Tarifas España 2024'!AP52 -> 0.000119 | AS52: ='Tarifas España 2024'!AQ52 -> 3.1e-05 | AT52: 2 | AU52: 3.0 TD | AV52: Baja tensión > 15 kW | AW52: ='Tarifas España 2024'!AU52 -> 0.061031 | AX52: ='Tarifas España 2024'!AV52 -> 0.036409 | AY52: ='Tarifas España 2024'!AW52 -> 0.017674 | AZ52: ='Tarifas España 2024'!AX52 -> 0.009183 | BA52: ='Tarifas España 2024'!AY52 -> 0.004286 | BB52: ='Tarifas España 2024'!AZ52 -> 0.002631
AE53: 6.1 TD | AF53: ='Tarifas España 2024'!AD53 -> 0.017674 | AG53: ='Tarifas España 2024'!AE53 -> 0.013092 | AH53: ='Tarifas España 2024'!AF53 -> 0.007069 | AI53: ='Tarifas España 2024'!AG53 -> 0.003535 | AJ53: ='Tarifas España 2024'!AH53 -> 0.002266 | AK53: ='Tarifas España 2024'!AI53 -> 0.001414 | AM53: 6.1 TD | AN53: ='Tarifas España 2024'!AL53 -> 0.027104 | AO53: ='Tarifas España 2024'!AM53 -> 0.011894 | AP53: ='Tarifas España 2024'!AN53 -> 0.004726 | AQ53: ='Tarifas España 2024'!AO53 -> 0.002739 | AR53: ='Tarifas España 2024'!AP53 -> 0.000122 | AS53: ='Tarifas España 2024'!AQ53 -> 2.9e-05 | AT53: 3 | AU53: 6.1 TD | AV53: 1 kV > U > 30 kV | AW53: ='Tarifas España 2024'!AU53 -> 0.044778 | AX53: ='Tarifas España 2024'!AV53 -> 0.024986 | AY53: ='Tarifas España 2024'!AW53 -> 0.011795 | AZ53: ='Tarifas España 2024'!AX53 -> 0.006274 | BA53: ='Tarifas España 2024'!AY53 -> 0.002388 | BB53: ='Tarifas España 2024'!AZ53 -> 0.001443
AE54: 6.2 TD | AF54: ='Tarifas España 2024'!AD54 -> 0.008293 | AG54: ='Tarifas España 2024'!AE54 -> 0.006142 | AH54: ='Tarifas España 2024'!AF54 -> 0.003317 | AI54: ='Tarifas España 2024'!AG54 -> 0.001659 | AJ54: ='Tarifas España 2024'!AH54 -> 0.001063 | AK54: ='Tarifas España 2024'!AI54 -> 0.000663 | AM54: 6.2 TD | AN54: ='Tarifas España 2024'!AL54 -> 0.01477 | AO54: ='Tarifas España 2024'!AM54 -> 0.00684 | AP54: ='Tarifas España 2024'!AN54 -> 0.002279 | AQ54: ='Tarifas España 2024'!AO54 -> 0.001219 | AR54: ='Tarifas España 2024'!AP54 -> 6.3e-05 | AS54: ='Tarifas España 2024'!AQ54 -> 2e-05 | AT54: 4 | AU54: 6.2 TD | AV54: 30 kV > U > 72 kV | AW54: ='Tarifas España 2024'!AU54 -> 0.023063 | AX54: ='Tarifas España 2024'!AV54 -> 0.012982 | AY54: ='Tarifas España 2024'!AW54 -> 0.005596 | AZ54: ='Tarifas España 2024'!AX54 -> 0.002878 | BA54: ='Tarifas España 2024'!AY54 -> 0.001126 | BB54: ='Tarifas España 2024'!AZ54 -> 0.000683
AE55: 6.3 TD | AF55: ='Tarifas España 2024'!AD55 -> 0.006798 | AG55: ='Tarifas España 2024'!AE55 -> 0.005035 | AH55: ='Tarifas España 2024'!AF55 -> 0.002719 | AI55: ='Tarifas España 2024'!AG55 -> 0.00136 | AJ55: ='Tarifas España 2024'!AH55 -> 0.000871 | AK55: ='Tarifas España 2024'!AI55 -> 0.000544 | AM55: 6.3 TD | AN55: ='Tarifas España 2024'!AL55 -> 0.012294 | AO55: ='Tarifas España 2024'!AM55 -> 0.00547 | AP55: ='Tarifas España 2024'!AN55 -> 0.001931 | AQ55: ='Tarifas España 2024'!AO55 -> 0.001063 | AR55: ='Tarifas España 2024'!AP55 -> 5.5e-05 | AS55: ='Tarifas España 2024'!AQ55 -> 1.5e-05 | AT55: 5 | AU55: 6.3 TD | AV55: 72 kV > U > 145 kV | AW55: ='Tarifas España 2024'!AU55 -> 0.019092 | AX55: ='Tarifas España 2024'!AV55 -> 0.010505 | AY55: ='Tarifas España 2024'!AW55 -> 0.00465 | AZ55: ='Tarifas España 2024'!AX55 -> 0.002423 | BA55: ='Tarifas España 2024'!AY55 -> 0.000926 | BB55: ='Tarifas España 2024'!AZ55 -> 0.000559
AE56: 6.4 TD | AF56: ='Tarifas España 2024'!AD56 -> 0.002582 | AG56: ='Tarifas España 2024'!AE56 -> 0.001913 | AH56: ='Tarifas España 2024'!AF56 -> 0.001033 | AI56: ='Tarifas España 2024'!AG56 -> 0.000516 | AJ56: ='Tarifas España 2024'!AH56 -> 0.000331 | AK56: ='Tarifas España 2024'!AI56 -> 0.000207 | AM56: 6.4 TD | AN56: ='Tarifas España 2024'!AL56 -> 0.007944 | AO56: ='Tarifas España 2024'!AM56 -> 0.003569 | AP56: ='Tarifas España 2024'!AN56 -> 0.001288 | AQ56: ='Tarifas España 2024'!AO56 -> 0.000681 | AR56: ='Tarifas España 2024'!AP56 -> 3.6e-05 | AS56: ='Tarifas España 2024'!AQ56 -> 4e-06 | AT56: 6 | AU56: 6.4 TD | AV56: U > 145 kV | AW56: ='Tarifas España 2024'!AU56 -> 0.010526 | AX56: ='Tarifas España 2024'!AV56 -> 0.005482 | AY56: ='Tarifas España 2024'!AW56 -> 0.002321 | AZ56: ='Tarifas España 2024'!AX56 -> 0.001197 | BA56: ='Tarifas España 2024'!AY56 -> 0.000367 | BB56: ='Tarifas España 2024'!AZ56 -> 0.000211 | BU56: 31
BU57: 28
AE58: Segmento tarifario | AF58: Pagos de capacidad (€/kWh) | BU58: 31
R59: ENERO | S59: 31 | AF59: Periodo 1 | AG59: Periodo 2 | AH59: Periodo 3 | AI59: Periodo 4 | AJ59: Periodo 5 | AK59: Periodo 6
R60: FEBRERO | S60: 28 | AE60: 2.0 TD | AF60: ='Tarifas España 2024'!AD60 -> 0.000844 | AG60: ='Tarifas España 2024'!AE60 -> 0.00014 | AH60: ='Tarifas España 2024'!AF60 -> 0 | AI60: ='Tarifas España 2024'!AG60 -> 0 | AJ60: ='Tarifas España 2024'!AH60 -> 0 | AK60: ='Tarifas España 2024'!AI60 -> 0
R61: MARZO | S61: 31 | AE61: 3.0 TD | AF61: ='Tarifas España 2024'!AD61 -> 0.001141 | AG61: ='Tarifas España 2024'!AE61 -> 0.000527 | AH61: ='Tarifas España 2024'!AF61 -> 0.000351 | AI61: ='Tarifas España 2024'!AG61 -> 0.000264 | AJ61: ='Tarifas España 2024'!AH61 -> 0.000264 | AK61: ='Tarifas España 2024'!AI61 -> 0
R62: ABRIL | S62: 30 | AE62: 6.1 TD | AF62: ='Tarifas España 2024'!AD62 -> 0.00049 | AG62: ='Tarifas España 2024'!AE62 -> 0.000225 | AH62: ='Tarifas España 2024'!AF62 -> 0.00015 | AI62: ='Tarifas España 2024'!AG62 -> 0.000113 | AJ62: ='Tarifas España 2024'!AH62 -> 0.000113 | AK62: ='Tarifas España 2024'!AI62 -> 0
R63: MAYO | S63: 31 | AE63: 6.2 TD | AF63: ='Tarifas España 2024'!AD63 -> 0.00049 | AG63: ='Tarifas España 2024'!AE63 -> 0.000225 | AH63: ='Tarifas España 2024'!AF63 -> 0.00015 | AI63: ='Tarifas España 2024'!AG63 -> 0.000113 | AJ63: ='Tarifas España 2024'!AH63 -> 0.000113 | AK63: ='Tarifas España 2024'!AI63 -> 0
R64: JUNIO | S64: 30 | AE64: 6.3 TD | AF64: ='Tarifas España 2024'!AD64 -> 0.00049 | AG64: ='Tarifas España 2024'!AE64 -> 0.000225 | AH64: ='Tarifas España 2024'!AF64 -> 0.00015 | AI64: ='Tarifas España 2024'!AG64 -> 0.000113 | AJ64: ='Tarifas España 2024'!AH64 -> 0.000113 | AK64: ='Tarifas España 2024'!AI64 -> 0
R65: JULIO | S65: 31 | AE65: 6.4 TD | AF65: ='Tarifas España 2024'!AD65 -> 0.00049 | AG65: ='Tarifas España 2024'!AE65 -> 0.000225 | AH65: ='Tarifas España 2024'!AF65 -> 0.00015 | AI65: ='Tarifas España 2024'!AG65 -> 0.000113 | AJ65: ='Tarifas España 2024'!AH65 -> 0.000113 | AK65: ='Tarifas España 2024'!AI65 -> 0
R66: AGOSTO | S66: 31
R67: SEPTIEMBRE | S67: 30 | AE67: Segmento tarifario | AF67: Coeficientes estándar de pérdidas
R68: OCTUBRE | S68: 31 | AF68: Periodo 1 | AG68: Periodo 2 | AH68: Periodo 3 | AI68: Periodo 4 | AJ68: Periodo 5 | AK68: Periodo 6
R69: NOVIEMBRE | S69: 30 | AE69: 2.0 TD | AF69: ='Tarifas España 2024'!AD69 -> 0.167 | AG69: ='Tarifas España 2024'!AE69 -> 0.163 | AH69: ='Tarifas España 2024'!AF69 -> 0.18 | AI69: ='Tarifas España 2024'!AG69 -> 0 | AJ69: ='Tarifas España 2024'!AH69 -> 0 | AK69: ='Tarifas España 2024'!AI69 -> 0
R70: DICIEMBRE | S70: 31 | AE70: 3.0 TD | AF70: ='Tarifas España 2024'!AD70 -> 0.166 | AG70: ='Tarifas España 2024'!AE70 -> 0.175 | AH70: ='Tarifas España 2024'!AF70 -> 0.165 | AI70: ='Tarifas España 2024'!AG70 -> 0.165 | AJ70: ='Tarifas España 2024'!AH70 -> 0.138 | AK70: ='Tarifas España 2024'!AI70 -> 0.18
S71: =SUM(S59:S70) -> 365 | AE71: 6.1 TD | AF71: ='Tarifas España 2024'!AD71 -> 0.067 | AG71: ='Tarifas España 2024'!AE71 -> 0.068 | AH71: ='Tarifas España 2024'!AF71 -> 0.065 | AI71: ='Tarifas España 2024'!AG71 -> 0.065 | AJ71: ='Tarifas España 2024'!AH71 -> 0.043 | AK71: ='Tarifas España 2024'!AI71 -> 0.077
AE72: 6.2 TD | AF72: ='Tarifas España 2024'!AD72 -> 0.052 | AG72: ='Tarifas España 2024'!AE72 -> 0.054 | AH72: ='Tarifas España 2024'!AF72 -> 0.049 | AI72: ='Tarifas España 2024'!AG72 -> 0.05 | AJ72: ='Tarifas España 2024'!AH72 -> 0.035 | AK72: ='Tarifas España 2024'!AI72 -> 0.054
AE73: 6.3 TD | AF73: ='Tarifas España 2024'!AD73 -> 0.042 | AG73: ='Tarifas España 2024'!AE73 -> 0.043 | AH73: ='Tarifas España 2024'!AF73 -> 0.04 | AI73: ='Tarifas España 2024'!AG73 -> 0.04 | AJ73: ='Tarifas España 2024'!AH73 -> 0.03 | AK73: ='Tarifas España 2024'!AI73 -> 0.044
AE74: 6.4 TD | AF74: ='Tarifas España 2024'!AD74 -> 0.016 | AG74: ='Tarifas España 2024'!AE74 -> 0.016 | AH74: ='Tarifas España 2024'!AF74 -> 0.016 | AI74: ='Tarifas España 2024'!AG74 -> 0.016 | AJ74: ='Tarifas España 2024'!AH74 -> 0.015 | AK74: ='Tarifas España 2024'!AI74 -> 0.017
R77: ENERO | S77: FEBRERO | T77: MARZO | V77: ABRIL | W77: MAYO | X77: JUNIO | Y77: JULIO | Z77: AGOSTO | AA77: SEPTIEMBRE | AB77: OCTUBRE | AC77: NOVIEMBRE | AD77: DICIEMBRE | AE77: 1 | AF77: 2 | AG77: 3 | AH77: 4 | AI77: 5 | AJ77: 6 | AK77: 7 | AL77: 8 | AM77: 9 | AN77: 10 | AO77: 11 | AP77: 12 | AQ77: 13 | AR77: 14 | AS77: 15 | AT77: 16 | AU77: 17 | AV77: 18 | AW77: 19 | AX77: 20 | AY77: 21 | AZ77: 22 | BA77: 23 | BB77: 24 | BC77: 25 | BD77: 26 | BE77: 27 | BF77: 28 | BG77: 29 | BH77: 30 | BI77: 31 | BJ77: 1 | BK77: 2 | BL77: 3 | BM77: 4 | BN77: 5 | BO77: 6 | BP77: 7 | BQ77: 8 | BR77: 9 | BS77: 10 | BT77: 11 | BU77: 12 | BV77: 13 | BW77: 14 | BX77: 15 | BY77: 16 | BZ77: 17 | CA77: 18 | CB77: 19 | CC77: 20 | CD77: 21 | CE77: 22 | CF77: 23 | CG77: 24 | CH77: 25 | CI77: 26 | CJ77: 27 | CK77: 28 | CL77: 1 | CM77: 2 | CN77: 3 | CO77: 4 | CP77: 5 | CQ77: 6 | CR77: 7 | CS77: 8 | CT77: 9 | CU77: 10 | CV77: 11 | CW77: 12 | CX77: 13 | CY77: 14 | CZ77: 15 | DA77: 16 | DB77: 17 | DC77: 18 | DD77: 19 | DE77: 20 | DF77: 21 | DG77: 22 | DH77: 23 | DI77: 24 | DJ77: 25 | DK77: 26 | DL77: 27 | DM77: 28 | DN77: 29 | DO77: 30 | DP77: 31 | DQ77: 1 | DR77: 2 | DS77: 3 | DT77: 4 | DU77: 5 | DV77: 6 | DW77: 7 | DX77: 8 | DY77: 9 | DZ77: 10 | EA77: 11 | EB77: 12 | EC77: 13 | ED77: 14 | EE77: 15 | EF77: 16 | EG77: 17 | EH77: 18 | EI77: 19 | EJ77: 20 | EK77: 21 | EL77: 22 | EM77: 23 | EN77: 24 | EO77: 25 | EP77: 26 | EQ77: 27 | ER77: 28 | ES77: 29 | ET77: 30 | EU77: 1 | EV77: 2 | EW77: 3 | EX77: 4 | EY77: 5 | EZ77: 6 | FA77: 7 | FB77: 8 | FC77: 9 | FD77: 10 | FE77: 11 | FF77: 12 | FG77: 13 | FH77: 14 | FI77: 15 | FJ77: 16 | FK77: 17 | FL77: 18 | FM77: 19 | FN77: 20 | FO77: 21 | FP77: 22 | FQ77: 23 | FR77: 24 | FS77: 25 | FT77: 26 | FU77: 27 | FV77: 28 | FW77: 29 | FX77: 30 | FY77: 1 | FZ77: 2 | GA77: 3 | GB77: 4 | GC77: 5 | GD77: 6 | GE77: 7 | GF77: 8 | GG77: 9 | GH77: 10 | GI77: 11 | GJ77: 12 | GK77: 13 | GL77: 14 | GM77: 15 | GN77: 16 | GO77: 17 | GP77: 18 | GQ77: 19 | GR77: 20 | GS77: 21 | GT77: 22 | GU77: 23 | GV77: 24 | GW77: 25 | GX77: 26 | GY77: 27 | GZ77: 28 | HA77: 29 | HB77: 30 | HC77: 31 | HD77: 1 | HE77: 2 | HF77: 3 | HG77: 4 | HH77: 5 | HI77: 6 | HJ77: 7 | HK77: 8 | HL77: 9 | HM77: 10 | HN77: 11 | HO77: 12 | HP77: 13 | HQ77: 14 | HR77: 15 | HS77: 16 | HT77: 17 | HU77: 18 | HV77: 19 | HW77: 20 | HX77: 21 | HY77: 22 | HZ77: 23 | IA77: 24 | IB77: 25 | IC77: 26 | ID77: 27 | IE77: 28 | IF77: 29 | IG77: 30 | IH77: 31 | II77: 1 | IJ77: 2 | IK77: 3 | IL77: 4 | IM77: 5 | IN77: 6 | IO77: 7 | IP77: 8 | IQ77: 9 | IR77: 10 | IS77: 11 | IT77: 12 | IU77: 13 | IV77: 14 | IW77: 15 | IX77: 16 | IY77: 17 | IZ77: 18 | JA77: 19 | JB77: 20 | JC77: 21 | JD77: 22 | JE77: 23 | JF77: 24 | JG77: 25 | JH77: 26 | JI77: 27 | JJ77: 28 | JK77: 29 | JL77: 30 | JM77: 31 | JN77: 1 | JO77: 2 | JP77: 3 | JQ77: 4 | JR77: 5 | JS77: 6 | JT77: 7 | JU77: 8 | JV77: 9 | JW77: 10 | JX77: 11 | JY77: 12 | JZ77: 13 | KA77: 14 | KB77: 15 | KC77: 16 | KD77: 17 | KE77: 18 | KF77: 19 | KG77: 20 | KH77: 21 | KI77: 22 | KJ77: 23 | KK77: 24 | KL77: 25 | KM77: 26 | KN77: 27 | KO77: 28 | KP77: 29 | KQ77: 30 | KR77: 1 | KS77: 2 | KT77: 3 | KU77: 4 | KV77: 5 | KW77: 6 | KX77: 7 | KY77: 8 | KZ77: 9 | LA77: 10 | LB77: 11 | LC77: 12 | LD77: 13 | LE77: 14 | LF77: 15 | LG77: 16 | LH77: 17 | LI77: 18 | LJ77: 19 | LK77: 20 | LL77: 21 | LM77: 22 | LN77: 23 | LO77: 24 | LP77: 25 | LQ77: 26 | LR77: 27 | LS77: 28 | LT77: 29 | LU77: 30 | LV77: 31 | LW77: 1 | LX77: 2 | LY77: 3 | LZ77: 4 | MA77: 5 | MB77: 6 | MC77: 7 | MD77: 8 | ME77: 9 | MF77: 10 | MG77: 11 | MH77: 12 | MI77: 13 | MJ77: 14 | MK77: 15 | ML77: 16 | MM77: 17 | MN77: 18 | MO77: 19 | MP77: 20 | MQ77: 21 | MR77: 22 | MS77: 23 | MT77: 24 | MU77: 25 | MV77: 26 | MW77: 27 | MX77: 28 | MY77: 29 | MZ77: 30 | NA77: 1 | NB77: 2 | NC77: 3 | ND77: 4 | NE77: 5 | NF77: 6 | NG77: 7 | NH77: 8 | NI77: 9 | NJ77: 10 | NK77: 11 | NL77: 12 | NM77: 13 | NN77: 14 | NO77: 15 | NP77: 16 | NQ77: 17 | NR77: 18 | NS77: 19 | NT77: 20 | NU77: 21 | NV77: 22 | NW77: 23 | NX77: 24 | NY77: 25 | NZ77: 26 | OA77: 27 | OB77: 28 | OC77: 29 | OD77: 30 | OE77: 31
R78: =MAX(AE78:BI78) -> 329.54 | S78: =MAX(BJ78:CK78) -> 361.8 | T78: =MAX(CL78:DP78) -> 26.97 | V78: =MAX(DP78:ET78) -> 16.53 | W78: =MAX(EU78:FX78) -> 16.34 | X78: =MAX(FY78:HC78) -> 16.46 | Y78: =MAX(HD78:IH78) -> 13.64 | Z78: =MAX(II78:JM78) -> 12.53 | AA78: =MAX(JN78:KQ78) -> 15.7 | AB78: =MAX(KR78:LV78) -> 136.48 | AC78: =MAX(LW78:MZ78) -> 120.34 | AD78: =MAX(NA78:OE78) -> 21.17 | AE78: =Industria!K54 -> 13.72 | AF78: =Industria!L54 -> 13.68 | AG78: =Industria!M54 -> 18.36 | AH78: =Industria!N54 -> 18.5 | AI78: =Industria!O54 -> 18.8 | AJ78: =Industria!P54 -> 16.52 | AK78: =Industria!Q54 -> 13.46 | AL78: =Industria!R54 -> 14.36 | ... OE78: =Industria!NK54 -> 14.15
R79: =MAX(AE79:BI79) -> 336.38 | S79: =MAX(BJ79:CK79) -> 200.99 | T79: =MAX(CL79:DP79) -> 27.1 | V79: =MAX(DP79:ET79) -> 16.2 | W79: =MAX(EU79:FX79) -> 15.92 | X79: =MAX(FY79:HC79) -> 14.44 | Y79: =MAX(HD79:IH79) -> 13.57 | Z79: =MAX(II79:JM79) -> 12.78 | AA79: =MAX(JN79:KQ79) -> 14.44 | AB79: =MAX(KR79:LV79) -> 19.79 | AC79: =MAX(LW79:MZ79) -> 94.5 | AD79: =MAX(NA79:OE79) -> 20.74 | AE79: =Industria!K55 -> 14.3 | AF79: =Industria!L55 -> 14.41 | AG79: =Industria!M55 -> 18.46 | AH79: =Industria!N55 -> 18.54 | AI79: =Industria!O55 -> 18.58 | AJ79: =Industria!P55 -> 16.64 | AK79: =Industria!Q55 -> 14.1 | AL79: =Industria!R55 -> 13.97 | ... OE79: =Industria!NK55 -> 14.18
R80: =MAX(AE80:BI80) -> 290.49 | S80: =MAX(BJ80:CK80) -> 26.39 | T80: =MAX(CL80:DP80) -> 22.18 | V80: =MAX(DP80:ET80) -> 16.71 | W80: =MAX(EU80:FX80) -> 16.13 | X80: =MAX(FY80:HC80) -> 14.07 | Y80: =MAX(HD80:IH80) -> 14.26 | Z80: =MAX(II80:JM80) -> 15.23 | AA80: =MAX(JN80:KQ80) -> 13.64 | AB80: =MAX(KR80:LV80) -> 16.49 | AC80: =MAX(LW80:MZ80) -> 96.01 | AD80: =MAX(NA80:OE80) -> 18.47 | AE80: =Industria!K56 -> 13.76 | AF80: =Industria!L56 -> 13.83 | AG80: =Industria!M56 -> 18.46 | AH80: =Industria!N56 -> 18.54 | AI80: =Industria!O56 -> 18.6 | AJ80: =Industria!P56 -> 16.85 | AK80: =Industria!Q56 -> 13.79 | AL80: =Industria!R56 -> 14.25 | ... OE80: =Industria!NK56 -> 12.13
R81: =MAX(AE81:BI81) -> 304.88 | S81: =MAX(BJ81:CK81) -> 26.14 | T81: =MAX(CL81:DP81) -> 19.98 | V81: =MAX(DP81:ET81) -> 14.79 | W81: =MAX(EU81:FX81) -> 14.11 | X81: =MAX(FY81:HC81) -> 13.29 | Y81: =MAX(HD81:IH81) -> 14.8 | Z81: =MAX(II81:JM81) -> 17.53 | AA81: =MAX(JN81:KQ81) -> 13.89 | AB81: =MAX(KR81:LV81) -> 16.02 | AC81: =MAX(LW81:MZ81) -> 89.85 | AD81: =MAX(NA81:OE81) -> 18.4 | AE81: =Industria!K57 -> 14.47 | AF81: =Industria!L57 -> 14.4 | AG81: =Industria!M57 -> 18.53 | AH81: =Industria!N57 -> 18.58 | AI81: =Industria!O57 -> 18.62 | AJ81: =Industria!P57 -> 16.78 | AK81: =Industria!Q57 -> 13.76 | AL81: =Industria!R57 -> 14.4 | ... OE81: =Industria!NK57 -> 13.28
R82: =MAX(AE82:BI82) -> 325.94 | S82: =MAX(BJ82:CK82) -> 26.14 | T82: =MAX(CL82:DP82) -> 20.06 | V82: =MAX(DP82:ET82) -> 14.87 | W82: =MAX(EU82:FX82) -> 13.89 | X82: =MAX(FY82:HC82) -> 13.25 | Y82: =MAX(HD82:IH82) -> 14.33 | Z82: =MAX(II82:JM82) -> 15.95 | AA82: =MAX(JN82:KQ82) -> 14.58 | AB82: =MAX(KR82:LV82) -> 14.4 | AC82: =MAX(LW82:MZ82) -> 89.96 | AD82: =MAX(NA82:OE82) -> 17.03 | AE82: =Industria!K58 -> 13.89 | AF82: =Industria!L58 -> 13.76 | AG82: =Industria!M58 -> 18.33 | AH82: =Industria!N58 -> 18.5 | AI82: =Industria!O58 -> 18.44 | AJ82: =Industria!P58 -> 16.78 | AK82: =Industria!Q58 -> 14 | AL82: =Industria!R58 -> 14.11 | ... OE82: =Industria!NK58 -> 15.04
R83: =MAX(AE83:BI83) -> 280.74 | S83: =MAX(BJ83:CK83) -> 26.07 | T83: =MAX(CL83:DP83) -> 21.3 | V83: =MAX(DP83:ET83) -> 14.9 | W83: =MAX(EU83:FX83) -> 13.46 | X83: =MAX(FY83:HC83) -> 13.57 | Y83: =MAX(HD83:IH83) -> 13.94 | Z83: =MAX(II83:JM83) -> 13.04 | AA83: =MAX(JN83:KQ83) -> 14.62 | AB83: =MAX(KR83:LV83) -> 14.8 | AC83: =MAX(LW83:MZ83) -> 91.12 | AD83: =MAX(NA83:OE83) -> 18.23 | AE83: =Industria!K59 -> 14.18 | AF83: =Industria!L59 -> 14.04 | AG83: =Industria!M59 -> 18.25 | AH83: =Industria!N59 -> 18.47 | AI83: =Industria!O59 -> 18.53 | AJ83: =Industria!P59 -> 16.71 | AK83: =Industria!Q59 -> 13.75 | AL83: =Industria!R59 -> 14.61 | ... OE83: =Industria!NK59 -> 12.52
R84: =MAX(AE84:BI84) -> 331.09 | S84: =MAX(BJ84:CK84) -> 25.92 | T84: =MAX(CL84:DP84) -> 19.91 | V84: =MAX(DP84:ET84) -> 14.65 | W84: =MAX(EU84:FX84) -> 13.79 | X84: =MAX(FY84:HC84) -> 13.43 | Y84: =MAX(HD84:IH84) -> 13.28 | Z84: =MAX(II84:JM84) -> 13.14 | AA84: =MAX(JN84:KQ84) -> 13.46 | AB84: =MAX(KR84:LV84) -> 13.64 | AC84: =MAX(LW84:MZ84) -> 94.03 | AD84: =MAX(NA84:OE84) -> 16.41 | AE84: =Industria!K60 -> 13.79 | AF84: =Industria!L60 -> 13.86 | AG84: =Industria!M60 -> 18.36 | AH84: =Industria!N60 -> 18.46 | AI84: =Industria!O60 -> 18.47 | AJ84: =Industria!P60 -> 16.7 | AK84: =Industria!Q60 -> 14.23 | AL84: =Industria!R60 -> 14 | ... OE84: =Industria!NK60 -> 12.77
R85: =MAX(AE85:BI85) -> 254.53 | S85: =MAX(BJ85:CK85) -> 27.47 | T85: =MAX(CL85:DP85) -> 45.05 | V85: =MAX(DP85:ET85) -> 54.54 | W85: =MAX(EU85:FX85) -> 27.18 | X85: =MAX(FY85:HC85) -> 23.83 | Y85: =MAX(HD85:IH85) -> 38.92 | Z85: =MAX(II85:JM85) -> 40.28 | AA85: =MAX(JN85:KQ85) -> 23.37 | AB85: =MAX(KR85:LV85) -> 19.51 | AC85: =MAX(LW85:MZ85) -> 95.1 | AD85: =MAX(NA85:OE85) -> 27.86 | AE85: =Industria!K61 -> 13.64 | AF85: =Industria!L61 -> 22.61 | AG85: =Industria!M61 -> 28.08 | AH85: =Industria!N61 -> 24.77 | AI85: =Industria!O61 -> 23.9 | AJ85: =Industria!P61 -> 16.45 | AK85: =Industria!Q61 -> 13.61 | AL85: =Industria!R61 -> 22.32 | ... OE85: =Industria!NK61 -> 13.32
R86: =MAX(AE86:BI86) -> 458.89 | S86: =MAX(BJ86:CK86) -> 442.26 | T86: =MAX(CL86:DP86) -> 440.13 | V86: =MAX(DP86:ET86) -> 406.51 | W86: =MAX(EU86:FX86) -> 404.17 | X86: =MAX(FY86:HC86) -> 383.9 | Y86: =MAX(HD86:IH86) -> 398.56 | Z86: =MAX(II86:JM86) -> 369.58 | AA86: =MAX(JN86:KQ86) -> 355.28 | AB86: =MAX(KR86:LV86) -> 403.49 | AC86: =MAX(LW86:MZ86) -> 401.43 | AD86: =MAX(NA86:OE86) -> 362.78 | AE86: =Industria!K62 -> 14.44 | AF86: =Industria!L62 -> 183.47 | AG86: =Industria!M62 -> 326.16 | AH86: =Industria!N62 -> 458.89 | AI86: =Industria!O62 -> 424.94 | AJ86: =Industria!P62 -> 16.57 | AK86: =Industria!Q62 -> 14.59 | AL86: =Industria!R62 -> 376.78 | ... OE86: =Industria!NK62 -> 14.14
R87: =MAX(AE87:BI87) -> 508.39 | S87: =MAX(BJ87:CK87) -> 459.55 | T87: =MAX(CL87:DP87) -> 522.76 | V87: =MAX(DP87:ET87) -> 438.62 | W87: =MAX(EU87:FX87) -> 470.84 | X87: =MAX(FY87:HC87) -> 386.38 | Y87: =MAX(HD87:IH87) -> 422.21 | Z87: =MAX(II87:JM87) -> 399.57 | AA87: =MAX(JN87:KQ87) -> 390.64 | AB87: =MAX(KR87:LV87) -> 456.45 | AC87: =MAX(LW87:MZ87) -> 554.01 | AD87: =MAX(NA87:OE87) -> 412.74 | AE87: =Industria!K63 -> 15.19 | AF87: =Industria!L63 -> 209.04 | AG87: =Industria!M63 -> 364.79 | AH87: =Industria!N63 -> 508.39 | AI87: =Industria!O63 -> 462.39 | AJ87: =Industria!P63 -> 17.22 | AK87: =Industria!Q63 -> 14.93 | AL87: =Industria!R63 -> 448.42 | ... OE87: =Industria!NK63 -> 12.71
R88: =MAX(AE88:BI88) -> 530.6 | S88: =MAX(BJ88:CK88) -> 473.51 | T88: =MAX(CL88:DP88) -> 424.87 | V88: =MAX(DP88:ET88) -> 411.78 | W88: =MAX(EU88:FX88) -> 464.97 | X88: =MAX(FY88:HC88) -> 401.54 | Y88: =MAX(HD88:IH88) -> 413.22 | Z88: =MAX(II88:JM88) -> 424.51 | AA88: =MAX(JN88:KQ88) -> 405.44 | AB88: =MAX(KR88:LV88) -> 423.32 | AC88: =MAX(LW88:MZ88) -> 546.09 | AD88: =MAX(NA88:OE88) -> 414.75 | AE88: =Industria!K64 -> 15.59 | AF88: =Industria!L64 -> 265.79 | AG88: =Industria!M64 -> 274.86 | AH88: =Industria!N64 -> 428.62 | AI88: =Industria!O64 -> 452.42 | AJ88: =Industria!P64 -> 15.88 | AK88: =Industria!Q64 -> 15.26 | AL88: =Industria!R64 -> 476.65 | ... OE88: =Industria!NK64 -> 14.25
R89: =MAX(AE89:BI89) -> 564.3 | S89: =MAX(BJ89:CK89) -> 493.93 | T89: =MAX(CL89:DP89) -> 432.68 | V89: =MAX(DP89:ET89) -> 415.8 | W89: =MAX(EU89:FX89) -> 472.89 | X89: =MAX(FY89:HC89) -> 388.98 | Y89: =MAX(HD89:IH89) -> 397.18 | Z89: =MAX(II89:JM89) -> 413.94 | AA89: =MAX(JN89:KQ89) -> 436.78 | AB89: =MAX(KR89:LV89) -> 432.83 | AC89: =MAX(LW89:MZ89) -> 503.53 | AD89: =MAX(NA89:OE89) -> 468.8 | AE89: =Industria!K65 -> 14.44 | AF89: =Industria!L65 -> 487.15 | AG89: =Industria!M65 -> 279.39 | AH89: =Industria!N65 -> 477.79 | AI89: =Industria!O65 -> 478.04 | AJ89: =Industria!P65 -> 15.09 | AK89: =Industria!Q65 -> 14.52 | AL89: =Industria!R65 -> 500.1 | ... OE89: =Industria!NK65 -> 15.24
... R101: =MAX(AE101:BI101) -> 360.54 | S101: =MAX(BJ101:CK101) -> 355.11 | T101: =MAX(CL101:DP101) -> 27 | V101: =MAX(DP101:ET101) -> 19.01 | W101: =MAX(EU101:FX101) -> 16.96 | X101: =MAX(FY101:HC101) -> 16.7 | Y101: =MAX(HD101:IH101) -> 15.12 | Z101: =MAX(II101:JM101) -> 12.63 | AA101: =MAX(JN101:KQ101) -> 17.16 | AB101: =MAX(KR101:LV101) -> 263.48 | AC101: =MAX(LW101:MZ101) -> 127.01 | AD101: =MAX(NA101:OE101) -> 20.92 | AE101: =Industria!K77 -> 13.86 | AF101: =Industria!L77 -> 18.29 | AG101: =Industria!M77 -> 18.47 | AH101: =Industria!N77 -> 18.53 | AI101: =Industria!O77 -> 16.38 | AJ101: =Industria!P77 -> 13.83 | AK101: =Industria!Q77 -> 13.58 | AL101: =Industria!R77 -> 18.68 | ... OE101: =Industria!NK77 -> 14.97
V103: MAX P
T104: P1 | V104: =MAX(R87:S91,R96:S99,Y96:Y99,Y87:Y91,AD87:AD91,AD96:AD99) -> 564.3 | W104: =ROUND(V104/100,1)*100+10 -> 570
T105: P2 | V105: =MAX(R86,S86,R92:S95,R100:S101,T87:T91,T96:T99,Y92:Y95,Y86,Y100:Y101,AC87:AC91,AC96:AC99,AD86,AD92:AD95,AD100:AD101) -> 554.01 | W105: =ROUND(V105/100,1)*100+10 -> 560
T106: P3 | V106: =MAX(T86,T92:T95,T100:T101,X87:X91,X96:X99,Z87:AA91,Z96:AA99,AC86,AC92:AC95,AC100:AC101) -> 466.56 | W106: =ROUND(V106/100,1)*100+10 -> 480
T107: P4 | V107: =MAX(V88:W91,V96:W99,X86,X92:X95,X100:X101,Z86:AA86,Z92:AA95,Z100:AA101,AB87:AB91,AB96:AB99) -> 472.89 | W107: =ROUND(V107/100,1)*100+10 -> 480
T108: P5 | V108: =MAX(V86:W86,V92:W95,V100:W101,AB86,AB92:AB95,AB100:AB101) -> 453.09 | W108: =ROUND(V108/100,1)*100+10 -> 460
T109: P6 | V109: =MAX(R78:AD85) -> 361.8 | W109: =ROUND(V109/100,1)*100+10 -> 370

Sheet Precios Bolsa Colombia 2024
A1: 2024 | B1: min | C1: max | D1: average | E1: 2024
A2: USD/KWh | B2: USD/COP | C2: USD/COP | D2: USD/COP | E2: Enero | F2: Febrero | G2: Marzo | H2: Abril | I2: Mayo | J2: Junio | K2: Julio | L2: Agosto | M2: Septiembre | N2: Octubre | O2: Noviembre | P2: Diciembre
A3: 0.15860415 | B3: 96.364056 | C3: 2674.6989 | D3: 634.41658 | E3: 550.99785 | F3: 533.19271 | G3: 623.63596 | H3: 688.24948 | I3: 231.30511 | J3: 217.97603 | K3: 234.73863 | L3: 512.65672 | M3: 856.5216 | N3: 1557.8168 | O3: 953.40495 | P3: 651.73014
A4: 0.12171982 | B4: 97.390224 | C4: 2674.6989 | D4: 486.87926 | E4: 545.85634 | F4: 517.29054 | G4: 617.65631 | H4: 677.37182 | I4: 224.82553 | J4: 218.8062 | K4: 240.70414 | L4: 521.58253 | M4: 853.28953 | N4: 1395.3863 | O4: 827.57621 | P4: 652.11121
A5: 0.11909825 | B5: 97.390224 | C5: 2498.8041 | D5: 476.39301 | E5: 537.88473 | F5: 507.22168 | G5: 598.13354 | H5: 639.36092 | I5: 224.22098 | J5: 212.8222 | K5: 229.76398 | L5: 502.9085 | M5: 849.23 | N5: 1267.8876 | O5: 735.57585 | P5: 640.77056
A6: 0.1160119 | B6: 97.346224 | C6: 2498.8041 | D6: 464.04759 | E6: 528.06482 | F6: 496.84799 | G6: 589.22709 | H6: 639.95235 | I6: 227.97614 | J6: 211.21223 | K6: 225.28811 | L6: 488.13466 | M6: 848.65066 | N6: 1208.4758 | O6: 728.78951 | P6: 635.85037
A7: 0.1184893 | B7: 97.390224 | C7: 2498.8041 | D7: 473.95719 | E7: 533.04885 | F7: 511.19702 | G7: 595.3786 | H7: 679.53755 | I7: 233.45872 | J7: 217.3942 | K7: 234.21463 | L7: 505.30085 | M7: 849.534 | N7: 1192.0089 | O7: 709.32471 | P7: 637.59898
A8: 0.12427995 | B8: 97.390224 | C8: 2498.8041 | D8: 497.1198 | E8: 540.76515 | F8: 557.87995 | G8: 599.40654 | H8: 697.56642 | I8: 247.14759 | J8: 224.1418 | K8: 244.38163 | L8: 531.00014 | M8: 861.87826 | N8: 1225.3316 | O8: 887.63125 | P8: 663.81585
A9: 0.12433783 | B9: 97.390224 | C9: 2498.8041 | D9: 497.35133 | E9: 539.00924 | F9: 548.10471 | G9: 587.72235 | H9: 690.52142 | I9: 243.0354 | J9: 226.1308 | K9: 245.6174 | L9: 533.81559 | M9: 853.2841 | N9: 1244.7784 | O9: 894.02175 | P9: 664.13888
A10: 0.13064242 | B10: 95.851608 | C10: 2498.8041 | D10: 522.5697 | E10: 534.05076 | F10: 560.52271 | G10: 588.42022 | H10: 700.47282 | I10: 249.73546 | J10: 245.4498 | K10: 249.43721 | L10: 536.41453 | M10: 849.22626 | N10: 1210.7548 | O10: 881.52688 | P10: 646.81198
A11: 0.13763512 | B11: 95.851608 | C11: 2498.8041 | D11: 550.54046 | E11: 543.02637 | F11: 568.59847 | G11: 593.23802 | H11: 705.93688 | I11: 252.82191 | J11: 253.1756 | K11: 255.74305 | L11: 540.46133 | M11: 849.09976 | N11: 1282.5107 | O11: 884.74758 | P11: 655.8275
A12: 0.14010958 | B12: 95.851608 | C12: 2498.8041 | D12: 560.43832 | E12: 542.84556 | F12: 567.41547 | G12: 587.04373 | H12: 717.76802 | I12: 252.69353 | J12: 256.25986 | K12: 258.75918 | L12: 543.52282 | M12: 853.75106 | N12: 1320.1857 | O12: 925.04005 | P12: 677.05011
A13: 0.14431613 | B13: 95.851608 | C13: 2498.8041 | D13: 577.26454 | E13: 549.39263 | F13: 570.14395 | G13: 602.18131 | H13: 739.58045 | I13: 257.27595 | J13: 262.92646 | K13: 268.20153 | L13: 554.20217 | M13: 865.45966 | N13: 1365.8243 | O13: 1050.88 | P13: 703.02711
A14: 0.14789205 | B14: 104.0472 | C14: 2674.6989 | D14: 591.56819 | E14: 559.73782 | F14: 580.00933 | G14: 622.8618 | H14: 754.74652 | I14: 282.08437 | J14: 284.10566 | K14: 285.48972 | L14: 571.01275 | M14: 878.42793 | N14: 1502.4866 | O14: 1093.1927 | P14: 752.86888
... A27: 0.14100992 | B27: 102.98494 | C27: 2608.9478 | D27: 564.03969 | E27: 558.7222 | F27: 568.70609 | G27: 622.77357 | H27: 748.65676 | I27: 291.54985 | J27: 280.69736 | K27: 285.09281 | L27: 567.41776 | M27: 873.70695 | N27: 1530.5736 | O27: 1047.1069 | P27: 741.76218
E28: =E27/$E$31 -> 0.13968055 | F28: =F27/$E$31 -> 0.14217652 | G28: =G27/$E$31 -> 0.15569339 | H28: =H27/$E$31 -> 0.18716419 | I28: =I27/$E$31 -> 0.072887463 | J28: =J27/$E$31 -> 0.070174341 | K28: =K27/$E$31 -> 0.071273203 | L28: =L27/$E$31 -> 0.14185444 | ... P28: =P27/$E$31 -> 0.18544054
A29: Precio de Escasez | C29: =937/E31 -> 0.23425 | D29: USD/kWh | E29: =IF(E28>$C$29,$C$29,E28) -> 0.13968055 | F29: =IF(F28>$C$29,$C$29,F28) -> 0.14217652 | G29: =IF(G28>$C$29,$C$29,G28) -> 0.15569339 | H29: =IF(H28>$C$29,$C$29,H28) -> 0.18716419 | I29: =IF(I28>$C$29,$C$29,I28) -> 0.072887463 | J29: =IF(J28>$C$29,$C$29,J28) -> 0.070174341 | K29: =IF(K28>$C$29,$C$29,K28) -> 0.071273203 | L29: =IF(L28>$C$29,$C$29,L28) -> 0.14185444 | ... P29: =IF(P28>$C$29,$C$29,P28) -> 0.18544054 | Q29: =AVERAGE(E29:P29) -> 0.15443928
Q30: =Q29*4000 -> 617.75713
A31: hora | B31: spot USD/kWh | C31: spot COP/kWh | D31: TRM | E31: 4000 | F31: COP/USD
A32: 1 | B32: =C32/$E$31 -> 0.062977902 | C32: 251.91161
A33: =A32+1 -> 2 | B33: =C33/$E$31 -> 0.062977902 | C33: 251.91161
A34: =A33+1 -> 3 | B34: =C34/$E$31 -> 0.062977902 | C34: 251.91161
A35: =A34+1 -> 4 | B35: =C35/$E$31 -> 0.070477902 | C35: 281.91161
A36: =A35+1 -> 5 | B36: =C36/$E$31 -> 0.070477902 | C36: 281.91161
A37: =A36+1 -> 6 | B37: =C37/$E$31 -> 0.062977902 | C37: 251.91161
A38: =A37+1 -> 7 | B38: =C38/$E$31 -> 0.038227902 | C38: 152.91161
A39: =A38+1 -> 8 | B39: =C39/$E$31 -> 0.023962902 | C39: 95.851608
A40: =A39+1 -> 9 | B40: =C40/$E$31 -> 0.023962902 | C40: 95.851608
A41: =A40+1 -> 10 | B41: =C41/$E$31 -> 0.023962902 | C41: 95.851608
A42: =A41+1 -> 11 | B42: =C42/$E$31 -> 0.023962902 | C42: 95.851608
A43: =A42+1 -> 12 | B43: =C43/$E$31 -> 0.038227902 | C43: 152.91161
A44: =A43+1 -> 13 | B44: =C44/$E$31 -> 0.038227902 | C44: 152.91161
... A8815: =A8814+1 -> 8784 | B8815: =C8815/$E$31 -> 0.029809363 | C8815: 119.23745

Sheet Tarifas Colombia 2024
B2: Costos U Aire-Barranquilla 2024
C3: Mes | P3: Promedio 2024
C4: 1 | D4: 2 | E4: 3 | F4: 4 | G4: 5 | H4: 6 | I4: 7 | J4: 8 | K4: 9 | L4: 10 | M4: 11 | N4: 12 | P4: COP/kWh | Q4: USD/kWh
B5: G | C5: 370.84 | D5: 373.83 | E5: 377.18 | F5: 451.5 | G5: 459.64 | H5: 411.59 | I5: 371.77 | J5: 338.3 | K5: 398.58 | L5: 394.86 | M5: 418.95 | N5: 402.69 | P5: =AVERAGE(C5:N5) -> 397.4775 | Q5: =P5/$C$29 -> 0.099369375
B6: T | C6: 54.32 | D6: 49.2 | E6: 57.43 | F6: 54.26 | G6: 47.96 | H6: 52.84 | I6: 55.93 | J6: 57.14 | K6: 48.55 | L6: 52.27 | M6: 55.37 | N6: 58.19 | P6: =AVERAGE(C6:N6) -> 53.621667 | Q6: =P6/$C$29 -> 0.013405417
B7: D-N1 | C7: 189.6 | D7: 196.69 | E7: 202.47 | F7: 160.93 | G7: 148.47 | H7: 133.25 | I7: 161.62 | J7: 148.28 | K7: 154.91 | L7: 160.55 | M7: 173.6 | N7: 178.7 | P7: =AVERAGE(C7:N7) -> 167.4225 | Q7: =P7/$C$29 -> 0.041855625
B8: PR-N1 | C8: 207.64 | D8: 206.21 | E8: 211.08 | F8: 123.15 | G8: 104.36 | H8: 114.19 | I8: 104.49 | J8: 98.52 | K8: 110.35 | L8: 110.29 | M8: 114.87 | N8: 111.2 | P8: =AVERAGE(C8:N8) -> 134.69583 | Q8: =P8/$C$29 -> 0.033673958
B9: Comerc N1 | C9: 330.47 | D9: 325.79 | E9: 354.03 | F9: 147.04 | G9: 139.18 | H9: 135.95 | I9: 128.91 | J9: 125.95 | K9: 128.92 | L9: 135.29 | M9: 138.95 | N9: 147.13 | P9: =AVERAGE(C9:N9) -> 186.4675 | Q9: =P9/$C$29 -> 0.046616875
B10: D-N2 | C10: 111.87 | D10: 114.69 | E10: 118.9 | F10: 110.83 | G10: 109.96 | H10: 86.35 | I10: 106.61 | J10: 98.94 | K10: 103.26 | L10: 107.82 | M10: 113 | N10: 119.74 | P10: =AVERAGE(C10:N10) -> 108.4975 | Q10: =P10/$C$29 -> 0.027124375
B11: PR-N2 | C11: 65.3 | D11: 62.35 | E11: 66.48 | F11: 50.79 | G11: 31.95 | H11: 47.76 | I11: 43.7 | J11: 42.22 | K11: 46.39 | L11: 46.3 | M11: 47.31 | N11: 46.6 | P11: =AVERAGE(C11:N11) -> 49.7625 | Q11: =P11/$C$29 -> 0.012440625
B12: Comerc Cvmj | C12: 137.38 | D12: 136.72 | E12: 145.76 | F12: 147.04 | G12: =G9 -> 139.18 | H12: =H9 -> 135.95 | I12: =I9 -> 128.91 | J12: =J9 -> 125.95 | K12: 116.12 | L12: 123.27 | M12: 125.65 | N12: 133.83 | P12: =AVERAGE(C12:N12) -> 132.98 | Q12: =P12/$C$29 -> 0.033245
B13: Restr | C13: 12.44 | D13: 13.21 | E13: 9.1 | F13: 9.06 | G13: 50.23 | H13: 33.78 | I13: 36.52 | J13: 39.09 | K13: 13.73 | L13: 1.57 | M13: 5.49 | N13: 8.3 | P13: =AVERAGE(C13:N13) -> 19.376667 | Q13: =P13/$C$29 -> 0.0048441667
B15: CU N1 | C15: =C5+C6+C7+C8+C13+C9 -> 1165.31 | D15: =D5+D6+D7+D8+D13+D9 -> 1164.93 | E15: =E5+E6+E7+E8+E13+E9 -> 1211.29 | F15: =F5+F6+F7+F8+F13+F9 -> 945.94 | G15: =G5+G6+G7+G8+G13+G9 -> 949.84 | H15: =H5+H6+H7+H8+H13+H9 -> 881.6 | I15: =I5+I6+I7+I8+I13+I9 -> 859.24 | J15: =J5+J6+J7+J8+J13+J9 -> 807.28 | ... N15: =N5+N6+N7+N8+N13+N9 -> 906.21 | P15: =AVERAGE(C15:N15) -> 959.06167 | Q15: =P15/$C$29 -> 0.23976542
B16: CU N2 | C16: =C5+C10+C11+C12+C13+C6 -> 752.15 | D16: =D5+D10+D11+D12+D13+D6 -> 750 | E16: =E5+E10+E11+E12+E13+E6 -> 774.85 | F16: =F5+F10+F11+F12+F13+F6 -> 823.48 | G16: =G5+G10+G11+G12+G13+G6 -> 838.92 | H16: =H5+H10+H11+H12+H13+H6 -> 768.27 | I16: =I5+I10+I11+I12+I13+I6 -> 743.44 | J16: =J5+J10+J11+J12+J13+J6 -> 701.64 | ... N16: =N5+N10+N11+N12+N13+N6 -> 769.35 | P16: =AVERAGE(C16:N16) -> 761.71583 | Q16: =P16/$C$29 -> 0.19042896
B18: CU N1 | C18: =C15/$C$29 -> 0.2913275 | D18: =D15/$C$29 -> 0.2912325 | E18: =E15/$C$29 -> 0.3028225 | F18: =F15/$C$29 -> 0.236485 | G18: =G15/$C$29 -> 0.23746 | H18: =H15/$C$29 -> 0.2204 | I18: =I15/$C$29 -> 0.21481 | J18: =J15/$C$29 -> 0.20182 | ... N18: =N15/$C$29 -> 0.2265525 | P18: =Q18*$C$29 -> 959.06167 | Q18: =AVERAGE(C18:N18) -> 0.23976542
B19: CU N2 | C19: =C16/$C$29 -> 0.1880375 | D19: =D16/$C$29 -> 0.1875 | E19: =E16/$C$29 -> 0.1937125 | F19: =F16/$C$29 -> 0.20587 | G19: =G16/$C$29 -> 0.20973 | H19: =H16/$C$29 -> 0.1920675 | I19: =I16/$C$29 -> 0.18586 | J19: =J16/$C$29 -> 0.17541 | ... N19: =N16/$C$29 -> 0.1923375 | P19: =Q19*$C$29 -> 761.71583 | Q19: =AVERAGE(C19:N19) -> 0.19042896
B21: CUpico N2 | C21: =C16/$C$26 -> 763.97241 | D21: =D16/$C$26 -> 761.78861 | E21: =E16/$C$26 -> 787.02921 | F21: =F16/$C$26 -> 836.42358 | G21: =G16/$C$26 -> 852.10627 | H21: =H16/$C$26 -> 780.34578 | I21: =I16/$C$26 -> 755.1255 | J21: =J16/$C$26 -> 712.66848 | ... N21: =N16/$C$26 -> 781.44276 | P21: =P16/$C$26 -> 773.6886 | Q21: =P21/$C$29 -> 0.19342215
B22: CUnopico N2 | C22: =C16/$C$27 -> 749.05931 | D22: =D16/$C$27 -> 746.91814 | E22: =E16/$C$27 -> 771.66603 | F22: =F16/$C$27 -> 820.0962 | G22: =G16/$C$27 -> 835.47276 | H22: =H16/$C$27 -> 765.11307 | I22: =I16/$C$27 -> 740.3851 | J22: =J16/$C$27 -> 698.75686 | ... N22: =N16/$C$27 -> 766.18863 | P22: =P16/$C$27 -> 758.58584 | Q22: =P22/$C$29 -> 0.18964646
B26: 5 | C26: 0.98452509 | P26: =(B26*P21+B27*P22)/24 -> 761.73224 | Q26: =P26/$C$29 -> 0.19043306
B27: 19 | C27: 1.0041261
B29: TRM 2024 | C29: 4000 | D29: COP/USD

Sheet Tarifas España 2024
AL7: Costes de Operación | AM7: =1/1000 -> 0.001 | AN7: Eur/kWh
AD8: fp>.95 | AE8: 0 | AF8: Eur/kVARh | AL8: Retribucion OM+OS | AM8: =0.20949/1000 -> 0.00020949 | AN8: Eur/kWh
AD9: .95<fp<.8 | AE9: 0.041554 | AF9: Eur/kVARh | AL9: Bono Social | AM9: =0.358725/1000 -> 0.000358725 | AN9: Eur/kWh
AD10: fp<.8 | AE10: 0.062332 | AF10: Eur/kVARh | AL10: Tasa Local | AM10: 0.015 | AN10: Eur/kWh
AC40: Segmento tarifario | AD40: Término de potencia de los cargos (€/kW año) | AK40: Grupo tarifario | AL40: Término de potencia del peaje de transporte y distribución (€/kW año) | AS40: Tarifa de acceso | AU40: Término de potencia (€/kW año)
AD41: Periodo 1 | AE41: Periodo 2 | AF41: Periodo 3 | AG41: Periodo 4 | AH41: Periodo 5 | AI41: Periodo 6 | AL41: Periodo 1 | AM41: Periodo 2 | AN41: Periodo 3 | AO41: Periodo 4 | AP41: Periodo 5 | AQ41: Periodo 6 | AU41: Periodo 1 | AV41: Periodo 2 | AW41: Periodo 3 | AX41: Periodo 4 | AY41: Periodo 5 | AZ41: Periodo 6
AC42: 2.0 TD | AD42: 3.971618 | AE42: 0.255423 | AK42: 2.0 TD | AL42: 22.958932 | AM42: 0.442165 | AR42: 1 | AS42: 2.0 TD | AT42: Baja tensión < 15 kW | AU42: =AD42+AL42 -> 26.93055 | AV42: =AE42+AM42 -> 0.697588
AC43: 3.0 TD | AD43: 4.935064 | AE43: 2.469687 | AF43: 1.794284 | AG43: 1.794284 | AH43: 1.794284 | AI43: 0.822511 | AK43: 3.0 TD | AL43: 14.723431 | AM43: 7.781964 | AN43: 2.468252 | AO43: 1.887267 | AP43: 0.533883 | AQ43: 0.533883 | AR43: 2 | AS43: 3.0 TD | AT43: Baja tensión > 15 kW | AU43: =AD43+AL43 -> 19.658495 | AV43: =AE43+AM43 -> 10.251651 | AW43: =AF43+AN43 -> 4.262536 | AX43: =AG43+AO43 -> 3.681551 | AY43: =AH43+AP43 -> 2.328167 | AZ43: =AI43+AQ43 -> 1.356394
AC44: 6.1 TD | AD44: 5.122811 | AE44: 2.563728 | AF44: 1.86284 | AG44: 1.86284 | AH44: 1.86284 | AI44: 0.853802 | AK44: 6.1 TD | AL44: 23.669055 | AM44: 12.513915 | AN44: 4.69633 | AO44: 3.309245 | AP44: 0.069965 | AQ44: 0.062286 | AR44: 3 | AS44: 6.1 TD | AT44: 1 kV > U > 30 kV | AU44: =AD44+AL44 -> 28.791866 | AV44: =AE44+AM44 -> 15.077643 | AW44: =AF44+AN44 -> 6.55917 | AX44: =AG44+AO44 -> 5.172085 | AY44: =AH44+AP44 -> 1.932805 | AZ44: =AI44+AQ44 -> 0.916088
AC45: 6.2 TD | AD45: 3.008289 | AE45: 1.505746 | AF45: 1.093923 | AG45: 1.093923 | AH45: 1.093923 | AI45: 0.501382 | AK45: 6.2 TD | AL45: 16.620368 | AM45: 9.426053 | AN45: 2.481516 | AO45: 1.512028 | AP45: 0.059278 | AQ45: 0.052654 | AR45: 4 | AS45: 6.2 TD | AT45: 30 kV > U > 72 kV | AU45: =AD45+AL45 -> 19.628657 | AV45: =AE45+AM45 -> 10.931799 | AW45: =AF45+AN45 -> 3.575439 | AX45: =AG45+AO45 -> 2.605951 | AY45: =AH45+AP45 -> 1.153201 | AZ45: =AI45+AQ45 -> 0.554036
AC46: 6.3 TD | AD46: 2.408681 | AE46: 1.205367 | AF46: 0.875748 | AG46: 0.875748 | AH46: 0.875748 | AI46: 0.401447 | AK46: 6.3 TD | AL46: 10.791377 | AM46: 6.502236 | AN46: 2.118318 | AO46: 1.380541 | AP46: 0.045332 | AQ46: 0.039905 | AR46: 5 | AS46: 6.3 TD | AT46: 72 kV > U > 145 kV | AU46: =AD46+AL46 -> 13.200058 | AV46: =AE46+AM46 -> 7.707603 | AW46: =AF46+AN46 -> 2.994066 | AX46: =AG46+AO46 -> 2.256289 | AY46: =AH46+AP46 -> 0.92108 | AZ46: =AI46+AQ46 -> 0.441352
AC47: 6.4 TD | AD47: 1.178247 | AE47: 0.589615 | AF47: 0.428453 | AG47: 0.428453 | AH47: 0.428453 | AI47: 0.196374 | AK47: 6.4 TD | AL47: 6.590215 | AM47: 3.93998 | AN47: 0.956817 | AO47: 0.665081 | AP47: 0.019779 | AQ47: 0.013181 | AR47: 6 | AS47: 6.4 TD | AT47: U > 145 kV | AU47: =AD47+AL47 -> 7.768462 | AV47: =AE47+AM47 -> 4.529595 | AW47: =AF47+AN47 -> 1.38527 | AX47: =AG47+AO47 -> 1.093534 | AY47: =AH47+AP47 -> 0.448232 | AZ47: =AI47+AQ47 -> 0.209555
AC49: Segmento tarifario | AD49: Término de energía de los cargos (€/kWh) | AK49: Grupo tarifario | AL49: Término de energía del peaje de transporte y distribución (€/kWh) | AS49: Tarifa de acceso | AU49: Término de energía (€/kWh)
AD50: Periodo 1 | AE50: Periodo 2 | AF50: Periodo 3 | AG50: Periodo 4 | AH50: Periodo 5 | AI50: Periodo 6 | AL50: Periodo 1 | AM50: Periodo 2 | AN50: Periodo 3 | AO50: Periodo 4 | AP50: Periodo 5 | AQ50: Periodo 6 | AU50: Periodo 1 | AV50: Periodo 2 | AW50: Periodo 3 | AX50: Periodo 4 | AY50: Periodo 5 | AZ50: Periodo 6
AC51: 2.0 TD | AD51: 0.058305 | AE51: 0.011661 | AF51: 0.002915 | AK51: 2.0 TD | AL51: 0.034234 | AM51: 0.01654 | AN51: 7.9e-05 | AR51: 1 | AS51: 2.0 TD | AT51: Baja tensión < 15 kW | AU51: =AD51+AL51 -> 0.092539 | AV51: =AE51+AM51 -> 0.028201 | AW51: =AF51+AN51 -> 0.002994
AC52: 3.0 TD | AD52: 0.032503 | AE52: 0.024066 | AF52: 0.013001 | AG52: 0.006501 | AH52: 0.004167 | AI52: 0.0026 | AK52: 3.0 TD | AL52: 0.028528 | AM52: 0.012343 | AN52: 0.004673 | AO52: 0.002682 | AP52: 0.000119 | AQ52: 3.1e-05 | AR52: 2 | AS52: 3.0 TD | AT52: Baja tensión > 15 kW | AU52: =AD52+AL52 -> 0.061031 | AV52: =AE52+AM52 -> 0.036409 | AW52: =AF52+AN52 -> 0.017674 | AX52: =AG52+AO52 -> 0.009183 | AY52: =AH52+AP52 -> 0.004286 | AZ52: =AI52+AQ52 -> 0.002631
AC53: 6.1 TD | AD53: 0.017674 | AE53: 0.013092 | AF53: 0.007069 | AG53: 0.003535 | AH53: 0.002266 | AI53: 0.001414 | AK53: 6.1 TD | AL53: 0.027104 | AM53: 0.011894 | AN53: 0.004726 | AO53: 0.002739 | AP53: 0.000122 | AQ53: 2.9e-05 | AR53: 3 | AS53: 6.1 TD | AT53: 1 kV > U > 30 kV | AU53: =AD53+AL53 -> 0.044778 | AV53: =AE53+AM53 -> 0.024986 | AW53: =AF53+AN53 -> 0.011795 | AX53: =AG53+AO53 -> 0.006274 | AY53: =AH53+AP53 -> 0.002388 | AZ53: =AI53+AQ53 -> 0.001443
AC54: 6.2 TD | AD54: 0.008293 | AE54: 0.006142 | AF54: 0.003317 | AG54: 0.001659 | AH54: 0.001063 | AI54: 0.000663 | AK54: 6.2 TD | AL54: 0.01477 | AM54: 0.00684 | AN54: 0.002279 | AO54: 0.001219 | AP54: 6.3e-05 | AQ54: 2e-05 | AR54: 4 | AS54: 6.2 TD | AT54: 30 kV > U > 72 kV | AU54: =AD54+AL54 -> 0.023063 | AV54: =AE54+AM54 -> 0.012982 | AW54: =AF54+AN54 -> 0.005596 | AX54: =AG54+AO54 -> 0.002878 | AY54: =AH54+AP54 -> 0.001126 | AZ54: =AI54+AQ54 -> 0.000683
AC55: 6.3 TD | AD55: 0.006798 | AE55: 0.005035 | AF55: 0.002719 | AG55: 0.00136 | AH55: 0.000871 | AI55: 0.000544 | AK55: 6.3 TD | AL55: 0.012294 | AM55: 0.00547 | AN55: 0.001931 | AO55: 0.001063 | AP55: 5.5e-05 | AQ55: 1.5e-05 | AR55: 5 | AS55: 6.3 TD | AT55: 72 kV > U > 145 kV | AU55: =AD55+AL55 -> 0.019092 | AV55: =AE55+AM55 -> 0.010505 | AW55: =AF55+AN55 -> 0.00465 | AX55: =AG55+AO55 -> 0.002423 | AY55: =AH55+AP55 -> 0.000926 | AZ55: =AI55+AQ55 -> 0.000559
AC56: 6.4 TD | AD56: 0.002582 | AE56: 0.001913 | AF56: 0.001033 | AG56: 0.000516 | AH56: 0.000331 | AI56: 0.000207 | AK56: 6.4 TD | AL56: 0.007944 | AM56: 0.003569 | AN56: 0.001288 | AO56: 0.000681 | AP56: 3.6e-05 | AQ56: 4e-06 | AR56: 6 | AS56: 6.4 TD | AT56: U > 145 kV | AU56: =AD56+AL56 -> 0.010526 | AV56: =AE56+AM56 -> 0.005482 | AW56: =AF56+AN56 -> 0.002321 | AX56: =AG56+AO56 -> 0.001197 | AY56: =AH56+AP56 -> 0.000367 | AZ56: =AI56+AQ56 -> 0.000211 | BS56: 31
BS57: 28
AC58: Segmento tarifario | AD58: Pagos de capacidad (€/kWh) | BS58: 31
AD59: Periodo 1 | AE59: Periodo 2 | AF59: Periodo 3 | AG59: Periodo 4 | AH59: Periodo 5 | AI59: Periodo 6
AC60: 2.0 TD | AD60: 0.000844 | AE60: 0.00014
AC61: 3.0 TD | AD61: 0.001141 | AE61: 0.000527 | AF61: 0.000351 | AG61: 0.000264 | AH61: 0.000264 | AI61: 0
AC62: 6.1 TD | AD62: 0.00049 | AE62: 0.000225 | AF62: 0.00015 | AG62: 0.000113 | AH62: 0.000113 | AI62: 0
AC63: 6.2 TD | AD63: 0.00049 | AE63: 0.000225 | AF63: 0.00015 | AG63: 0.000113 | AH63: 0.000113 | AI63: 0
AC64: 6.3 TD | AD64: 0.00049 | AE64: 0.000225 | AF64: 0.00015 | AG64: 0.000113 | AH64: 0.000113 | AI64: 0
AC65: 6.4 TD | AD65: 0.00049 | AE65: 0.000225 | AF65: 0.00015 | AG65: 0.000113 | AH65: 0.000113 | AI65: 0
AC67: Segmento tarifario | AD67: Coeficientes estándar de pérdidas
AD68: Periodo 1 | AE68: Periodo 2 | AF68: Periodo 3 | AG68: Periodo 4 | AH68: Periodo 5 | AI68: Periodo 6
AC69: 2.0 TD | AD69: 0.167 | AE69: 0.163 | AF69: 0.18
C70: https://www.boe.es/diario_boe/txt.php?id=BOE-A-2024-26218 | AC70: 3.0 TD | AD70: 0.166 | AE70: 0.175 | AF70: 0.165 | AG70: 0.165 | AH70: 0.138 | AI70: 0.18
Q71: =SUM(Q59:Q70) -> 0 | AC71: 6.1 TD | AD71: 0.067 | AE71: 0.068 | AF71: 0.065 | AG71: 0.065 | AH71: 0.043 | AI71: 0.077
AC72: 6.2 TD | AD72: 0.052 | AE72: 0.054 | AF72: 0.049 | AG72: 0.05 | AH72: 0.035 | AI72: 0.054
AC73: 6.3 TD | AD73: 0.042 | AE73: 0.043 | AF73: 0.04 | AG73: 0.04 | AH73: 0.03 | AI73: 0.044
AC74: 6.4 TD | AD74: 0.016 | AE74: 0.016 | AF74: 0.016 | AG74: 0.016 | AH74: 0.015 | AI74: 0.017

Sheet Precios Bolsa España 2024
A1: % | B1: Mercado diario €/MWh | C1: Restricciones €/MWh | D1: Procesos OS €/MWh | E1: horames | F1: mes | G1: horadia | H1: DIA
A2: DBL=[ | B2: 63.33 | C2: 14.29 | D2: 1.49 | E2: 1 | F2: 1 | G2: 1 | H2: 1 | I2: ;
B3: 50.09 | C3: 15.23 | D3: 5.71 | E3: =E2+1 -> 2 | F3: =F2 -> 1 | G3: 2 | H3: 1 | I3: ; | K3: DIAS | L3: HORAS | M3: MES | O3: Spot | P3: Restricciones | Q3: Porcesos OS | R3: Total | S3: Restricciones Y Procesos OS
B4: 47.5 | C4: 16.75 | D4: 2.51 | E4: =E3+1 -> 3 | F4: =F3 -> 1 | G4: 3 | H4: 1 | I4: ; | J4: ENERO | K4: 31 | L4: =K4*24 -> 744 | M4: 1 | N4: 0 | O4: 0.068746795 | P4: 0.0072543014 | Q4: 0.0025313699 | R4: =O4+P4+Q4 -> 0.078532466 | S4: =P4+Q4 -> 0.0097856712
B5: 43.5 | C5: 18.29 | D5: 2.94 | E5: =E4+1 -> 4 | F5: =F4 -> 1 | G5: 4 | H5: 1 | I5: ; | J5: FEBRERO | K5: 28 | L5: =K5*24 -> 672 | M5: 2 | N5: 1 | O5: 0.064382932 | P5: 0.0081311507 | Q5: 0.0027362192 | R5: =O5+P5+Q5 -> 0.075250301 | S5: =P5+Q5 -> 0.01086737
B6: 42.5 | C6: 19.81 | D6: 2.8 | E6: =E5+1 -> 5 | F6: =F5 -> 1 | G6: 5 | H6: 1 | I6: ; | J6: MARZO | K6: 31 | L6: =K6*24 -> 744 | M6: 3 | N6: 2 | O6: 0.062238411 | P6: 0.0092259726 | Q6: 0.002448137 | R6: =O6+P6+Q6 -> 0.073912521 | S6: =P6+Q6 -> 0.01167411
B7: 42.09 | C7: 20.84 | D7: 3.44 | E7: =E6+1 -> 6 | F7: =F6 -> 1 | G7: 6 | H7: 1 | I7: ; | J7: ABRIL | K7: 30 | L7: =K7*24 -> 720 | M7: 4 | N7: 3 | O7: 0.060464137 | P7: 0.0097246575 | Q7: 0.0022396712 | R7: =O7+P7+Q7 -> 0.072428466 | S7: =P7+Q7 -> 0.011964329
B8: 42.5 | C8: 20.02 | D8: 4.02 | E8: =E7+1 -> 7 | F8: =F7 -> 1 | G8: 7 | H8: 1 | I8: ; | J8: MAYO | K8: 31 | L8: =K8*24 -> 744 | M8: 5 | N8: 4 | O8: 0.060655534 | P8: 0.0098196438 | Q8: 0.0022953699 | R8: =O8+P8+Q8 -> 0.072770548 | S8: =P8+Q8 -> 0.012115014
B9: 42.59 | C9: 18.67 | D9: 3.32 | E9: =E8+1 -> 8 | F9: =F8 -> 1 | G9: 8 | H9: 1 | I9: ; | J9: JUNIO | K9: 30 | L9: =K9*24 -> 720 | M9: 6 | N9: 5 | O9: 0.065132137 | P9: 0.010057589 | Q9: 0.0025469041 | R9: =O9+P9+Q9 -> 0.07773663 | S9: =P9+Q9 -> 0.012604493
B10: 43.37 | C10: 18.12 | D10: 2.79 | E10: =E9+1 -> 9 | F10: =F9 -> 1 | G10: 9 | H10: 1 | I10: ; | J10: JULIO | K10: 31 | L10: =K10*24 -> 744 | M10: 7 | N10: 6 | O10: 0.073826082 | P10: 0.0099409041 | Q10: 0.0041280822 | R10: =O10+P10+Q10 -> 0.087895068 | S10: =P10+Q10 -> 0.014068986
B11: 42.29 | C11: 17.85 | D11: 3.43 | E11: =E10+1 -> 10 | F11: =F10 -> 1 | G11: 10 | H11: 1 | I11: ; | J11: AGOSTO | K11: 31 | L11: =K11*24 -> 744 | M11: 8 | N11: 7 | O11: 0.076148795 | P11: 0.010411233 | Q11: 0.0055221918 | R11: =O11+P11+Q11 -> 0.092082219 | S11: =P11+Q11 -> 0.015933425
B12: 25 | C12: 13.52 | D12: 3.28 | E12: =E11+1 -> 11 | F12: =F11 -> 1 | G12: 11 | H12: 1 | I12: ; | J12: SEPTIEMBRE | K12: 30 | L12: =K12*24 -> 720 | M12: 9 | N12: 8 | O12: 0.069382712 | P12: 0.0094291507 | Q12: 0.0059585753 | R12: =O12+P12+Q12 -> 0.084770438 | S12: =P12+Q12 -> 0.015387726
B13: 3.9 | C13: 13.03 | D13: 2.63 | E13: =E12+1 -> 12 | F13: =F12 -> 1 | G13: 12 | H13: 1 | I13: ; | J13: OCTUBRE | K13: 31 | L13: =K13*24 -> 744 | M13: 10 | N13: 9 | O13: 0.056760082 | P13: 0.0080707671 | Q13: 0.0045372055 | R13: =O13+P13+Q13 -> 0.069368055 | S13: =P13+Q13 -> 0.012607973
B14: 3.2 | C14: 12.82 | D14: 1.92 | E14: =E13+1 -> 13 | F14: =F13 -> 1 | G14: 13 | H14: 1 | I14: ; | J14: NOVIEMBRE | K14: 30 | L14: =K14*24 -> 720 | M14: 11 | N14: 10 | O14: 0.04694937 | P14: 0.0071172055 | Q14: 0.0031848219 | R14: =O14+P14+Q14 -> 0.057251397 | S14: =P14+Q14 -> 0.010302027
B15: 2.06 | C15: 12.63 | D15: 1.89 | E15: =E14+1 -> 14 | F15: =F14 -> 1 | G15: 14 | H15: 1 | I15: ; | J15: DICIEMBRE | K15: 31 | L15: =K15*24 -> 744 | M15: 12 | N15: 11 | O15: 0.04184674 | P15: 0.0070680548 | Q15: 0.0025854521 | R15: =O15+P15+Q15 -> 0.051500247 | S15: =P15+Q15 -> 0.0096535068
B16: 1.73 | C16: 12.66 | D16: 2.41 | E16: =E15+1 -> 15 | F16: =F15 -> 1 | G16: 15 | H16: 1 | I16: ; | N16: 12 | O16: 0.039593726 | P16: 0.0070899726 | Q16: 0.002544274 | R16: =O16+P16+Q16 -> 0.049227973 | S16: =P16+Q16 -> 0.0096342466
B17: 5.72 | C17: 13.07 | D17: 2.92 | E17: =E16+1 -> 16 | F17: =F16 -> 1 | G17: 16 | H17: 1 | I17: ; | N17: 13 | O17: 0.037885123 | P17: 0.0075278082 | Q17: 0.0024952877 | R17: =O17+P17+Q17 -> 0.047908219 | S17: =P17+Q17 -> 0.010023096
B18: 18.49 | C18: 12.17 | D18: 5.19 | E18: =E17+1 -> 17 | F18: =F17 -> 1 | G18: 17 | H18: 1 | I18: ; | N18: 14 | O18: 0.036840932 | P18: 0.0075245753 | Q18: 0.0024581096 | R18: =O18+P18+Q18 -> 0.046823616 | S18: =P18+Q18 -> 0.0099826849
B19: 37 | C19: 10.28 | D19: 7.56 | E19: =E18+1 -> 18 | F19: =F18 -> 1 | G19: 18 | H19: 1 | I19: ; | N19: 15 | O19: 0.038253699 | P19: 0.0076432329 | Q19: 0.0030550685 | R19: =O19+P19+Q19 -> 0.048952 | S19: =P19+Q19 -> 0.010698301
B20: 47.5 | C20: 9.21 | D20: 2.84 | E20: =E19+1 -> 19 | F20: =F19 -> 1 | G20: 19 | H20: 1 | I20: ; | N20: 16 | O20: 0.046423205 | P20: 0.0078807123 | Q20: 0.0042375616 | R20: =O20+P20+Q20 -> 0.058541479 | S20: =P20+Q20 -> 0.012118274
B21: 54.97 | C21: 5.77 | D21: 2.6 | E21: =E20+1 -> 20 | F21: =F20 -> 1 | G21: 20 | H21: 1 | I21: ; | N21: 17 | O21: 0.059484767 | P21: 0.008736274 | Q21: 0.0056707671 | R21: =O21+P21+Q21 -> 0.073891808 | S21: =P21+Q21 -> 0.014407041
B22: 60.9 | C22: 5.27 | D22: 2.03 | E22: =E21+1 -> 21 | F22: =F21 -> 1 | G22: 21 | H22: 1 | I22: ; | N22: 18 | O22: 0.076155178 | P22: 0.010724877 | Q22: 0.0059901918 | R22: =O22+P22+Q22 -> 0.092870247 | S22: =P22+Q22 -> 0.016715068
B23: 60 | C23: 5.29 | D23: 3.17 | E23: =E22+1 -> 22 | F23: =F22 -> 1 | G23: 22 | H23: 1 | I23: ; | N23: 19 | O23: 0.090286438 | P23: 0.012580219 | Q23: 0.0045248767 | R23: =O23+P23+Q23 -> 0.10739153 | S23: =P23+Q23 -> 0.017105096
B24: 47.5 | C24: 4.52 | D24: 3.21 | E24: =E23+1 -> 23 | F24: =F23 -> 1 | G24: 23 | H24: 1 | I24: ; | N24: 20 | O24: 0.099023507 | P24: 0.011415753 | Q24: 0.0031109041 | R24: =O24+P24+Q24 -> 0.11355016 | S24: =P24+Q24 -> 0.014526658
B25: 42.09 | C25: 4.65 | D25: 2.82 | E25: =E24+1 -> 24 | F25: =F24 -> 1 | G25: 24 | H25: 1 | I25: ; | N25: 21 | O25: 0.09037211 | P25: 0.01131526 | Q25: 0.0030031507 | R25: =O25+P25+Q25 -> 0.10469052 | S25: =P25+Q25 -> 0.014318411
B26: 37.8 | C26: 12.13 | D26: 1.61 | E26: =E25+1 -> 25 | F26: =F25 -> 1 | G26: =G2 -> 1 | H26: =H2+1 -> 2 | I26: ; | N26: 22 | O26: 0.081188795 | P26: 0.012232575 | Q26: 0.0028552603 | R26: =O26+P26+Q26 -> 0.09627663 | S26: =P26+Q26 -> 0.015087836
B27: 25 | C27: 14.71 | D27: 3.79 | E27: =E26+1 -> 26 | F27: =F26 -> 1 | G27: =G3 -> 2 | H27: =H3+1 -> 2 | I27: ; | N27: 23 | O27: 0.074767233 | P27: 0.0088425753 | Q27: 0.0028075068 | R27: =O27+P27+Q27 -> 0.086417315 | S27: =P27+Q27 -> 0.011650082
B28: 3.99 | C28: 16.71 | D28: 4.71 | E28: =E27+1 -> 27 | F28: =F27 -> 1 | G28: =G4 -> 3 | H28: =H4+1 -> 2 | I28: ;
B29: 14 | C29: 16.68 | D29: 3.28 | E29: =E28+1 -> 28 | F29: =F28 -> 1 | G29: =G5 -> 4 | H29: =H5+1 -> 2 | I29: ;
B30: 10 | C30: 17 | D30: 5.39 | E30: =E29+1 -> 29 | F30: =F29 -> 1 | G30: =G6 -> 5 | H30: =H6+1 -> 2 | I30: ;
B31: 14.54 | C31: 16.05 | D31: 5.57 | E31: =E30+1 -> 30 | F31: =F30 -> 1 | G31: =G7 -> 6 | H31: =H7+1 -> 2 | I31: ;
B32: 36.29 | C32: 12.09 | D32: 4.28 | E32: =E31+1 -> 31 | F32: =F31 -> 1 | G32: =G8 -> 7 | H32: =H8+1 -> 2 | I32: ;
B33: 44.7 | C33: 8.64 | D33: 3.52 | E33: =E32+1 -> 32 | F33: =F32 -> 1 | G33: =G9 -> 8 | H33: =H9+1 -> 2 | I33: ;
B34: 53.78 | C34: 6.23 | D34: 2.84 | E34: =E33+1 -> 33 | F34: =F33 -> 1 | G34: =G10 -> 9 | H34: =H10+1 -> 2 | I34: ;
B35: 54.23 | C35: 4.62 | D35: 2.76 | E35: =E34+1 -> 34 | F35: =F34 -> 1 | G35: =G11 -> 10 | H35: =H11+1 -> 2 | I35: ;
B36: 50 | C36: 4.16 | D36: 2.28 | E36: =E35+1 -> 35 | F36: =F35 -> 1 | G36: =G12 -> 11 | H36: =H12+1 -> 2 | I36: ;
B37: 52.2 | C37: 4.37 | D37: 2.28 | E37: =E36+1 -> 36 | F37: =F36 -> 1 | G37: =G13 -> 12 | H37: =H13+1 -> 2 | I37: ;
B38: 45 | C38: 4.62 | D38: 3.34 | E38: =E37+1 -> 37 | F38: =F37 -> 1 | G38: =G14 -> 13 | H38: =H14+1 -> 2 | I38: ;
B39: 43 | C39: 4.3 | D39: 3.76 | E39: =E38+1 -> 38 | F39: =F38 -> 1 | G39: =G15 -> 14 | H39: =H15+1 -> 2 | I39: ;
... B745: 77.52 | C745: 3.34 | D745: 4.19 | E745: =E744+1 -> 744 | F745: =F744 -> 1 | G745: =G721 -> 24 | H745: =H721+1 -> 31 | I745: ;
B746: 69 | C746: 6.43 | D746: 2.72 | E746: 1 | F746: =F745+1 -> 2 | G746: =G722 -> 1 | H746: 1 | I746: ;
B747: 60.44 | C747: 6.58 | D747: 2.68 | E747: =E746+1 -> 2 | F747: =F746 -> 2 | G747: =G723 -> 2 | H747: 1 | I747: ;
B748: 55.1 | C748: 6.19 | D748: 3.1 | E748: =E747+1 -> 3 | F748: =F747 -> 2 | G748: =G724 -> 3 | H748: 1 | I748: ;
B749: 54.6 | C749: 7.59 | D749: 2.22 | E749: =E748+1 -> 4 | F749: =F748 -> 2 | G749: =G725 -> 4 | H749: 1 | I749: ;
B750: 53.47 | C750: 7.67 | D750: 2.24 | E750: =E749+1 -> 5 | F750: =F749 -> 2 | G750: =G726 -> 5 | H750: 1 | I750: ;
B751: 59.82 | C751: 7.08 | D751: 2.26 | E751: =E750+1 -> 6 | F751: =F750 -> 2 | G751: =G727 -> 6 | H751: 1 | I751: ;
B752: 72.42 | C752: 4.28 | D752: 2.36 | E752: =E751+1 -> 7 | F752: =F751 -> 2 | G752: =G728 -> 7 | H752: 1 | I752: ;
B753: 88.76 | C753: 6.1 | D753: 3.36 | E753: =E752+1 -> 8 | F753: =F752 -> 2 | G753: =G729 -> 8 | H753: 1 | I753: ;
B754: 95.76 | C754: 8.88 | D754: 2.83 | E754: =E753+1 -> 9 | F754: =F753 -> 2 | G754: =G730 -> 9 | H754: 1 | I754: ;
B755: 88.77 | C755: 9.54 | D755: 3.95 | E755: =E754+1 -> 10 | F755: =F754 -> 2 | G755: =G731 -> 10 | H755: 1 | I755: ;
B756: 62.8 | C756: 6.57 | D756: 3.13 | E756: =E755+1 -> 11 | F756: =F755 -> 2 | G756: =G732 -> 11 | H756: 1 | I756: ;
B757: 55.98 | C757: 3.1 | D757: 3.24 | E757: =E756+1 -> 12 | F757: =F756 -> 2 | G757: =G733 -> 12 | H757: 1 | I757: ;
B758: 54.44 | C758: 8.78 | D758: 4.24 | E758: =E757+1 -> 13 | F758: =F757 -> 2 | G758: =G734 -> 13 | H758: 1 | I758: ;
... B769: 71.19 | C769: 10.26 | D769: 3.16 | E769: =E768+1 -> 24 | F769: =F768 -> 2 | G769: =G745 -> 24 | H769: 1 | I769: ;
B770: 62.95 | C770: 11.29 | D770: 2.03 | E770: =E769+1 -> 25 | F770: =F769 -> 2 | G770: =G746 -> 1 | H770: =H746+1 -> 2 | I770: ;
B771: 60.05 | C771: 2.97 | D771: 2.95 | E771: =E770+1 -> 26 | F771: =F770 -> 2 | G771: =G747 -> 2 | H771: =H747+1 -> 2 | I771: ;
B772: 58 | C772: 3.45 | D772: 4.44 | E772: =E771+1 -> 27 | F772: =F771 -> 2 | G772: =G748 -> 3 | H772: =H748+1 -> 2 | I772: ;
B773: 54.69 | C773: 4.37 | D773: 3.98 | E773: =E772+1 -> 28 | F773: =F772 -> 2 | G773: =G749 -> 4 | H773: =H749+1 -> 2 | I773: ;
B774: 52.41 | C774: 4.53 | D774: 3.88 | E774: =E773+1 -> 29 | F774: =F773 -> 2 | G774: =G750 -> 5 | H774: =H750+1 -> 2 | I774: ;
B775: 55 | C775: 4.25 | D775: 3.3 | E775: =E774+1 -> 30 | F775: =F774 -> 2 | G775: =G751 -> 6 | H775: =H751+1 -> 2 | I775: ;
B776: 61 | C776: 6.63 | D776: 2.96 | E776: =E775+1 -> 31 | F776: =F775 -> 2 | G776: =G752 -> 7 | H776: =H752+1 -> 2 | I776: ;
B777: 80.34 | C777: 8.14 | D777: 4.09 | E777: =E776+1 -> 32 | F777: =F776 -> 2 | G777: =G753 -> 8 | H777: =H753+1 -> 2 | I777: ;
B778: 90.75 | C778: 8.29 | D778: 4.28 | E778: =E777+1 -> 33 | F778: =F777 -> 2 | G778: =G754 -> 9 | H778: =H754+1 -> 2 | I778: ;
B779: 83.98 | C779: 8.69 | D779: 5.24 | E779: =E778+1 -> 34 | F779: =F778 -> 2 | G779: =G755 -> 10 | H779: =H755+1 -> 2 | I779: ;
B780: 61.42 | C780: 3.72 | D780: 8.22 | E780: =E779+1 -> 35 | F780: =F779 -> 2 | G780: =G756 -> 11 | H780: =H756+1 -> 2 | I780: ;
B781: 54 | C781: 2.04 | D781: 6.34 | E781: =E780+1 -> 36 | F781: =F780 -> 2 | G781: =G757 -> 12 | H781: =H757+1 -> 2 | I781: ;
... B1417: 11.29 | C1417: 17.23 | D1417: 2.23 | E1417: =E1416+1 -> 672 | F1417: =F1416 -> 2 | G1417: =G1393 -> 24 | H1417: =H1393+1 -> 28 | I1417: ;
B1418: 2.17 | C1418: 7.75 | D1418: 3.19 | E1418: 1 | F1418: 3 | G1418: =G1394 -> 1 | H1418: 1 | I1418: ;
B1419: 0.5 | C1419: 8.21 | D1419: 3.16 | E1419: =E1418+1 -> 2 | F1419: =F1418 -> 3 | G1419: =G1395 -> 2 | H1419: 1 | I1419: ;
B1420: 0.2 | C1420: 9.3 | D1420: 3.65 | E1420: =E1419+1 -> 3 | F1420: =F1419 -> 3 | G1420: =G1396 -> 3 | H1420: 1 | I1420: ;
B1421: 0.1 | C1421: 9.57 | D1421: 2.54 | E1421: =E1420+1 -> 4 | F1421: =F1420 -> 3 | G1421: =G1397 -> 4 | H1421: 1 | I1421: ;
B1422: 0.01 | C1422: 9.64 | D1422: 2.51 | E1422: =E1421+1 -> 5 | F1422: =F1421 -> 3 | G1422: =G1398 -> 5 | H1422: 1 | I1422: ;
B1423: 0.5 | C1423: 9.32 | D1423: 2.55 | E1423: =E1422+1 -> 6 | F1423: =F1422 -> 3 | G1423: =G1399 -> 6 | H1423: 1 | I1423: ;
B1424: 3 | C1424: 7.81 | D1424: 1.44 | E1424: =E1423+1 -> 7 | F1424: =F1423 -> 3 | G1424: =G1400 -> 7 | H1424: 1 | I1424: ;
B1425: 3.25 | C1425: 8.37 | D1425: 2.57 | E1425: =E1424+1 -> 8 | F1425: =F1424 -> 3 | G1425: =G1401 -> 8 | H1425: 1 | I1425: ;
B1426: 3.25 | C1426: 7.39 | D1426: 2.36 | E1426: =E1425+1 -> 9 | F1426: =F1425 -> 3 | G1426: =G1402 -> 9 | H1426: 1 | I1426: ;
B1427: 3.2 | C1427: 5.92 | D1427: 1.15 | E1427: =E1426+1 -> 10 | F1427: =F1426 -> 3 | G1427: =G1403 -> 10 | H1427: 1 | I1427: ;
B1428: 0 | C1428: 6.35 | D1428: 2.46 | E1428: =E1427+1 -> 11 | F1428: =F1427 -> 3 | G1428: =G1404 -> 11 | H1428: 1 | I1428: ;
B1429: 0 | C1429: 6.49 | D1429: 1.24 | E1429: =E1428+1 -> 12 | F1429: =F1428 -> 3 | G1429: =G1405 -> 12 | H1429: 1 | I1429: ;
B1430: 0 | C1430: 6.37 | D1430: 1.56 | E1430: =E1429+1 -> 13 | F1430: =F1429 -> 3 | G1430: =G1406 -> 13 | H1430: 1 | I1430: ;
... B1441: 3.8 | C1441: 5.56 | D1441: 3.37 | E1441: =E1440+1 -> 24 | F1441: =F1440 -> 3 | G1441: =G1417 -> 24 | H1441: 1 | I1441: ;
B1442: 3.2 | C1442: 6.1 | D1442: 1.21 | E1442: =E1441+1 -> 25 | F1442: =F1441 -> 3 | G1442: =G1418 -> 1 | H1442: =H1418+1 -> 2 | I1442: ;
B1443: 2 | C1443: 6.56 | D1443: 1.78 | E1443: =E1442+1 -> 26 | F1443: =F1442 -> 3 | G1443: =G1419 -> 2 | H1443: =H1419+1 -> 2 | I1443: ;
B1444: 0.5 | C1444: 8.26 | D1444: 1.18 | E1444: =E1443+1 -> 27 | F1444: =F1443 -> 3 | G1444: =G1420 -> 3 | H1444: =H1420+1 -> 2 | I1444: ;
B1445: 0.01 | C1445: 8.5 | D1445: 0.54 | E1445: =E1444+1 -> 28 | F1445: =F1444 -> 3 | G1445: =G1421 -> 4 | H1445: =H1421+1 -> 2 | I1445: ;
B1446: 0.01 | C1446: 8.66 | D1446: 1.64 | E1446: =E1445+1 -> 29 | F1446: =F1445 -> 3 | G1446: =G1422 -> 5 | H1446: =H1422+1 -> 2 | I1446: ;
B1447: 0 | C1447: 8.71 | D1447: 1.6 | E1447: =E1446+1 -> 30 | F1447: =F1446 -> 3 | G1447: =G1423 -> 6 | H1447: =H1423+1 -> 2 | I1447: ;
B1448: 0.1 | C1448: 8.47 | D1448: 0.65 | E1448: =E1447+1 -> 31 | F1448: =F1447 -> 3 | G1448: =G1424 -> 7 | H1448: =H1424+1 -> 2 | I1448: ;
B1449: 2.1 | C1449: 6.72 | D1449: 0.59 | E1449: =E1448+1 -> 32 | F1449: =F1448 -> 3 | G1449: =G1425 -> 8 | H1449: =H1425+1 -> 2 | I1449: ;
B1450: 2.17 | C1450: 8.68 | D1450: 1.88 | E1450: =E1449+1 -> 33 | F1450: =F1449 -> 3 | G1450: =G1426 -> 9 | H1450: =H1426+1 -> 2 | I1450: ;
B1451: 2.05 | C1451: 8.22 | D1451: 0.72 | E1451: =E1450+1 -> 34 | F1451: =F1450 -> 3 | G1451: =G1427 -> 10 | H1451: =H1427+1 -> 2 | I1451: ;
B1452: 1.68 | C1452: 8.45 | D1452: 1.35 | E1452: =E1451+1 -> 35 | F1452: =F1451 -> 3 | G1452: =G1428 -> 11 | H1452: =H1428+1 -> 2 | I1452: ;
B1453: 0.01 | C1453: 8.88 | D1453: 1.11 | E1453: =E1452+1 -> 36 | F1453: =F1452 -> 3 | G1453: =G1429 -> 12 | H1453: =H1429+1 -> 2 | I1453: ;
... B2161: 0.7 | C2161: 15.1 | D2161: 3.21 | E2161: =E2160+1 -> 744 | F2161: =F2160 -> 3 | G2161: =G2137 -> 24 | H2161: =H2137+1 -> 31 | I2161: ;
B2162: 0.02 | C2162: 16.38 | D2162: 2.51 | E2162: 1 | F2162: 4 | G2162: =G2138 -> 1 | H2162: 1 | I2162: ;
B2163: 0 | C2163: 17.4 | D2163: 2.76 | E2163: =E2162+1 -> 2 | F2163: =F2162 -> 4 | G2163: =G2139 -> 2 | H2163: 1 | I2163: ;
B2164: 0 | C2164: 17.9 | D2164: 3.21 | E2164: =E2163+1 -> 3 | F2164: =F2163 -> 4 | G2164: =G2140 -> 3 | H2164: 1 | I2164: ;
B2165: 0 | C2165: 17.99 | D2165: 3.05 | E2165: =E2164+1 -> 4 | F2165: =F2164 -> 4 | G2165: =G2141 -> 4 | H2165: 1 | I2165: ;
B2166: 0 | C2166: 17.62 | D2166: 1.23 | E2166: =E2165+1 -> 5 | F2166: =F2165 -> 4 | G2166: =G2142 -> 5 | H2166: 1 | I2166: ;
B2167: 0.13 | C2167: 17.87 | D2167: 1.45 | E2167: =E2166+1 -> 6 | F2167: =F2166 -> 4 | G2167: =G2143 -> 6 | H2167: 1 | I2167: ;
...

Sheet Industria
A1: % | B1: Periodo | C1: P KW | D1: Q kVARr | E1: horames | F1: mes | G1: horadia | H1: DIA | T1: P | V1: ©
A2: DBP=[ | B2: 6 | C2: 13.72 | D2: 14.25 | E2: 1 | F2: 1 | G2: 1 | H2: 1 | I2: ; | T2: kWh | U2: Fc | V2: kVArh
B3: 6 | C3: 14.3 | D3: 16.48 | E3: =E2+1 -> 2 | F3: =F2 -> 1 | G3: 2 | H3: 1 | I3: ; | S3: 0 | T3: =$Q$17*U3 -> 31.307452 | U3: 0.13538863 | V3: 27.875151
B4: 6 | C4: 13.76 | D4: 16.03 | E4: =E3+1 -> 3 | F4: =F3 -> 1 | G4: 3 | H4: 1 | I4: ; | S4: 1 | T4: =$Q$17*U4 -> 20.898959 | U4: 0.090377249 | V4: 22.371534
B5: 6 | C5: 14.47 | D5: 17.56 | E5: =E4+1 -> 4 | F5: =F4 -> 1 | G5: 4 | H5: 1 | I5: ; | S5: 2 | T5: =$Q$17*U5 -> 17.653808 | U5: 0.076343641 | V5: 20.669616
B6: 6 | C6: 13.89 | D6: 16.24 | E6: =E5+1 -> 5 | F6: =F5 -> 1 | G6: 5 | H6: 1 | I6: ; | S6: 3 | T6: =$Q$17*U6 -> 17.394959 | U6: 0.075224251 | V6: 20.802712
B7: 6 | C7: 14.18 | D7: 15.98 | E7: =E6+1 -> 6 | F7: =F6 -> 1 | G7: 6 | H7: 1 | I7: ; | S7: 4 | T7: =$Q$17*U7 -> 17.182986 | U7: 0.074307579 | V7: 20.762822
B8: 6 | C8: 13.79 | D8: 14.98 | E8: =E7+1 -> 7 | F8: =F7 -> 1 | G8: 7 | H8: 1 | I8: ; | S8: 5 | T8: =$Q$17*U8 -> 16.905041 | U8: 0.073105609 | V8: 20.711205
B9: 6 | C9: 13.64 | D9: 15.62 | E9: =E8+1 -> 8 | F9: =F8 -> 1 | G9: 8 | H9: 1 | I9: ; | S9: 6 | T9: =$Q$17*U9 -> 16.974548 | U9: 0.07340619 | V9: 20.580986
B10: 6 | C10: 14.44 | D10: 12.95 | E10: =E9+1 -> 9 | F10: =F9 -> 1 | G10: 9 | H10: 1 | I10: ; | S10: 7 | T10: =$Q$17*U10 -> 19.774932 | U10: 0.085516409 | V10: 21.413726
B11: 6 | C11: 15.19 | D11: 0 | E11: =E10+1 -> 10 | F11: =F10 -> 1 | G11: 10 | H11: 1 | I11: ; | S11: 8 | T11: =$Q$17*U11 -> 204.33975 | U11: 0.88366434 | V11: 141.48904
B12: 6 | C12: 15.59 | D12: 0 | E12: =E11+1 -> 11 | F12: =F11 -> 1 | G12: 11 | H12: 1 | I12: ; | S12: 9 | T12: =$Q$17*U12 -> 231.24137 | U12: 1 | V12: 95.876274
B13: 6 | C13: 14.44 | D13: 0 | E13: =E12+1 -> 12 | F13: =F12 -> 1 | G13: 12 | H13: 1 | I13: ; | S13: 10 | T13: =$Q$17*U13 -> 223.66726 | U13: 0.96724587 | V13: 91.472521
B14: 6 | C14: 15.19 | D14: 0 | E14: =E13+1 -> 13 | F14: =F13 -> 1 | G14: 13 | H14: 1 | I14: ; | S14: 11 | T14: =$Q$17*U14 -> 223.47403 | U14: 0.96641024 | V14: 126.74858
... B16: 6 | C16: 15.16 | D16: 0 | E16: =E15+1 -> 15 | F16: =F15 -> 1 | G16: 15 | H16: 1 | I16: ; | S16: 13 | T16: =$Q$17*U16 -> 206.30877 | U16: 0.89217932 | V16: 84.879041
B17: 6 | C17: 15.58 | D17: 0 | E17: =E16+1 -> 16 | F17: =F16 -> 1 | G17: 16 | H17: 1 | I17: ; | L17: Eactiva | M17: =SUM(C2:C8761) -> 959636.71 | N17: kWh | P17: PLMAX | Q17: 231.24137 | R17: KW | S17: 14 | T17: =$Q$17*U17 -> 224.04178 | U17: 0.96886548 | V17: 91.807945
B18: 6 | C18: 15.49 | D18: 0 | E18: =E17+1 -> 17 | F18: =F17 -> 1 | G18: 17 | H18: 1 | I18: ; | L18: Ereactiva | M18: =SUM(D2:D8761) -> 456759.84 | N18: kWh | S18: 15 | T18: =$Q$17*U18 -> 221.80392 | U18: 0.95918787 | V18: 91.090274
B19: 6 | C19: 14.86 | D19: 0 | E19: =E18+1 -> 18 | F19: =F18 -> 1 | G19: 18 | H19: 1 | I19: ; | L19: cosf | M19: =COS(ATAN(M18/M17)) -> 0.90293721 | N19: kWh | S19: 16 | T19: =$Q$17*U19 -> 219.05268 | U19: 0.94729021 | V19: 89.880685
B20: 6 | C20: 15.16 | D20: 0 | E20: =E19+1 -> 19 | F20: =F19 -> 1 | G20: 19 | H20: 1 | I20: ; | L20: maxP | M20: =MAX(C2:C8761) -> 564.3 | N20: kWh | S20: 17 | T20: =$Q$17*U20 -> 149.68 | U20: 0.64728902 | V20: 43.575068
B21: 6 | C21: 14.9 | D21: 0 | E21: =E20+1 -> 20 | F21: =F20 -> 1 | G21: 20 | H21: 1 | I21: ; | L21: FC | M21: =M17/8760/M20 -> 0.19413002 | S21: 18 | T21: =$Q$17*U21 -> 145.21233 | U21: 0.62796864 | V21: 64.533123
B22: 6 | C22: 15.54 | D22: 0 | E22: =E21+1 -> 21 | F22: =F21 -> 1 | G22: 21 | H22: 1 | I22: ; | S22: 19 | T22: =$Q$17*U22 -> 152.46567 | U22: 0.65933562 | V22: 54.343753
B23: 6 | C23: 14.87 | D23: 0 | E23: =E22+1 -> 22 | F23: =F22 -> 1 | G23: 22 | H23: 1 | I23: ; | S23: 20 | T23: =$Q$17*U23 -> 134.48767 | U23: 0.58159001 | V23: 40.603753
B24: 6 | C24: 14 | D24: 12.74 | E24: =E23+1 -> 23 | F24: =F23 -> 1 | G24: 23 | H24: 1 | I24: ; | S24: 21 | T24: =$Q$17*U24 -> 41.442603 | U24: 0.17921794 | V24: 3.4742192
B25: 6 | C25: 13.86 | D25: 13.79 | E25: =E24+1 -> 24 | F25: =F24 -> 1 | G25: 24 | H25: 1 | I25: ; | S25: 22 | T25: =$Q$17*U25 -> 33.502959 | U25: 0.14488307 | V25: 26.909671
B26: 6 | C26: 13.68 | D26: 14.98 | E26: =E25+1 -> 25 | F26: =F25 -> 1 | G26: =G2 -> 1 | H26: =H2+1 -> 2 | I26: ; | S26: 23 | T26: =$Q$17*U26 -> 31.920795 | U26: 0.13804102 | V26: 27.457562
B27: 6 | C27: 14.41 | D27: 17.03 | E27: =E26+1 -> 26 | F27: =F26 -> 1 | G27: =G3 -> 2 | H27: =H3+1 -> 2 | I27: ; | T27: =SUM(T3:T26) -> 2629.1417 | V27: =SUM(V3:V26) -> 1251.3968
B28: 6 | C28: 13.83 | D28: 15.99 | E28: =E27+1 -> 27 | F28: =F27 -> 1 | G28: =G4 -> 3 | H28: =H4+1 -> 2 | I28: ; | T28: kWh/dia | V28: kVArh/dia
B29: 6 | C29: 14.4 | D29: 16.73 | E29: =E28+1 -> 28 | F29: =F28 -> 1 | G29: =G5 -> 4 | H29: =H5+1 -> 2 | I29: ; | T29: =T27*365 -> 959636.71 | V29: =V27*365 -> 456759.84
B30: 6 | C30: 13.76 | D30: 15.01 | E30: =E29+1 -> 29 | F30: =F29 -> 1 | G30: =G6 -> 5 | H30: =H6+1 -> 2 | I30: ; | T30: kWh/año | V30: kVArh/año
B31: 6 | C31: 14.04 | D31: 15.23 | E31: =E30+1 -> 30 | F31: =F30 -> 1 | G31: =G7 -> 6 | H31: =H7+1 -> 2 | I31: ;
B32: 6 | C32: 13.86 | D32: 14.44 | E32: =E31+1 -> 31 | F32: =F31 -> 1 | G32: =G8 -> 7 | H32: =H8+1 -> 2 | I32: ;
B33: 6 | C33: 22.61 | D33: 17.39 | E33: =E32+1 -> 32 | F33: =F32 -> 1 | G33: =G9 -> 8 | H33: =H9+1 -> 2 | I33: ;
B34: 2 | C34: 183.47 | D34: 95.34 | E34: =E33+1 -> 33 | F34: =F33 -> 1 | G34: =G10 -> 9 | H34: =H10+1 -> 2 | I34: ;
B35: 1 | C35: 209.04 | D35: 22.26 | E35: =E34+1 -> 34 | F35: =F34 -> 1 | G35: =G11 -> 10 | H35: =H11+1 -> 2 | I35: ;
B36: 1 | C36: 265.79 | D36: 73.76 | E36: =E35+1 -> 35 | F36: =F35 -> 1 | G36: =G12 -> 11 | H36: =H12+1 -> 2 | I36: ;
B37: 1 | C37: 487.15 | D37: 269.68 | E37: =E36+1 -> 36 | F37: =F36 -> 1 | G37: =G13 -> 12 | H37: =H13+1 -> 2 | I37: ;
B38: 1 | C38: 43.95 | D38: 5.54 | E38: =E37+1 -> 37 | F38: =F37 -> 1 | G38: =G14 -> 13 | H38: =H14+1 -> 2 | I38: ;
B39: 1 | C39: 410.58 | D39: 167.22 | E39: =E38+1 -> 38 | F39: =F38 -> 1 | G39: =G15 -> 14 | H39: =H15+1 -> 2 | I39: ;
B40: 2 | C40: 478.19 | D40: 197.25 | E40: =E39+1 -> 39 | F40: =F39 -> 1 | G40: =G16 -> 15 | H40: =H16+1 -> 2 | I40: ;
B41: 2 | C41: 474.18 | D41: 210.88 | E41: =E40+1 -> 40 | F41: =F40 -> 1 | G41: =G17 -> 16 | H41: =H17+1 -> 2 | I41: ;
B42: 2 | C42: 456.56 | D42: 187.67 | E42: =E41+1 -> 41 | F42: =F41 -> 1 | G42: =G18 -> 17 | H42: =H18+1 -> 2 | I42: ;
... B52: 6 | C52: 18.46 | D52: 18.64 | E52: =E51+1 -> 51 | F52: =F51 -> 1 | G52: =G28 -> 3 | H52: =H28+1 -> 3 | I52: ;
B53: 6 | C53: 18.53 | D53: 18.97 | E53: =E52+1 -> 52 | F53: =F52 -> 1 | G53: =G29 -> 4 | H53: =H29+1 -> 3 | I53: ; | K53: 1 | L53: 2 | M53: 3 | N53: 4 | O53: 5 | P53: 6 | Q53: 7 | R53: 8 | S53: 9 | T53: 10 | U53: 11 | V53: 12 | W53: 13 | X53: 14 | Y53: 15 | Z53: 16 | AA53: 17 | AB53: 18 | AC53: 19 | AD53: 20 | AE53: 21 | AF53: 22 | AG53: 23 | AH53: 24 | AI53: 25 | AJ53: 26 | AK53: 27 | AL53: 28 | AM53: 29 | AN53: 30 | AO53: 31 | AP53: 1 | AQ53: 2 | AR53: 3 | AS53: 4 | AT53: 5 | AU53: 6 | AV53: 7 | AW53: 8 | AX53: 9 | AY53: 10 | AZ53: 11 | BA53: 12 | BB53: 13 | BC53: 14 | BD53: 15 | BE53: 16 | BF53: 17 | BG53: 18 | BH53: 19 | BI53: 20 | BJ53: 21 | BK53: 22 | BL53: 23 | BM53: 24 | BN53: 25 | BO53: 26 | BP53: 27 | BQ53: 28 | BR53: 1 | BS53: 2 | BT53: 3 | BU53: 4 | BV53: 5 | BW53: 6 | BX53: 7 | BY53: 8 | BZ53: 9 | CA53: 10 | CB53: 11 | CC53: 12 | CD53: 13 | CE53: 14 | CF53: 15 | CG53: 16 | CH53: 17 | CI53: 18 | CJ53: 19 | CK53: 20 | CL53: 21 | CM53: 22 | CN53: 23 | CO53: 24 | CP53: 25 | CQ53: 26 | CR53: 27 | CS53: 28 | CT53: 29 | CU53: 30 | CV53: 31 | CW53: 1 | CX53: 2 | CY53: 3 | CZ53: 4 | DA53: 5 | DB53: 6 | DC53: 7 | DD53: 8 | DE53: 9 | DF53: 10 | DG53: 11 | DH53: 12 | DI53: 13 | DJ53: 14 | DK53: 15 | DL53: 16 | DM53: 17 | DN53: 18 | DO53: 19 | DP53: 20 | DQ53: 21 | DR53: 22 | DS53: 23 | DT53: 24 | DU53: 25 | DV53: 26 | DW53: 27 | DX53: 28 | DY53: 29 | DZ53: 30 | EA53: 1 | EB53: 2 | EC53: 3 | ED53: 4 | EE53: 5 | EF53: 6 | EG53: 7 | EH53: 8 | EI53: 9 | EJ53: 10 | EK53: 11 | EL53: 12 | EM53: 13 | EN53: 14 | EO53: 15 | EP53: 16 | EQ53: 17 | ER53: 18 | ES53: 19 | ET53: 20 | EU53: 21 | EV53: 22 | EW53: 23 | EX53: 24 | EY53: 25 | EZ53: 26 | FA53: 27 | FB53: 28 | FC53: 29 | FD53: 30 | FE53: 1 | FF53: 2 | FG53: 3 | FH53: 4 | FI53: 5 | FJ53: 6 | FK53: 7 | FL53: 8 | FM53: 9 | FN53: 10 | FO53: 11 | FP53: 12 | FQ53: 13 | FR53: 14 | FS53: 15 | FT53: 16 | FU53: 17 | FV53: 18 | FW53: 19 | FX53: 20 | FY53: 21 | FZ53: 22 | GA53: 23 | GB53: 24 | GC53: 25 | GD53: 26 | GE53: 27 | GF53: 28 | GG53: 29 | GH53: 30 | GI53: 31 | GJ53: 1 | GK53: 2 | GL53: 3 | GM53: 4 | GN53: 5 | GO53: 6 | GP53: 7 | GQ53: 8 | GR53: 9 | GS53: 10 | GT53: 11 | GU53: 12 | GV53: 13 | GW53: 14 | GX53: 15 | GY53: 16 | GZ53: 17 | HA53: 18 | HB53: 19 | HC53: 20 | HD53: 21 | HE53: 22 | HF53: 23 | HG53: 24 | HH53: 25 | HI53: 26 | HJ53: 27 | HK53: 28 | HL53: 29 | HM53: 30 | HN53: 31 | HO53: 1 | HP53: 2 | HQ53: 3 | HR53: 4 | HS53: 5 | HT53: 6 | HU53: 7 | HV53: 8 | HW53: 9 | HX53: 10 | HY53: 11 | HZ53: 12 | IA53: 13 | IB53: 14 | IC53: 15 | ID53: 16 | IE53: 17 | IF53: 18 | IG53: 19 | IH53: 20 | II53: 21 | IJ53: 22 | IK53: 23 | IL53: 24 | IM53: 25 | IN53: 26 | IO53: 27 | IP53: 28 | IQ53: 29 | IR53: 30 | IS53: 31 | IT53: 1 | IU53: 2 | IV53: 3 | IW53: 4 | IX53: 5 | IY53: 6 | IZ53: 7 | JA53: 8 | JB53: 9 | JC53: 10 | JD53: 11 | JE53: 12 | JF53: 13 | JG53: 14 | JH53: 15 | JI53: 16 | JJ53: 17 | JK53: 18 | JL53: 19 | JM53: 20 | JN53: 21 | JO53: 22 | JP53: 23 | JQ53: 24 | JR53: 25 | JS53: 26 | JT53: 27 | JU53: 28 | JV53: 29 | JW53: 30 | JX53: 1 | JY53: 2 | JZ53: 3 | KA53: 4 | KB53: 5 | KC53: 6 | KD53: 7 | KE53: 8 | KF53: 9 | KG53: 10 | KH53: 11 | KI53: 12 | KJ53: 13 | KK53: 14 | KL53: 15 | KM53: 16 | KN53: 17 | KO53: 18 | KP53: 19 | KQ53: 20 | KR53: 21 | KS53: 22 | KT53: 23 | KU53: 24 | KV53: 25 | KW53: 26 | KX53: 27 | KY53: 28 | KZ53: 29 | LA53: 30 | LB53: 31 | LC53: 1 | LD53: 2 | LE53: 3 | LF53: 4 | LG53: 5 | LH53: 6 | LI53: 7 | LJ53: 8 | LK53: 9 | LL53: 10 | LM53: 11 | LN53: 12 | LO53: 13 | LP53: 14 | LQ53: 15 | LR53: 16 | LS53: 17 | LT53: 18 | LU53: 19 | LV53: 20 | LW53: 21 | LX53: 22 | LY53: 23 | LZ53: 24 | MA53: 25 | MB53: 26 | MC53: 27 | MD53: 28 | ME53: 29 | MF53: 30 | MG53: 1 | MH53: 2 | MI53: 3 | MJ53: 4 | MK53: 5 | ML53: 6 | MM53: 7 | MN53: 8 | MO53: 9 | MP53: 10 | MQ53: 11 | MR53: 12 | MS53: 13 | MT53: 14 | MU53: 15 | MV53: 16 | MW53: 17 | MX53: 18 | MY53: 19 | MZ53: 20 | NA53: 21 | NB53: 22 | NC53: 23 | ND53: 24 | NE53: 25 | NF53: 26 | NG53: 27 | NH53: 28 | NI53: 29 | NJ53: 30 | NK53: 31
B54: 6 | C54: 18.33 | D54: 17.42 | E54: =E53+1 -> 53 | F54: =F53 -> 1 | G54: =G30 -> 5 | H54: =H30+1 -> 3 | I54: ; | K54: 13.72 | L54: 13.68 | M54: 18.36 | N54: 18.5 | O54: 18.8 | P54: 16.52 | Q54: 13.46 | R54: 14.36 | S54: 18.79 | T54: 18.22 | U54: 18.47 | V54: 18.84 | W54: 18.61 | X54: 18.4 | Y54: 18.4 | Z54: 18.5 | AA54: 18.75 | AB54: 147.86 | AC54: 268.74 | AD54: 290.92 | AE54: 149.23 | AF54: 16.28 | AG54: 152.6 | AH54: 154.98 | AI54: 160.01 | AJ54: 149.9 | AK54: 210.2 | AL54: 16.44 | AM54: 18.8 | AN54: 329.54 | AO54: 303.83 | AP54: 324.72 | AQ54: 341.28 | AR54: 148.82 | AS54: 137.6 | AT54: 17.86 | AU54: 284.58 | AV54: 161.24 | AW54: 119.02 | AX54: 204.97 | AY54: 310.07 | AZ54: 17.31 | BA54: 15.92 | BB54: 194.15 | BC54: 238.76 | BD54: 14.19 | BE54: 12.53 | BF54: 13.04 | BG54: 13 | BH54: 13.87 | BI54: 355.91 | BJ54: 361.8 | BK54: 319.89 | BL54: 165.02 | BM54: 316.08 | BN54: 203.29 | BO54: 15.3 | BP54: 23 | BQ54: 23.98 | BR54: 18.9 | BS54: 13.04 | BT54: 13.5 | BU54: 12.38 | BV54: 12.17 | BW54: 26.97 | BX54: 17.68 | BY54: 12.43 | BZ54: 19.76 | CA54: 12.56 | CB54: 13.36 | CC54: 15.41 | CD54: 18.11 | CE54: 15.31 | CF54: 13.61 | CG54: 15.01 | CH54: 14.76 | CI54: 12.13 | CJ54: 12.82 | CK54: 14.66 | CL54: 15.69 | CM54: 15.58 | CN54: 16.6 | CO54: 14.72 | CP54: 12.16 | CQ54: 12.46 | CR54: 14.97 | CS54: 14.55 | CT54: 14.52 | CU54: 14 | CV54: 13.6 | CW54: 11.09 | CX54: 11.99 | CY54: 14.65 | CZ54: 14.59 | DA54: 16.49 | DB54: 15.4 | DC54: 14.94 | DD54: 13.17 | DE54: 12.89 | DF54: 14.18 | DG54: 15.31 | DH54: 14.62 | DI54: 16.53 | DJ54: 14.43 | DK54: 13.4 | DL54: 13.21 | DM54: 15.15 | DN54: 14.51 | DO54: 12.78 | DP54: 14.32 | DQ54: 13.94 | DR54: 12.17 | DS54: 12.68 | DT54: 15.31 | DU54: 14.4 | DV54: 14.69 | DW54: 14.32 | DX54: 12.82 | DY54: 10.44 | DZ54: 11.6 | EA54: 11.56 | EB54: 11.59 | EC54: 14.9 | ED54: 14.51 | EE54: 16.34 | EF54: 11.95 | EG54: 12.67 | EH54: 14.48 | EI54: 16.1 | EJ54: 14.36 | EK54: 16.09 | EL54: 14.29 | EM54: 11.63 | EN54: 12.39 | EO54: 14.05 | EP54: 15.27 | EQ54: 13.9 | ER54: 15.02 | ES54: 14.59 | ET54: 12.78 | EU54: 12.38 | EV54: 12.23 | EW54: 13.75 | EX54: 12.56 | EY54: 14.39 | EZ54: 13.97 | FA54: 11.05 | FB54: 11.59 | FC54: 12.85 | FD54: 12.17 | FE54: 13.18 | FF54: 12.38 | FG54: 13.67 | FH54: 13.5 | FI54: 11.55 | FJ54: 13.98 | FK54: 14.35 | FL54: 11.95 | FM54: 13.68 | FN54: 12.71 | FO54: 12.06 | FP54: 12.36 | FQ54: 16.46 | FR54: 12.92 | FS54: 12.09 | FT54: 14.01 | FU54: 14.07 | FV54: 11.99 | FW54: 10.99 | FX54: 11.35 | FY54: 12.43 | FZ54: 14.95 | GA54: 11.95 | GB54: 11.95 | GC54: 10.27 | GD54: 11.55 | GE54: 10.4 | GF54: 11.09 | GG54: 11.67 | GH54: 12.59 | GI54: 12.28 | GJ54: 11.38 | GK54: 11.81 | GL54: 11.59 | GM54: 12.67 | GN54: 13.21 | GO54: 13.22 | GP54: 12.78 | GQ54: 11.71 | GR54: 11.62 | GS54: 13.64 | GT54: 13.43 | GU54: 12.39 | GV54: 10.98 | GW54: 10.56 | GX54: 11.36 | GY54: 11.6 | GZ54: 11.77 | HA54: 10.88 | HB54: 11.41 | HC54: 11.8 | HD54: 12.24 | HE54: 11.7 | HF54: 11.92 | HG54: 12.14 | HH54: 12.05 | HI54: 10.55 | HJ54: 11.26 | HK54: 11.53 | HL54: 11.01 | HM54: 10.76 | HN54: 12.67 | HO54: 11.15 | HP54: 10.65 | HQ54: 12.02 | HR54: 11.12 | HS54: 11.74 | HT54: 10.61 | HU54: 11.3 | HV54: 12.53 | HW54: 11.45 | HX54: 10.72 | HY54: 10.91 | HZ54: 10.88 | IA54: 11.6 | IB54: 12.17 | IC54: 10.7 | ID54: 11.01 | IE54: 11.19 | IF54: 10.8 | IG54: 10.47 | IH54: 12.3 | II54: 11.2 | IJ54: 10.55 | IK54: 12.29 | IL54: 11.71 | IM54: 10.88 | IN54: 10.44 | IO54: 11.88 | IP54: 10.33 | IQ54: 11.09 | IR54: 11.74 | IS54: 10.84 | IT54: 12.01 | IU54: 10.55 | IV54: 11.57 | IW54: 10.72 | IX54: 10 | IY54: 11.23 | IZ54: 13.28 | JA54: 12.83 | JB54: 11.8 | JC54: 11.19 | JD54: 10.38 | JE54: 11.71 | JF54: 11.31 | JG54: 15.7 | JH54: 10.59 | JI54: 10.91 | JJ54: 10.95 | JK54: 13.35 | JL54: 10.98 | JM54: 11.59 | JN54: 12.32 | JO54: 10.23 | JP54: 10.16 | JQ54: 10.59 | JR54: 11.52 | JS54: 10.51 | JT54: 10.65 | JU54: 11.37 | JV54: 10.19 | JW54: 11.02 | JX54: 11.12 | JY54: 10.27 | JZ54: 13.52 | KA54: 11.81 | KB54: 13.89 | KC54: 13 | KD54: 10.55 | KE54: 12.14 | KF54: 14.54 | KG54: 11.55 | KH54: 14.19 | KI54: 14.25 | KJ54: 14.4 | KK54: 11.17 | KL54: 12 | KM54: 16.63 | KN54: 14.72 | KO54: 15.81 | KP54: 14.62 | KQ54: 136.48 | KR54: 11.06 | KS54: 11.38 | KT54: 14.66 | KU54: 17.47 | KV54: 12.78 | KW54: 15.08 | KX54: 14.62 | KY54: 12.06 | KZ54: 11.12 | LA54: 14.65 | LB54: 14.47 | LC54: 17.68 | LD54: 13.42 | LE54: 17 | LF54: 11.67 | LG54: 12.81 | LH54: 14.83 | LI54: 14.47 | LJ54: 14.62 | LK54: 14.18 | LL54: 19.44 | LM54: 11.05 | LN54: 12.31 | LO54: 19.23 | LP54: 120.34 | LQ54: 15.66 | LR54: 16.28 | LS54: 16.99 | LT54: 12.73 | LU54: 13.17 | LV54: 14.48 | LW54: 14.56 | LX54: 15.01 | LY54: 16.27 | LZ54: 14.17 | MA54: 12.31 | MB54: 13.68 | MC54: 18.98 | MD54: 94.46 | ME54: 15.92 | MF54: 16.07 | MG54: 15.52 | MH54: 13.97 | MI54: 16.35 | MJ54: 18.43 | MK54: 15.66 | ML54: 17.96 | MM54: 16.02 | MN54: 15.96 | MO54: 15.15 | MP54: 13.24 | MQ54: 17.46 | MR54: 16.63 | MS54: 16.63 | MT54: 21.17 | MU54: 16.45 | MV54: 13.65 | MW54: 16.85 | MX54: 18.14 | MY54: 16.63 | MZ54: 16.06 | NA54: 15.52 | NB54: 16.1 | NC54: 15.01 | ND54: 14.07 | NE54: 15.51 | NF54: 12.99 | NG54: 14.8 | NH54: 15.51 | NI54: 17.31 | NJ54: 15.26 | NK54: 14.15
B55: 6 | C55: 18.25 | D55: 17.28 | E55: =E54+1 -> 54 | F55: =F54 -> 1 | G55: =G31 -> 6 | H55: =H31+1 -> 3 | I55: ; | K55: 14.3 | L55: 14.41 | M55: 18.46 | N55: 18.54 | O55: 18.58 | P55: 16.64 | Q55: 14.1 | R55: 13.97 | S55: 18.9 | T55: 18.43 | U55: 18.51 | V55: 19.05 | W55: 18.68 | X55: 18.57 | Y55: 18.43 | Z55: 18.53 | AA55: 18.79 | AB55: 132.62 | AC55: 129.74 | AD55: 336.38 | AE55: 158.91 | AF55: 16.78 | AG55: 122.98 | AH55: 128.87 | AI55: 150.05 | AJ55: 154.81 | AK55: 205.24 | AL55: 17.9 | AM55: 16.78 | AN55: 114.48 | AO55: 183.78 | AP55: 109.86 | AQ55: 39.42 | AR55: 81.22 | AS55: 41.04 | AT55: 16.89 | AU55: 32.11 | AV55: 37.77 | AW55: 34.67 | AX55: 67.64 | AY55: 35.25 | AZ55: 16.16 | BA55: 17.03 | BB55: 200.99 | BC55: 57.56 | BD55: 13.83 | BE55: 13.83 | BF55: 13.21 | BG55: 12.78 | BH55: 14.11 | BI55: 93.35 | BJ55: 55.47 | BK55: 100.05 | BL55: 49.68 | BM55: 80.21 | BN55: 30.6 | BO55: 15.48 | BP55: 20.09 | BQ55: 22.9 | BR55: 14.65 | BS55: 14.79 | BT55: 13.52 | BU55: 12.71 | BV55: 13.9 | BW55: 27.1 | BX55: 12.67 | BY55: 13.62 | BZ55: 19.8 | CA55: 12.35 | CB55: 12.47 | CC55: 15.52 | CD55: 18.22 | CE55: 15.41 | CF55: 13.75 | CG55: 15.01 | CH55: 14.83 | CI55: 12.93 | CJ55: 12.35 | CK55: 13.65 | CL55: 15.63 | CM55: 15.67 | CN55: 15.55 | CO55: 14.83 | CP55: 12.38 | CQ55: 12.42 | CR55: 14.98 | CS55: 14.47 | CT55: 14.22 | CU55: 14 | CV55: 11.31 | CW55: 11.95 | CX55: 11.99 | CY55: 14.66 | CZ55: 14.62 | DA55: 12.27 | DB55: 15.48 | DC55: 15.05 | DD55: 12.64 | DE55: 12.36 | DF55: 14.76 | DG55: 15.24 | DH55: 14.58 | DI55: 16.2 | DJ55: 14.58 | DK55: 13.04 | DL55: 12.5 | DM55: 14.26 | DN55: 14.62 | DO55: 13.07 | DP55: 15.65 | DQ55: 13.96 | DR55: 12.2 | DS55: 13.54 | DT55: 13.54 | DU55: 14.04 | DV55: 13.85 | DW55: 15.99 | DX55: 13.11 | DY55: 10.4 | DZ55: 12.48 | EA55: 12.74 | EB55: 13.47 | EC55: 14.76 | ED55: 14.29 | EE55: 12.49 | EF55: 12.71 | EG55: 12.59 | EH55: 14.55 | EI55: 12.57 | EJ55: 15.92 | EK55: 14.66 | EL55: 13.35 | EM55: 12.31 | EN55: 13.06 | EO55: 13.72 | EP55: 15.45 | EQ55: 13.42 | ER55: 15.18 | ES55: 13.65 | ET55: 12.28 | EU55: 11.99 | EV55: 12.89 | EW55: 12.09 | EX55: 12.71 | EY55: 13.86 | EZ55: 12.5 | FA55: 11.2 | FB55: 11.7 | FC55: 12.92 | FD55: 12.28 | FE55: 12.84 | FF55: 12.42 | FG55: 11.64 | FH55: 11.77 | FI55: 12.31 | FJ55: 14.11 | FK55: 14.44 | FL55: 12.82 | FM55: 11.92 | FN55: 11.59 | FO55: 12.05 | FP55: 11.6 | FQ55: 12.6 | FR55: 12.36 | FS55: 11.3 | FT55: 11.92 | FU55: 11.48 | FV55: 11.89 | FW55: 11.12 | FX55: 11.06 | FY55: 13.37 | FZ55: 11.56 | GA55: 11.98 | GB55: 11.92 | GC55: 10.33 | GD55: 12.92 | GE55: 10.54 | GF55: 11.16 | GG55: 12.67 | GH55: 11.88 | GI55: 11.52 | GJ55: 11.44 | GK55: 12.1 | GL55: 12.05 | GM55: 11.44 | GN55: 12.77 | GO55: 12.57 | GP55: 13.54 | GQ55: 11.27 | GR55: 10.95 | GS55: 12.06 | GT55: 11.63 | GU55: 11.84 | GV55: 11.17 | GW55: 10.65 | GX55: 12.31 | GY55: 11.63 | GZ55: 11.95 | HA55: 11.41 | HB55: 11.88 | HC55: 11.48 | HD55: 12.27 | HE55: 11.52 | HF55: 13.57 | HG55: 11.64 | HH55: 12.17 | HI55: 12.74 | HJ55: 11.44 | HK55: 13.35 | HL55: 11.23 | HM55: 11.02 | HN55: 11.48 | HO55: 10.69 | HP55: 11.41 | HQ55: 11.59 | HR55: 12.42 | HS55: 11.12 | HT55: 10.76 | HU55: 11.78 | HV55: 12.78 | HW55: 11.02 | HX55: 10.76 | HY55: 11.78 | HZ55: 10.95 | IA55: 11.12 | IB55: 11.44 | IC55: 10.44 | ID55: 10.77 | IE55: 11.09 | IF55: 10.65 | IG55: 10.44 | IH55: 11.08 | II55: 10.8 | IJ55: 10.47 | IK55: 12.03 | IL55: 11.71 | IM55: 11.13 | IN55: 10.44 | IO55: 11.77 | IP55: 10.95 | IQ55: 10.87 | IR55: 10.87 | IS55: 10.91 | IT55: 12.02 | IU55: 10.73 | IV55: 10.99 | IW55: 10.83 | IX55: 10.03 | IY55: 11.3 | IZ55: 13.25 | JA55: 12.35 | JB55: 11.16 | JC55: 11.7 | JD55: 11.38 | JE55: 11.81 | JF55: 10.9 | JG55: 14.44 | JH55: 11.7 | JI55: 10.91 | JJ55: 12.57 | JK55: 11.84 | JL55: 10.87 | JM55: 10.8 | JN55: 11.38 | JO55: 10.16 | JP55: 10.3 | JQ55: 10.51 | JR55: 10.55 | JS55: 10.47 | JT55: 10.34 | JU55: 11.81 | JV55: 11.23 | JW55: 10.27 | JX55: 11.05 | JY55: 10.8 | JZ55: 14.87 | KA55: 11.06 | KB55: 13.25 | KC55: 12.45 | KD55: 10.2 | KE55: 10.44 | KF55: 11.7 | KG55: 11.31 | KH55: 14.22 | KI55: 14.32 | KJ55: 14.4 | KK55: 11.76 | KL55: 12.06 | KM55: 13.18 | KN55: 16.31 | KO55: 14.32 | KP55: 14.52 | KQ55: 19.79 | KR55: 11.12 | KS55: 12.24 | KT55: 14.69 | KU55: 15 | KV55: 12.09 | KW55: 14.04 | KX55: 15.52 | KY55: 11.3 | KZ55: 12.16 | LA55: 14.73 | LB55: 14.87 | LC55: 15.66 | LD55: 12.36 | LE55: 15.23 | LF55: 11.81 | LG55: 11.74 | LH55: 14.8 | LI55: 14.4 | LJ55: 14.58 | LK55: 11.48 | LL55: 20.78 | LM55: 11.19 | LN55: 11.22 | LO55: 16.63 | LP55: 43.56 | LQ55: 14.21 | LR55: 14.97 | LS55: 15.81 | LT55: 13.81 | LU55: 11.67 | LV55: 14.48 | LW55: 12.31 | LX55: 16.09 | LY55: 14.58 | LZ55: 14.21 | MA55: 13 | MB55: 12.46 | MC55: 20.96 | MD55: 94.5 | ME55: 16.1 | MF55: 18.15 | MG55: 15.76 | MH55: 16.49 | MI55: 13.64 | MJ55: 19.12 | MK55: 15.27 | ML55: 15.91 | MM55: 16.19 | MN55: 17.86 | MO55: 15.16 | MP55: 12.79 | MQ55: 16.96 | MR55: 18.47 | MS55: 18.07 | MT55: 20.74 | MU55: 16.52 | MV55: 16.24 | MW55: 17.13 | MX55: 16.53 | MY55: 16.64 | MZ55: 16.17 | NA55: 15.63 | NB55: 15.98 | NC55: 16.63 | ND55: 14.11 | NE55: 14.32 | NF55: 13 | NG55: 15.3 | NH55: 16.71 | NI55: 15.01 | NJ55: 12.71 | NK55: 14.18
B56: 6 | C56: 18.36 | D56: 17.79 | E56: =E55+1 -> 55 | F56: =F55 -> 1 | G56: =G32 -> 7 | H56: =H32+1 -> 3 | I56: ; | K56: 13.76 | L56: 13.83 | M56: 18.46 | N56: 18.54 | O56: 18.6 | P56: 16.85 | Q56: 13.79 | R56: 14.25 | S56: 18.79 | T56: 18.29 | U56: 18.36 | V56: 19.12 | W56: 18.94 | X56: 18.57 | Y56: 18.4 | Z56: 18.61 | AA56: 18.95 | AB56: 150.29 | AC56: 290.49 | AD56: 284.69 | AE56: 153.22 | AF56: 16.34 | AG56: 143.1 | AH56: 122.8 | AI56: 132.51 | AJ56: 120.64 | AK56: 26.92 | AL56: 17.49 | AM56: 18.44 | AN56: 24.56 | AO56: 23.94 | AP56: 24.98 | AQ56: 25.45 | AR56: 24.34 | AS56: 23.65 | AT56: 16.7 | AU56: 25.35 | AV56: 23.87 | AW56: 24.34 | AX56: 23.68 | AY56: 26.39 | AZ56: 16.2 | BA56: 16.02 | BB56: 24.19 | BC56: 20.67 | BD56: 13.44 | BE56: 12.61 | BF56: 13.89 | BG56: 14.25 | BH56: 14.22 | BI56: 23.39 | BJ56: 23.44 | BK56: 24.01 | BL56: 24.19 | BM56: 24.02 | BN56: 23.47 | BO56: 17.99 | BP56: 15.56 | BQ56: 16.44 | BR56: 14.8 | BS56: 13.93 | BT56: 15.4 | BU56: 12.64 | BV56: 12.12 | BW56: 22.18 | BX56: 12.67 | BY56: 12.53 | BZ56: 19.95 | CA56: 12.99 | CB56: 12.59 | CC56: 15.48 | CD56: 15.88 | CE56: 15.08 | CF56: 13.75 | CG56: 13.24 | CH56: 12.56 | CI56: 12.16 | CJ56: 12.36 | CK56: 12.47 | CL56: 13.47 | CM56: 16.74 | CN56: 15.19 | CO56: 16.5 | CP56: 12.86 | CQ56: 13.18 | CR56: 16.59 | CS56: 14.15 | CT56: 13.13 | CU56: 14.5 | CV56: 11.06 | CW56: 11.12 | CX56: 11.45 | CY56: 14.58 | CZ56: 13.97 | DA56: 12.24 | DB56: 14.14 | DC56: 14.98 | DD56: 12.74 | DE56: 12.36 | DF56: 15.47 | DG56: 13.57 | DH56: 13.65 | DI56: 13.93 | DJ56: 15.3 | DK56: 12.85 | DL56: 13.6 | DM56: 13.39 | DN56: 16.71 | DO56: 12.16 | DP56: 12.3 | DQ56: 12.39 | DR56: 12.99 | DS56: 13.43 | DT56: 13.75 | DU56: 13.06 | DV56: 12.78 | DW56: 12.7 | DX56: 14.22 | DY56: 10.47 | DZ56: 12.5 | EA56: 11.67 | EB56: 11.63 | EC56: 14.9 | ED56: 16.13 | EE56: 12.02 | EF56: 11.91 | EG56: 12.07 | EH56: 12.75 | EI56: 12.67 | EJ56: 12.2 | EK56: 14.36 | EL56: 12.41 | EM56: 12.06 | EN56: 11.88 | EO56: 11.48 | EP56: 14.58 | EQ56: 12.53 | ER56: 12.67 | ES56: 12.21 | ET56: 13.28 | EU56: 11.95 | EV56: 12.2 | EW56: 12.06 | EX56: 11.81 | EY56: 11.59 | EZ56: 13.54 | FA56: 12.6 | FB56: 12.5 | FC56: 12.02 | FD56: 11.74 | FE56: 11.88 | FF56: 11.88 | FG56: 11.74 | FH56: 11.98 | FI56: 11.7 | FJ56: 14.07 | FK56: 13.36 | FL56: 12.7 | FM56: 11.48 | FN56: 11.74 | FO56: 11.34 | FP56: 12.63 | FQ56: 12.46 | FR56: 11.44 | FS56: 11.41 | FT56: 11.56 | FU56: 11.56 | FV56: 11.05 | FW56: 12.71 | FX56: 11.02 | FY56: 12.39 | FZ56: 11.67 | GA56: 12.16 | GB56: 10.8 | GC56: 10.41 | GD56: 11.56 | GE56: 10.61 | GF56: 11.23 | GG56: 12.24 | GH56: 12.06 | GI56: 11.6 | GJ56: 11.48 | GK56: 12.1 | GL56: 11.27 | GM56: 11.45 | GN56: 12.2 | GO56: 12.88 | GP56: 12.63 | GQ56: 11.27 | GR56: 11.02 | GS56: 11.92 | GT56: 11.06 | GU56: 12.02 | GV56: 11.48 | GW56: 11.52 | GX56: 12.17 | GY56: 12.35 | GZ56: 12.42 | HA56: 12.1 | HB56: 11.92 | HC56: 11.37 | HD56: 14.01 | HE56: 12.46 | HF56: 11.78 | HG56: 12.29 | HH56: 11.98 | HI56: 13.86 | HJ56: 12.02 | HK56: 14.26 | HL56: 10.68 | HM56: 11.95 | HN56: 12.41 | HO56: 10.76 | HP56: 10.88 | HQ56: 12.09 | HR56: 11.8 | HS56: 11.27 | HT56: 11.27 | HU56: 12.17 | HV56: 13.35 | HW56: 11.77 | HX56: 11.59 | HY56: 10.76 | HZ56: 11.66 | IA56: 11.19 | IB56: 12.23 | IC56: 12.09 | ID56: 11.58 | IE56: 11.56 | IF56: 10.91 | IG56: 11.38 | IH56: 10.8 | II56: 11.74 | IJ56: 10.73 | IK56: 15.23 | IL56: 11.66 | IM56: 11.99 | IN56: 11.38 | IO56: 12.61 | IP56: 10.33 | IQ56: 11.01 | IR56: 10.75 | IS56: 11.63 | IT56: 12.45 | IU56: 10.62 | IV56: 11.92 | IW56: 11.23 | IX56: 12.17 | IY56: 11.59 | IZ56: 11.81 | JA56: 12.39 | JB56: 11.36 | JC56: 11.45 | JD56: 11.23 | JE56: 11.67 | JF56: 12.13 | JG56: 13.21 | JH56: 10.66 | JI56: 11.74 | JJ56: 11.05 | JK56: 11.8 | JL56: 10.99 | JM56: 11.2 | JN56: 11.41 | JO56: 11.05 | JP56: 11.05 | JQ56: 10.58 | JR56: 11.34 | JS56: 11.09 | JT56: 10.3 | JU56: 13.64 | JV56: 10.11 | JW56: 10.38 | JX56: 10.7 | JY56: 11.56 | JZ56: 14.14 | KA56: 11.03 | KB56: 11.16 | KC56: 11.52 | KD56: 10.16 | KE56: 10.48 | KF56: 10.51 | KG56: 12.17 | KH56: 14.55 | KI56: 14.76 | KJ56: 13.78 | KK56: 11.77 | KL56: 11.23 | KM56: 12.54 | KN56: 15.48 | KO56: 14.55 | KP56: 14.87 | KQ56: 14.29 | KR56: 12.49 | KS56: 12.35 | KT56: 16.49 | KU56: 15.12 | KV56: 13 | KW56: 12.03 | KX56: 13.07 | KY56: 11.37 | KZ56: 12.16 | LA56: 14.07 | LB56: 15.56 | LC56: 15.66 | LD56: 13.24 | LE56: 14.37 | LF56: 13 | LG56: 12.81 | LH56: 16.2 | LI56: 11.77 | LJ56: 13.64 | LK56: 11.67 | LL56: 17.1 | LM56: 14.14 | LN56: 11.16 | LO56: 14.75 | LP56: 14.58 | LQ56: 16.3 | LR56: 13.61 | LS56: 13.57 | LT56: 13.83 | LU56: 12.64 | LV56: 13.16 | LW56: 11.63 | LX56: 14.66 | LY56: 12.3 | LZ56: 14.32 | MA56: 11.76 | MB56: 11.85 | MC56: 18.88 | MD56: 96.01 | ME56: 16.81 | MF56: 16.12 | MG56: 17.21 | MH56: 14.46 | MI56: 15.3 | MJ56: 14.51 | MK56: 17.17 | ML56: 13.43 | MM56: 17.65 | MN56: 16.1 | MO56: 13.32 | MP56: 14.73 | MQ56: 16.3 | MR56: 16.89 | MS56: 17.43 | MT56: 16.71 | MU56: 16.59 | MV56: 14.37 | MW56: 16.13 | MX56: 16.71 | MY56: 18.47 | MZ56: 17.71 | NA56: 15.72 | NB56: 15.12 | NC56: 13.79 | ND56: 14.87 | NE56: 12.78 | NF56: 17.07 | NG56: 16.56 | NH56: 15.28 | NI56: 15.02 | NJ56: 12.39 | NK56: 12.13
B57: 6 | C57: 28.08 | D57: 17.47 | E57: =E56+1 -> 56 | F57: =F56 -> 1 | G57: =G33 -> 8 | H57: =H33+1 -> 3 | I57: ; | K57: 14.47 | L57: 14.4 | M57: 18.53 | N57: 18.58 | O57: 18.62 | P57: 16.78 | Q57: 13.76 | R57: 14.4 | S57: 18.84 | T57: 18.29 | U57: 18.32 | V57: 18.97 | W57: 19.01 | X57: 18.07 | Y57: 18.54 | Z57: 18.5 | AA57: 18.76 | AB57: 150.15 | AC57: 195.19 | AD57: 304.88 | AE57: 155.64 | AF57: 16.3 | AG57: 154.08 | AH57: 166.06 | AI57: 133.23 | AJ57: 154.22 | AK57: 23.84 | AL57: 16.88 | AM57: 17.39 | AN57: 23.26 | AO57: 23.32 | AP57: 24.91 | AQ57: 25.45 | AR57: 23.87 | AS57: 23.34 | AT57: 17.42 | AU57: 25.28 | AV57: 23.72 | AW57: 24.11 | AX57: 22.46 | AY57: 26.14 | AZ57: 17.46 | BA57: 17.35 | BB57: 23.83 | BC57: 20.63 | BD57: 13.82 | BE57: 13.67 | BF57: 12.78 | BG57: 12.74 | BH57: 13.11 | BI57: 23.58 | BJ57: 21.35 | BK57: 23.79 | BL57: 23.79 | BM57: 23.76 | BN57: 19.84 | BO57: 15.28 | BP57: 15.63 | BQ57: 16.48 | BR57: 16.56 | BS57: 13.22 | BT57: 13.6 | BU57: 13.64 | BV57: 12.31 | BW57: 18.68 | BX57: 14.87 | BY57: 13.14 | BZ57: 19.98 | CA57: 12.81 | CB57: 13.43 | CC57: 14.29 | CD57: 14.9 | CE57: 13.12 | CF57: 13.82 | CG57: 12.77 | CH57: 12.35 | CI57: 12.16 | CJ57: 13.18 | CK57: 12.36 | CL57: 13.28 | CM57: 13.47 | CN57: 13.18 | CO57: 14.83 | CP57: 13.21 | CQ57: 12.61 | CR57: 12.93 | CS57: 13.11 | CT57: 12.16 | CU57: 11.82 | CV57: 11.63 | CW57: 11.27 | CX57: 11.33 | CY57: 13.82 | CZ57: 13.25 | DA57: 12.75 | DB57: 13.25 | DC57: 14.79 | DD57: 14.58 | DE57: 13.86 | DF57: 14.25 | DG57: 13.73 | DH57: 12.39 | DI57: 13.68 | DJ57: 12.35 | DK57: 12.52 | DL57: 12.46 | DM57: 12.67 | DN57: 14.3 | DO57: 12.95 | DP57: 12.09 | DQ57: 12.82 | DR57: 12.32 | DS57: 12.67 | DT57: 13.06 | DU57: 12.2 | DV57: 12.5 | DW57: 12.13 | DX57: 12.1 | DY57: 11.84 | DZ57: 11.48 | EA57: 11.71 | EB57: 11.56 | EC57: 13.82 | ED57: 14.11 | EE57: 11.74 | EF57: 12.1 | EG57: 11.99 | EH57: 12.08 | EI57: 13.42 | EJ57: 12.24 | EK57: 12.53 | EL57: 11.95 | EM57: 12.74 | EN57: 11.88 | EO57: 11.55 | EP57: 13.06 | EQ57: 12.57 | ER57: 12.75 | ES57: 12.86 | ET57: 13.18 | EU57: 12.7 | EV57: 13.03 | EW57: 12.2 | EX57: 12.53 | EY57: 12.42 | EZ57: 12.53 | FA57: 11.35 | FB57: 11.91 | FC57: 12.81 | FD57: 12.09 | FE57: 11.71 | FF57: 11.88 | FG57: 12.36 | FH57: 11.92 | FI57: 12.28 | FJ57: 12.6 | FK57: 12.2 | FL57: 11.95 | FM57: 11.56 | FN57: 12.42 | FO57: 11.34 | FP57: 11.64 | FQ57: 12.53 | FR57: 12.13 | FS57: 12.06 | FT57: 11.95 | FU57: 11.48 | FV57: 11.08 | FW57: 11.09 | FX57: 11.74 | FY57: 13.29 | FZ57: 11.74 | GA57: 12.89 | GB57: 10.8 | GC57: 12.32 | GD57: 11.48 | GE57: 11.52 | GF57: 11.59 | GG57: 11.71 | GH57: 12.64 | GI57: 11.98 | GJ57: 13.21 | GK57: 11.84 | GL57: 11.95 | GM57: 11.41 | GN57: 12.31 | GO57: 12.74 | GP57: 12.56 | GQ57: 11.91 | GR57: 11.06 | GS57: 11.47 | GT57: 11.15 | GU57: 12.67 | GV57: 11.73 | GW57: 11.98 | GX57: 11.55 | GY57: 11.63 | GZ57: 12.17 | HA57: 11.63 | HB57: 12.53 | HC57: 11.39 | HD57: 13.29 | HE57: 11.38 | HF57: 11.51 | HG57: 11.98 | HH57: 13.07 | HI57: 13.43 | HJ57: 11.56 | HK57: 14.8 | HL57: 10.84 | HM57: 11.01 | HN57: 11.81 | HO57: 10.95 | HP57: 11.01 | HQ57: 11.37 | HR57: 11.34 | HS57: 11.73 | HT57: 10.74 | HU57: 13.78 | HV57: 12.82 | HW57: 11.05 | HX57: 11.02 | HY57: 11.81 | HZ57: 11.15 | IA57: 10.88 | IB57: 12.95 | IC57: 10.51 | ID57: 10.88 | IE57: 11.37 | IF57: 10.4 | IG57: 10.98 | IH57: 10.68 | II57: 11.02 | IJ57: 11.81 | IK57: 17.53 | IL57: 13.93 | IM57: 11.98 | IN57: 10.91 | IO57: 11.71 | IP57: 10.19 | IQ57: 11.13 | IR57: 11.15 | IS57: 11.03 | IT57: 13.22 | IU57: 10.73 | IV57: 11.53 | IW57: 11.74 | IX57: 10 | IY57: 12.56 | IZ57: 11.85 | JA57: 13.18 | JB57: 12.05 | JC57: 12.38 | JD57: 10.47 | JE57: 13.89 | JF57: 10.99 | JG57: 13.22 | JH57: 11.27 | JI57: 12.03 | JJ57: 11.12 | JK57: 11.92 | JL57: 12.14 | JM57: 11.63 | JN57: 11.47 | JO57: 11.2 | JP57: 11.05 | JQ57: 11.77 | JR57: 10.51 | JS57: 11.49 | JT57: 11.09 | JU57: 11.73 | JV57: 10.36 | JW57: 11.16 | JX57: 10.55 | JY57: 10.37 | JZ57: 11.89 | KA57: 11.73 | KB57: 11.34 | KC57: 12.92 | KD57: 11.09 | KE57: 11.02 | KF57: 10.43 | KG57: 11.37 | KH57: 13.54 | KI57: 13.93 | KJ57: 11.23 | KK57: 11.06 | KL57: 11.2 | KM57: 12.43 | KN57: 13.18 | KO57: 13.03 | KP57: 14.79 | KQ57: 14 | KR57: 12.36 | KS57: 12.03 | KT57: 12.74 | KU57: 16.02 | KV57: 13.09 | KW57: 11.51 | KX57: 12.56 | KY57: 11.99 | KZ57: 11.24 | LA57: 11.67 | LB57: 12.96 | LC57: 13.14 | LD57: 12.63 | LE57: 12.88 | LF57: 13.18 | LG57: 11.81 | LH57: 13.28 | LI57: 11.88 | LJ57: 12.31 | LK57: 12.68 | LL57: 15.04 | LM57: 11.49 | LN57: 13.56 | LO57: 17.67 | LP57: 13.46 | LQ57: 15.66 | LR57: 12.5 | LS57: 14.14 | LT57: 13.22 | LU57: 11.74 | LV57: 13.06 | LW57: 12.84 | LX57: 12.77 | LY57: 12.95 | LZ57: 15.88 | MA57: 11.6 | MB57: 12.7 | MC57: 15.34 | MD57: 89.85 | ME57: 17.33 | MF57: 13.76 | MG57: 15.95 | MH57: 15.34 | MI57: 13.5 | MJ57: 14.73 | MK57: 12.95 | ML57: 13.5 | MM57: 15.52 | MN57: 14.29 | MO57: 12.27 | MP57: 13.14 | MQ57: 14.47 | MR57: 16.79 | MS57: 16.81 | MT57: 16.85 | MU57: 18.4 | MV57: 13.71 | MW57: 14.19 | MX57: 13.82 | MY57: 15.66 | MZ57: 15.54 | NA57: 15.81 | NB57: 14.69 | NC57: 13.87 | ND57: 15.55 | NE57: 13.64 | NF57: 13.58 | NG57: 13.64 | NH57: 15.45 | NI57: 15.04 | NJ57: 15.44 | NK57: 13.28
B58: 2 | C58: 326.16 | D58: 142.56 | E58: =E57+1 -> 57 | F58: =F57 -> 1 | G58: =G34 -> 9 | H58: =H34+1 -> 3 | I58: ; | K58: 13.89 | L58: 13.76 | M58: 18.33 | N58: 18.5 | O58: 18.44 | P58: 16.78 | Q58: 14 | R58: 14.11 | S58: 18.72 | T58: 18.25 | U58: 18.36 | V58: 18.97 | W58: 18.94 | X58: 17.61 | Y58: 18.43 | Z58: 18.46 | AA58: 18.68 | AB58: 152.09 | AC58: 159.84 | AD58: 325.94 | AE58: 159.62 | AF58: 16.78 | AG58: 154.65 | AH58: 146.63 | AI58: 157.11 | AJ58: 146.05 | AK58: 23.65 | AL58: 17.97 | AM58: 16.7 | AN58: 16.85 | AO58: 23.44 | AP58: 22.11 | AQ58: 25.53 | AR58: 23.71 | AS58: 23.29 | AT58: 16.67 | AU58: 20.41 | AV58: 23.04 | AW58: 23.19 | AX58: 17.28 | AY58: 26.14 | AZ58: 16.13 | BA58: 15.84 | BB58: 23.07 | BC58: 20.49 | BD58: 13.94 | BE58: 13.69 | BF58: 15.12 | BG58: 13.75 | BH58: 14.33 | BI58: 23.21 | BJ58: 15.76 | BK58: 17.57 | BL58: 23.64 | BM58: 23.65 | BN58: 15.91 | BO58: 15.55 | BP58: 17.17 | BQ58: 18.24 | BR58: 14.9 | BS58: 14.21 | BT58: 14.51 | BU58: 12.35 | BV58: 13.14 | BW58: 19.15 | BX58: 12.71 | BY58: 13.46 | BZ58: 20.06 | CA58: 12.32 | CB58: 12.56 | CC58: 12.67 | CD58: 14.86 | CE58: 13.14 | CF58: 14.58 | CG58: 12.77 | CH58: 12.43 | CI58: 12.93 | CJ58: 12.32 | CK58: 12.99 | CL58: 13.28 | CM58: 13.46 | CN58: 13.93 | CO58: 13.06 | CP58: 12.78 | CQ58: 13.33 | CR58: 12.5 | CS58: 12.06 | CT58: 12.67 | CU58: 11.88 | CV58: 12.17 | CW58: 12.13 | CX58: 11.95 | CY58: 13.26 | CZ58: 12.28 | DA58: 12.45 | DB58: 13.1 | DC58: 12.82 | DD58: 12.77 | DE58: 12.24 | DF58: 11.75 | DG58: 13.87 | DH58: 12.46 | DI58: 14.87 | DJ58: 12.4 | DK58: 12.46 | DL58: 13.36 | DM58: 13.54 | DN58: 12.24 | DO58: 12.21 | DP58: 12.16 | DQ58: 11.91 | DR58: 13.25 | DS58: 12.49 | DT58: 13.32 | DU58: 12.24 | DV58: 13.03 | DW58: 12.2 | DX58: 11.16 | DY58: 10.54 | DZ58: 11.59 | EA58: 12.46 | EB58: 11.63 | EC58: 12.54 | ED58: 12.16 | EE58: 12.24 | EF58: 12.31 | EG58: 11.84 | EH58: 12.38 | EI58: 12.64 | EJ58: 12.24 | EK58: 13.25 | EL58: 12.56 | EM58: 11.74 | EN58: 11.92 | EO58: 12.31 | EP58: 13.89 | EQ58: 13.35 | ER58: 12.67 | ES58: 12.13 | ET58: 12.39 | EU58: 12.95 | EV58: 12.2 | EW58: 12.96 | EX58: 11.84 | EY58: 11.7 | EZ58: 12.6 | FA58: 11.26 | FB58: 11.45 | FC58: 12.16 | FD58: 12.31 | FE58: 12.24 | FF58: 12.09 | FG58: 11.81 | FH58: 13.03 | FI58: 11.71 | FJ58: 12.71 | FK58: 13.25 | FL58: 11.91 | FM58: 12.09 | FN58: 12.14 | FO58: 12.13 | FP58: 12.27 | FQ58: 12.43 | FR58: 11.56 | FS58: 12.24 | FT58: 12.42 | FU58: 12.11 | FV58: 11.74 | FW58: 11.03 | FX58: 11.15 | FY58: 12.53 | FZ58: 12.71 | GA58: 12.8 | GB58: 11.34 | GC58: 10.4 | GD58: 11.4 | GE58: 11.3 | GF58: 11.81 | GG58: 11.78 | GH58: 12.05 | GI58: 11.62 | GJ58: 11.27 | GK58: 11.52 | GL58: 11.3 | GM58: 12.28 | GN58: 12.32 | GO58: 14.33 | GP58: 13.35 | GQ58: 12.2 | GR58: 12.38 | GS58: 11.7 | GT58: 11.7 | GU58: 12.11 | GV58: 12.13 | GW58: 10.96 | GX58: 11.41 | GY58: 12.28 | GZ58: 11.95 | HA58: 11.77 | HB58: 11.74 | HC58: 13.07 | HD58: 13.11 | HE58: 11.52 | HF58: 11.49 | HG58: 11.78 | HH58: 12.7 | HI58: 12.71 | HJ58: 12.43 | HK58: 13.79 | HL58: 11.48 | HM58: 10.99 | HN58: 12.75 | HO58: 12.2 | HP58: 11.88 | HQ58: 11.83 | HR58: 11.4 | HS58: 12.21 | HT58: 11.38 | HU58: 13.82 | HV58: 12.6 | HW58: 11.13 | HX58: 10.37 | HY58: 11.09 | HZ58: 11.63 | IA58: 13.03 | IB58: 11.64 | IC58: 10.62 | ID58: 10.98 | IE58: 12.46 | IF58: 10.19 | IG58: 11.45 | IH58: 11.13 | II58: 11.53 | IJ58: 10.44 | IK58: 15.95 | IL58: 11.81 | IM58: 11.23 | IN58: 10.62 | IO58: 11.63 | IP58: 10.88 | IQ58: 11.73 | IR58: 11.05 | IS58: 11.98 | IT58: 12.19 | IU58: 11.83 | IV58: 10.94 | IW58: 10.51 | IX58: 10.19 | IY58: 12.7 | IZ58: 12.88 | JA58: 12.67 | JB58: 12.35 | JC58: 11.3 | JD58: 10.34 | JE58: 11.78 | JF58: 12.13 | JG58: 14.58 | JH58: 10.87 | JI58: 10.99 | JJ58: 11.49 | JK58: 13.11 | JL58: 12.1 | JM58: 11.71 | JN58: 12.24 | JO58: 10.4 | JP58: 10.23 | JQ58: 11.27 | JR58: 10.5 | JS58: 10.3 | JT58: 10.73 | JU58: 11.84 | JV58: 11.02 | JW58: 11.27 | JX58: 10.77 | JY58: 10.33 | JZ58: 11.68 | KA58: 11.85 | KB58: 12.34 | KC58: 12.07 | KD58: 10.98 | KE58: 10.91 | KF58: 10.94 | KG58: 12.21 | KH58: 12.63 | KI58: 12.03 | KJ58: 12.42 | KK58: 11.09 | KL58: 11.88 | KM58: 13.26 | KN58: 12.46 | KO58: 12.79 | KP58: 12.28 | KQ58: 14.04 | KR58: 11.16 | KS58: 11.6 | KT58: 12.32 | KU58: 14.4 | KV58: 12.27 | KW58: 12.5 | KX58: 12.82 | KY58: 11.74 | KZ58: 11.09 | LA58: 12.59 | LB58: 11.84 | LC58: 13.11 | LD58: 12.42 | LE58: 13.79 | LF58: 11.88 | LG58: 12.79 | LH58: 12.36 | LI58: 12.95 | LJ58: 12.42 | LK58: 12.78 | LL58: 15.04 | LM58: 11.33 | LN58: 10.96 | LO58: 16.13 | LP58: 13.1 | LQ58: 14.36 | LR58: 13.5 | LS58: 13.68 | LT58: 13.97 | LU58: 12.82 | LV58: 11.55 | LW58: 13.07 | LX58: 13.06 | LY58: 13.6 | LZ58: 14.62 | MA58: 11.48 | MB58: 12.53 | MC58: 14.94 | MD58: 89.96 | ME58: 14.48 | MF58: 13.8 | MG58: 13.18 | MH58: 16.82 | MI58: 16.81 | MJ58: 16.27 | MK58: 12.5 | ML58: 17.03 | MM58: 13.75 | MN58: 13.61 | MO58: 13.82 | MP58: 13.53 | MQ58: 14.79 | MR58: 14.48 | MS58: 16.78 | MT58: 16.92 | MU58: 14.91 | MV58: 14.29 | MW58: 15.41 | MX58: 14.84 | MY58: 13.71 | MZ58: 13.54 | NA58: 13.04 | NB58: 13.42 | NC58: 16.34 | ND58: 14.51 | NE58: 15.12 | NF58: 13 | NG58: 11.88 | NH58: 17.03 | NI58: 13.42 | NJ58: 14.27 | NK58: 15.04
B59: 1 | C59: 364.79 | D59: 100.59 | E59: =E58+1 -> 58 | F59: =F58 -> 1 | G59: =G35 -> 10 | H59: =H35+1 -> 3 | I59: ; | K59: 14.18 | L59: 14.04 | M59: 18.25 | N59: 18.47 | O59: 18.53 | P59: 16.71 | Q59: 13.75 | R59: 14.61 | S59: 18.75 | T59: 18.25 | U59: 18.35 | V59: 19.04 | W59: 18.98 | X59: 16.88 | Y59: 17.1 | Z59: 18.4 | AA59: 18.72 | AB59: 156.53 | AC59: 244.18 | AD59: 280.74 | AE59: 62.89 | AF59: 16.23 | AG59: 155.62 | AH59: 150.9 | AI59: 158.61 | AJ59: 154.44 | AK59: 23.8 | AL59: 17.76 | AM59: 18.9 | AN59: 15.84 | AO59: 20.63 | AP59: 17.78 | AQ59: 23.11 | AR59: 21.02 | AS59: 23.4 | AT59: 16.5 | AU59: 17.71 | AV59: 16.82 | AW59: 18.94 | AX59: 17.25 | AY59: 26.07 | AZ59: 16.05 | BA59: 15.85 | BB59: 19.05 | BC59: 20.67 | BD59: 14.18 | BE59: 12.28 | BF59: 12.67 | BG59: 13.44 | BH59: 13.68 | BI59: 23.3 | BJ59: 15.72 | BK59: 15.92 | BL59: 17.42 | BM59: 23.58 | BN59: 16.55 | BO59: 18.36 | BP59: 16.17 | BQ59: 17.06 | BR59: 15.65 | BS59: 12.96 | BT59: 14.58 | BU59: 12.27 | BV59: 12.81 | BW59: 21.3 | BX59: 12.75 | BY59: 12.39 | BZ59: 19.97 | CA59: 12.39 | CB59: 12.57 | CC59: 12.6 | CD59: 16.13 | CE59: 13.03 | CF59: 13.76 | CG59: 13.03 | CH59: 12.71 | CI59: 12.09 | CJ59: 12.24 | CK59: 12.32 | CL59: 14.04 | CM59: 15.48 | CN59: 13.79 | CO59: 12.56 | CP59: 12.67 | CQ59: 12.43 | CR59: 12.53 | CS59: 12.05 | CT59: 12.28 | CU59: 12.38 | CV59: 11.3 | CW59: 11.63 | CX59: 11.24 | CY59: 12.42 | CZ59: 12.27 | DA59: 13.36 | DB59: 13.4 | DC59: 13.39 | DD59: 12.85 | DE59: 12.13 | DF59: 12.6 | DG59: 13.18 | DH59: 13.25 | DI59: 14.9 | DJ59: 13.25 | DK59: 14.23 | DL59: 12.31 | DM59: 13.49 | DN59: 12.28 | DO59: 13.17 | DP59: 12.05 | DQ59: 11.85 | DR59: 12.21 | DS59: 14.18 | DT59: 12.77 | DU59: 13.32 | DV59: 12.56 | DW59: 13.75 | DX59: 11.44 | DY59: 10.41 | DZ59: 11.26 | EA59: 11.56 | EB59: 12.28 | EC59: 13.21 | ED59: 11.95 | EE59: 12.85 | EF59: 11.77 | EG59: 13.11 | EH59: 13.46 | EI59: 13.32 | EJ59: 13.43 | EK59: 12.35 | EL59: 11.94 | EM59: 12.39 | EN59: 12.52 | EO59: 11.53 | EP59: 12.96 | EQ59: 12.49 | ER59: 13.09 | ES59: 12.2 | ET59: 12.35 | EU59: 11.84 | EV59: 12.86 | EW59: 12.88 | EX59: 11.85 | EY59: 12.06 | EZ59: 13.32 | FA59: 11.34 | FB59: 11.23 | FC59: 12.35 | FD59: 12.31 | FE59: 11.67 | FF59: 13.57 | FG59: 12.7 | FH59: 12.06 | FI59: 12.31 | FJ59: 11.77 | FK59: 12.77 | FL59: 11.95 | FM59: 12.5 | FN59: 12.11 | FO59: 11.33 | FP59: 11.41 | FQ59: 13.14 | FR59: 11.48 | FS59: 11.33 | FT59: 12.39 | FU59: 13.18 | FV59: 12.02 | FW59: 11.19 | FX59: 11.88 | FY59: 12.6 | FZ59: 12.6 | GA59: 11.8 | GB59: 10.58 | GC59: 10.3 | GD59: 12.05 | GE59: 10.88 | GF59: 11.3 | GG59: 11.77 | GH59: 12.92 | GI59: 12.13 | GJ59: 11.13 | GK59: 11.44 | GL59: 11.23 | GM59: 11.27 | GN59: 12.96 | GO59: 13.07 | GP59: 12.6 | GQ59: 11.12 | GR59: 10.8 | GS59: 11.8 | GT59: 11.05 | GU59: 12.39 | GV59: 11.33 | GW59: 10.98 | GX59: 11.2 | GY59: 11.2 | GZ59: 12.32 | HA59: 11.02 | HB59: 10.8 | HC59: 11.12 | HD59: 13.94 | HE59: 11.85 | HF59: 11.77 | HG59: 12.57 | HH59: 13.06 | HI59: 12.43 | HJ59: 11.33 | HK59: 13.18 | HL59: 10.8 | HM59: 11.41 | HN59: 12.92 | HO59: 10.72 | HP59: 11.37 | HQ59: 11.42 | HR59: 11.37 | HS59: 11.66 | HT59: 10.41 | HU59: 12.81 | HV59: 13.04 | HW59: 11.99 | HX59: 10.23 | HY59: 11.03 | HZ59: 11.34 | IA59: 10.8 | IB59: 11.6 | IC59: 10.51 | ID59: 11.59 | IE59: 11.13 | IF59: 10.48 | IG59: 10.59 | IH59: 10.8 | II59: 10.84 | IJ59: 10.45 | IK59: 12.63 | IL59: 11.6 | IM59: 11.1 | IN59: 10.72 | IO59: 12.31 | IP59: 11.16 | IQ59: 11.7 | IR59: 10.29 | IS59: 10.95 | IT59: 12.16 | IU59: 10.95 | IV59: 10.62 | IW59: 10.58 | IX59: 10.04 | IY59: 11.71 | IZ59: 11.92 | JA59: 13.57 | JB59: 11.45 | JC59: 11.95 | JD59: 10.66 | JE59: 11.6 | JF59: 11.26 | JG59: 14.62 | JH59: 10.55 | JI59: 10.8 | JJ59: 11.09 | JK59: 11.62 | JL59: 10.95 | JM59: 10.64 | JN59: 11.2 | JO59: 10.29 | JP59: 10.23 | JQ59: 10.62 | JR59: 12.2 | JS59: 10.38 | JT59: 10.19 | JU59: 12.53 | JV59: 10.3 | JW59: 10.29 | JX59: 12.21 | JY59: 11.09 | JZ59: 12.43 | KA59: 11.23 | KB59: 12.08 | KC59: 12.22 | KD59: 10.23 | KE59: 11.34 | KF59: 12.68 | KG59: 12.14 | KH59: 11.99 | KI59: 12.75 | KJ59: 11.66 | KK59: 13.79 | KL59: 11.88 | KM59: 13.42 | KN59: 14.68 | KO59: 11.91 | KP59: 12.09 | KQ59: 13.57 | KR59: 11.2 | KS59: 11.4 | KT59: 14.8 | KU59: 12.56 | KV59: 12.56 | KW59: 12.38 | KX59: 12.9 | KY59: 11.7 | KZ59: 12.03 | LA59: 11.44 | LB59: 12.71 | LC59: 15.31 | LD59: 13.07 | LE59: 13.86 | LF59: 11.85 | LG59: 11.63 | LH59: 13.25 | LI59: 12.71 | LJ59: 13.03 | LK59: 11.44 | LL59: 16.81 | LM59: 12.12 | LN59: 10.72 | LO59: 14.79 | LP59: 12.41 | LQ59: 14.22 | LR59: 13.36 | LS59: 12.75 | LT59: 13.83 | LU59: 12.1 | LV59: 12.32 | LW59: 11.56 | LX59: 14.76 | LY59: 11.88 | LZ59: 12.16 | MA59: 14.87 | MB59: 11.73 | MC59: 17.34 | MD59: 91.12 | ME59: 13.6 | MF59: 17.42 | MG59: 13.07 | MH59: 14.55 | MI59: 13.31 | MJ59: 18.23 | MK59: 12.28 | ML59: 13.71 | MM59: 14.72 | MN59: 14.26 | MO59: 14.35 | MP59: 13.87 | MQ59: 16.45 | MR59: 15.2 | MS59: 15.3 | MT59: 18.22 | MU59: 13.64 | MV59: 15.81 | MW59: 15.66 | MX59: 15.01 | MY59: 13.64 | MZ59: 14.03 | NA59: 12.92 | NB59: 15.52 | NC59: 15.61 | ND59: 13.36 | NE59: 14.26 | NF59: 14.43 | NG59: 12.27 | NH59: 13.5 | NI59: 12.09 | NJ59: 12.43 | NK59: 12.52
B60: 1 | C60: 274.86 | D60: 84.02 | E60: =E59+1 -> 59 | F60: =F59 -> 1 | G60: =G36 -> 11 | H60: =H36+1 -> 3 | I60: ; | K60: 13.79 | L60: 13.86 | M60: 18.36 | N60: 18.46 | O60: 18.47 | P60: 16.7 | Q60: 14.23 | R60: 14 | S60: 17.93 | T60: 17.75 | U60: 17.78 | V60: 18.98 | W60: 18.94 | X60: 16.96 | Y60: 21.21 | Z60: 18.5 | AA60: 18 | AB60: 150.81 | AC60: 307.8 | AD60: 331.09 | AE60: 19.48 | AF60: 16.02 | AG60: 155.09 | AH60: 158.94 | AI60: 158.22 | AJ60: 151.44 | AK60: 24.26 | AL60: 16.82 | AM60: 16.72 | AN60: 18.26 | AO60: 16.13 | AP60: 17.71 | AQ60: 17.13 | AR60: 16.34 | AS60: 22.42 | AT60: 17.86 | AU60: 19.01 | AV60: 17.14 | AW60: 18.32 | AX60: 18.86 | AY60: 25.92 | AZ60: 17.24 | BA60: 17.1 | BB60: 19.04 | BC60: 20.71 | BD60: 13.11 | BE60: 13.43 | BF60: 13.53 | BG60: 13.51 | BH60: 13.39 | BI60: 19.05 | BJ60: 18.79 | BK60: 18.24 | BL60: 16.24 | BM60: 19.19 | BN60: 17.14 | BO60: 15.37 | BP60: 15.91 | BQ60: 16.44 | BR60: 15.69 | BS60: 14.51 | BT60: 13.47 | BU60: 13.97 | BV60: 12.39 | BW60: 18.68 | BX60: 14.48 | BY60: 13.1 | BZ60: 19.91 | CA60: 13.15 | CB60: 13.25 | CC60: 13.43 | CD60: 14.84 | CE60: 13.54 | CF60: 13.6 | CG60: 12.68 | CH60: 12.89 | CI60: 11.99 | CJ60: 12.03 | CK60: 12.17 | CL60: 13.11 | CM60: 13.11 | CN60: 12.93 | CO60: 13.43 | CP60: 12.02 | CQ60: 12.71 | CR60: 14.29 | CS60: 11.88 | CT60: 12.67 | CU60: 11.71 | CV60: 11.02 | CW60: 10.79 | CX60: 11.89 | CY60: 12.82 | CZ60: 12.84 | DA60: 12.16 | DB60: 14.65 | DC60: 12.63 | DD60: 13.17 | DE60: 12.56 | DF60: 11.75 | DG60: 13.08 | DH60: 13.14 | DI60: 13.6 | DJ60: 13.28 | DK60: 12.24 | DL60: 12.95 | DM60: 12.53 | DN60: 12.82 | DO60: 12.03 | DP60: 13.93 | DQ60: 11.81 | DR60: 12.09 | DS60: 12.27 | DT60: 13.15 | DU60: 13.18 | DV60: 14.04 | DW60: 12.49 | DX60: 12.57 | DY60: 11.26 | DZ60: 11.94 | EA60: 11.71 | EB60: 12.25 | EC60: 12.56 | ED60: 13.17 | EE60: 11.78 | EF60: 12.53 | EG60: 11.56 | EH60: 11.92 | EI60: 12.75 | EJ60: 12.82 | EK60: 12.67 | EL60: 12.34 | EM60: 11.7 | EN60: 12.31 | EO60: 12.14 | EP60: 13.79 | EQ60: 13.47 | ER60: 13.43 | ES60: 12.75 | ET60: 13.14 | EU60: 12.6 | EV60: 12.13 | EW60: 12.05 | EX60: 12.52 | EY60: 11.52 | EZ60: 12.64 | FA60: 11.57 | FB60: 12.03 | FC60: 12.78 | FD60: 11.99 | FE60: 11.52 | FF60: 11.81 | FG60: 12.17 | FH60: 11.95 | FI60: 11.44 | FJ60: 12.47 | FK60: 12.03 | FL60: 13.43 | FM60: 11.91 | FN60: 11.59 | FO60: 12.09 | FP60: 11.19 | FQ60: 13.04 | FR60: 12.41 | FS60: 11.23 | FT60: 11.66 | FU60: 11.63 | FV60: 10.96 | FW60: 10.98 | FX60: 11.27 | FY60: 13.21 | FZ60: 11.78 | GA60: 11.81 | GB60: 11.45 | GC60: 10.16 | GD60: 11.73 | GE60: 10.44 | GF60: 11.96 | GG60: 11.91 | GH60: 12.63 | GI60: 11.3 | GJ60: 11.06 | GK60: 12.82 | GL60: 11.08 | GM60: 12.27 | GN60: 13 | GO60: 12.88 | GP60: 12.14 | GQ60: 11.84 | GR60: 10.68 | GS60: 11.44 | GT60: 11.92 | GU60: 11.78 | GV60: 11.09 | GW60: 10.8 | GX60: 13.1 | GY60: 11.81 | GZ60: 11.63 | HA60: 10.91 | HB60: 10.69 | HC60: 11.06 | HD60: 13.07 | HE60: 11.6 | HF60: 11.48 | HG60: 11.77 | HH60: 13.28 | HI60: 12.35 | HJ60: 11.84 | HK60: 12.88 | HL60: 11.48 | HM60: 10.8 | HN60: 12.35 | HO60: 10.72 | HP60: 10.76 | HQ60: 11.37 | HR60: 11.88 | HS60: 11.16 | HT60: 10.54 | HU60: 12.89 | HV60: 13.14 | HW60: 11.71 | HX60: 10.5 | HY60: 11.02 | HZ60: 11.52 | IA60: 10.73 | IB60: 12.03 | IC60: 11.23 | ID60: 10.88 | IE60: 11.05 | IF60: 11.27 | IG60: 10.58 | IH60: 11.31 | II60: 11.09 | IJ60: 10.29 | IK60: 12.53 | IL60: 11.48 | IM60: 11.74 | IN60: 10.88 | IO60: 11.48 | IP60: 10.23 | IQ60: 10.87 | IR60: 10.18 | IS60: 11.06 | IT60: 12.85 | IU60: 10.24 | IV60: 10.65 | IW60: 11.17 | IX60: 11.59 | IY60: 11.6 | IZ60: 12.77 | JA60: 13.24 | JB60: 11.95 | JC60: 10.95 | JD60: 10.73 | JE60: 11.56 | JF60: 11.02 | JG60: 13.46 | JH60: 10.59 | JI60: 11.62 | JJ60: 11.55 | JK60: 11.55 | JL60: 10.72 | JM60: 10.65 | JN60: 11.88 | JO60: 11.42 | JP60: 10.4 | JQ60: 11.17 | JR60: 10.2 | JS60: 10.11 | JT60: 9.86 | JU60: 12.74 | JV60: 10.41 | JW60: 10.23 | JX60: 9.93 | JY60: 11.26 | JZ60: 12.67 | KA60: 11.16 | KB60: 11.16 | KC60: 11.6 | KD60: 10.88 | KE60: 10.15 | KF60: 11.05 | KG60: 11.06 | KH60: 12.42 | KI60: 11.88 | KJ60: 11.69 | KK60: 10.99 | KL60: 10.88 | KM60: 12.24 | KN60: 12.96 | KO60: 12.64 | KP60: 12.7 | KQ60: 11.66 | KR60: 11.85 | KS60: 13.64 | KT60: 13.32 | KU60: 13.46 | KV60: 12.27 | KW60: 11.3 | KX60: 13.36 | KY60: 11.75 | KZ60: 11.66 | LA60: 11.38 | LB60: 11.98 | LC60: 12.86 | LD60: 13.07 | LE60: 12.71 | LF60: 12.82 | LG60: 12.6 | LH60: 12.92 | LI60: 11.59 | LJ60: 12.49 | LK60: 11.51 | LL60: 17.21 | LM60: 12.96 | LN60: 10.55 | LO60: 14.55 | LP60: 12.64 | LQ60: 15.55 | LR60: 12.31 | LS60: 12.63 | LT60: 13 | LU60: 11.77 | LV60: 11.84 | LW60: 11.52 | LX60: 12.57 | LY60: 11.82 | LZ60: 12.2 | MA60: 11.66 | MB60: 12.13 | MC60: 17.79 | MD60: 94.03 | ME60: 15.05 | MF60: 13.75 | MG60: 15.27 | MH60: 13.68 | MI60: 13.14 | MJ60: 14.43 | MK60: 16.38 | ML60: 13.14 | MM60: 15.16 | MN60: 15.84 | MO60: 12.67 | MP60: 14.19 | MQ60: 14.18 | MR60: 14.65 | MS60: 13.64 | MT60: 14.4 | MU60: 14.94 | MV60: 14.37 | MW60: 14.8 | MX60: 13.64 | MY60: 16.31 | MZ60: 15.05 | NA60: 15.44 | NB60: 14.08 | NC60: 13.57 | ND60: 15.01 | NE60: 12.74 | NF60: 15.95 | NG60: 16.41 | NH60: 12.32 | NI60: 14.18 | NJ60: 13.18 | NK60: 12.77
B61: 1 | C61: 279.39 | D61: 160.91 | E61: =E60+1 -> 60 | F61: =F60 -> 1 | G61: =G37 -> 12 | H61: =H37+1 -> 3 | I61: ; | K61: 13.64 | L61: 22.61 | M61: 28.08 | N61: 24.77 | O61: 23.9 | P61: 16.45 | Q61: 13.61 | R61: 22.32 | S61: 54.21 | T61: 25.63 | U61: 23.54 | V61: 23.58 | W61: 22.97 | X61: 17.23 | Y61: 23.3 | Z61: 30.27 | AA61: 24.19 | AB61: 152.24 | AC61: 254.53 | AD61: 162.72 | AE61: 19.05 | AF61: 20.12 | AG61: 164.66 | AH61: 157.83 | AI61: 159.69 | AJ61: 144.4 | AK61: 28.08 | AL61: 18.05 | AM61: 22.35 | AN61: 26.27 | AO61: 24.8 | AP61: 27.17 | AQ61: 26.11 | AR61: 16.74 | AS61: 17.1 | AT61: 23.08 | AU61: 27.33 | AV61: 26.24 | AW61: 27.47 | AX61: 25.53 | AY61: 25.82 | AZ61: 15.77 | BA61: 22.86 | BB61: 27.36 | BC61: 20.96 | BD61: 14.63 | BE61: 13.5 | BF61: 13.93 | BG61: 12.35 | BH61: 22.54 | BI61: 23.94 | BJ61: 21.28 | BK61: 23.36 | BL61: 25.92 | BM61: 18.87 | BN61: 15.55 | BO61: 22.75 | BP61: 22.22 | BQ61: 24.94 | BR61: 17.17 | BS61: 22.75 | BT61: 14.39 | BU61: 12.24 | BV61: 15.19 | BW61: 30.41 | BX61: 45.05 | BY61: 19.51 | BZ61: 27.94 | CA61: 12.76 | CB61: 12.75 | CC61: 16.53 | CD61: 19.45 | CE61: 15.58 | CF61: 17.79 | CG61: 15.81 | CH61: 12.78 | CI61: 12.61 | CJ61: 16.31 | CK61: 15.98 | CL61: 20.01 | CM61: 16.63 | CN61: 17.74 | CO61: 13.58 | CP61: 12.2 | CQ61: 16.13 | CR61: 17.24 | CS61: 17.02 | CT61: 14.62 | CU61: 14.91 | CV61: 11.56 | CW61: 10.76 | CX61: 15.76 | CY61: 15.59 | CZ61: 54.54 | DA61: 17.16 | DB61: 15.19 | DC61: 12.93 | DD61: 12.85 | DE61: 15.51 | DF61: 16.1 | DG61: 27.5 | DH61: 14.94 | DI61: 17.53 | DJ61: 12.79 | DK61: 12.36 | DL61: 26.42 | DM61: 20.35 | DN61: 15.12 | DO61: 17.57 | DP61: 14.36 | DQ61: 16.71 | DR61: 13 | DS61: 16.13 | DT61: 18.26 | DU61: 14.97 | DV61: 27.64 | DW61: 14 | DX61: 11.7 | DY61: 12.35 | DZ61: 27.94 | EA61: 12.16 | EB61: 24.66 | EC61: 17.6 | ED61: 15.23 | EE61: 11.52 | EF61: 12.39 | EG61: 12.74 | EH61: 15.52 | EI61: 27.18 | EJ61: 16.7 | EK61: 14.83 | EL61: 13.14 | EM61: 11.52 | EN61: 13.22 | EO61: 16.27 | EP61: 14.12 | EQ61: 13.39 | ER61: 15.25 | ES61: 13.39 | ET61: 13.18 | EU61: 12.56 | EV61: 12.67 | EW61: 14.29 | EX61: 15.45 | EY61: 13.9 | EZ61: 13.25 | FA61: 12.02 | FB61: 14.04 | FC61: 16.48 | FD61: 15.53 | FE61: 15.45 | FF61: 12.5 | FG61: 12.57 | FH61: 12.13 | FI61: 13.57 | FJ61: 13.5 | FK61: 16.85 | FL61: 13.24 | FM61: 13.51 | FN61: 11.6 | FO61: 11.26 | FP61: 16.5 | FQ61: 12.86 | FR61: 13.82 | FS61: 13.97 | FT61: 12.35 | FU61: 16.41 | FV61: 11.1 | FW61: 15.88 | FX61: 13.36 | FY61: 23.83 | FZ61: 12.86 | GA61: 18.97 | GB61: 12.67 | GC61: 10.45 | GD61: 13.97 | GE61: 12.52 | GF61: 12.82 | GG61: 14.9 | GH61: 13.03 | GI61: 12.39 | GJ61: 11.78 | GK61: 12.06 | GL61: 15.19 | GM61: 16.38 | GN61: 15.44 | GO61: 14.22 | GP61: 13.6 | GQ61: 27.26 | GR61: 13.87 | GS61: 15.62 | GT61: 12.06 | GU61: 14.25 | GV61: 13.06 | GW61: 13.09 | GX61: 18.01 | GY61: 14.95 | GZ61: 12.89 | HA61: 12.78 | HB61: 14.98 | HC61: 12.92 | HD61: 14.59 | HE61: 11.08 | HF61: 14.64 | HG61: 13.89 | HH61: 14.95 | HI61: 15.04 | HJ61: 15.23 | HK61: 20.84 | HL61: 11.59 | HM61: 13.03 | HN61: 38.92 | HO61: 10.76 | HP61: 10.55 | HQ61: 12.16 | HR61: 12.09 | HS61: 10.98 | HT61: 15.66 | HU61: 15.87 | HV61: 17.27 | HW61: 19.48 | HX61: 19.77 | HY61: 15.67 | HZ61: 10.77 | IA61: 14.11 | IB61: 13.75 | IC61: 15.2 | ID61: 15.4 | IE61: 12.54 | IF61: 40.28 | IG61: 10.9 | IH61: 13.14 | II61: 13.35 | IJ61: 14.04 | IK61: 14.58 | IL61: 14.44 | IM61: 12.09 | IN61: 12.89 | IO61: 14.21 | IP61: 12.45 | IQ61: 13.18 | IR61: 14.11 | IS61: 13.82 | IT61: 12.46 | IU61: 10.72 | IV61: 13.97 | IW61: 11.48 | IX61: 11.52 | IY61: 12.6 | IZ61: 12.34 | JA61: 12.78 | JB61: 11.96 | JC61: 12.13 | JD61: 11.99 | JE61: 13.96 | JF61: 13.83 | JG61: 15.3 | JH61: 16.96 | JI61: 10.65 | JJ61: 11.77 | JK61: 15.27 | JL61: 15.09 | JM61: 12.06 | JN61: 23.37 | JO61: 10.04 | JP61: 11.08 | JQ61: 10.44 | JR61: 10.41 | JS61: 10.77 | JT61: 22.35 | JU61: 12.2 | JV61: 11.87 | JW61: 11.01 | JX61: 11.53 | JY61: 11.6 | JZ61: 11.92 | KA61: 12.88 | KB61: 12.25 | KC61: 19.51 | KD61: 10.11 | KE61: 12.6 | KF61: 12.61 | KG61: 18.29 | KH61: 15.05 | KI61: 15.66 | KJ61: 12.17 | KK61: 10.87 | KL61: 18.32 | KM61: 16.56 | KN61: 16.51 | KO61: 15.91 | KP61: 16.23 | KQ61: 13.14 | KR61: 11.67 | KS61: 14.47 | KT61: 14.87 | KU61: 17 | KV61: 16.09 | KW61: 17.56 | KX61: 12.95 | KY61: 11.02 | KZ61: 13.65 | LA61: 16.96 | LB61: 14.87 | LC61: 16.13 | LD61: 16.38 | LE61: 13 | LF61: 12.17 | LG61: 18.07 | LH61: 14.79 | LI61: 16.62 | LJ61: 15.83 | LK61: 18.03 | LL61: 15.45 | LM61: 11.23 | LN61: 19.33 | LO61: 22.32 | LP61: 15.52 | LQ61: 20.2 | LR61: 16.71 | LS61: 15.98 | LT61: 15.41 | LU61: 16.67 | LV61: 17.25 | LW61: 18.42 | LX61: 17.32 | LY61: 19.26 | LZ61: 14.23 | MA61: 11.59 | MB61: 17.68 | MC61: 19.48 | MD61: 95.1 | ME61: 19.45 | MF61: 17.57 | MG61: 15.05 | MH61: 13.79 | MI61: 21.53 | MJ61: 17.86 | MK61: 15.73 | ML61: 17.39 | MM61: 17.15 | MN61: 13.86 | MO61: 11.98 | MP61: 19.36 | MQ61: 27.86 | MR61: 20.05 | MS61: 19.05 | MT61: 21.5 | MU61: 16.24 | MV61: 14.51 | MW61: 20.34 | MX61: 19.55 | MY61: 20.16 | MZ61: 18.8 | NA61: 19.05 | NB61: 14.54 | NC61: 13.67 | ND61: 20.38 | NE61: 14.9 | NF61: 16.41 | NG61: 16.63 | NH61: 21.21 | NI61: 12.99 | NJ61: 16.75 | NK61: 13.32
B62: 1 | C62: 35.32 | D62: 0.5 | E62: =E61+1 -> 61 | F62: =F61 -> 1 | G62: =G38 -> 13 | H62: =H38+1 -> 3 | I62: ; | K62: 14.44 | L62: 183.47 | M62: 326.16 | N62: 458.89 | O62: 424.94 | P62: 16.57 | Q62: 14.59 | R62: 376.78 | S62: 414.26 | T62: 428.19 | U62: 449.82 | V62: 384.81 | W62: 312.55 | X62: 56.12 | Y62: 290.95 | Z62: 285.87 | AA62: 253.58 | AB62: 272.23 | AC62: 260.89 | AD62: 159.26 | AE62: 19.34 | AF62: 278.24 | AG62: 265.32 | AH62: 289.19 | AI62: 295.02 | AJ62: 297.46 | AK62: 128.21 | AL62: 36 | AM62: 173.38 | AN62: 219.1 | AO62: 210.89 | AP62: 442.26 | AQ62: 203.33 | AR62: 145.29 | AS62: 17.21 | AT62: 235.66 | AU62: 365.75 | AV62: 253.62 | AW62: 221.43 | AX62: 388.69 | AY62: 23.98 | AZ62: 16.2 | BA62: 368.67 | BB62: 247.81 | BC62: 20.82 | BD62: 13.85 | BE62: 12.71 | BF62: 12.99 | BG62: 14.53 | BH62: 237.48 | BI62: 255.09 | BJ62: 256.24 | BK62: 368.7 | BL62: 296.24 | BM62: 223.71 | BN62: 16.96 | BO62: 206.39 | BP62: 245.05 | BQ62: 361.81 | BR62: 120.78 | BS62: 262.62 | BT62: 136.69 | BU62: 12.5 | BV62: 267.62 | BW62: 351.9 | BX62: 331.38 | BY62: 357.36 | BZ62: 298.69 | CA62: 47.31 | CB62: 100.04 | CC62: 327.27 | CD62: 262.23 | CE62: 242.89 | CF62: 401.54 | CG62: 368.61 | CH62: 297.4 | CI62: 12.21 | CJ62: 316.04 | CK62: 236.95 | CL62: 254.92 | CM62: 440.13 | CN62: 409.5 | CO62: 136.04 | CP62: 124.66 | CQ62: 198.03 | CR62: 211.64 | CS62: 180.15 | CT62: 224.21 | CU62: 247.64 | CV62: 12.02 | CW62: 11.8 | CX62: 195.41 | CY62: 364.46 | CZ62: 239.73 | DA62: 260.79 | DB62: 210.14 | DC62: 289.65 | DD62: 315.28 | DE62: 199.3 | DF62: 360.8 | DG62: 231.99 | DH62: 406.51 | DI62: 209.89 | DJ62: 118.16 | DK62: 13.57 | DL62: 263.81 | DM62: 163.98 | DN62: 397.77 | DO62: 254.82 | DP62: 192.48 | DQ62: 129.68 | DR62: 113.47 | DS62: 230.59 | DT62: 186.44 | DU62: 338.22 | DV62: 388.37 | DW62: 318.82 | DX62: 147.39 | DY62: 11.2 | DZ62: 333.18 | EA62: 11.77 | EB62: 339.08 | EC62: 404.17 | ED62: 245.66 | EE62: 11.99 | EF62: 11.88 | EG62: 307.91 | EH62: 285.42 | EI62: 213.12 | EJ62: 238.56 | EK62: 227.59 | EL62: 20.7 | EM62: 12.74 | EN62: 178.13 | EO62: 183.84 | EP62: 194.62 | EQ62: 249.27 | ER62: 384.22 | ES62: 166.07 | ET62: 93.45 | EU62: 210.31 | EV62: 93.45 | EW62: 364.25 | EX62: 379.33 | EY62: 214.67 | EZ62: 132.37 | FA62: 11.56 | FB62: 184.72 | FC62: 167.65 | FD62: 197.82 | FE62: 347.66 | FF62: 193.49 | FG62: 42.37 | FH62: 11.28 | FI62: 175.72 | FJ62: 186.31 | FK62: 377.86 | FL62: 383.9 | FM62: 206.1 | FN62: 12.31 | FO62: 11.92 | FP62: 242.75 | FQ62: 325.45 | FR62: 238.57 | FS62: 352.04 | FT62: 170.78 | FU62: 111.18 | FV62: 11.88 | FW62: 347.4 | FX62: 206.99 | FY62: 329.08 | FZ62: 210.61 | GA62: 210.52 | GB62: 154.48 | GC62: 90.86 | GD62: 207.07 | GE62: 145.62 | GF62: 213.92 | GG62: 141.04 | GH62: 193.5 | GI62: 158.9 | GJ62: 11.62 | GK62: 151.34 | GL62: 179.21 | GM62: 306.11 | GN62: 348.55 | GO62: 398.56 | GP62: 293.37 | GQ62: 359.36 | GR62: 189.65 | GS62: 212.83 | GT62: 261.39 | GU62: 228.09 | GV62: 164.34 | GW62: 134.35 | GX62: 331.23 | GY62: 335.16 | GZ62: 215.82 | HA62: 170.25 | HB62: 235.76 | HC62: 195.27 | HD62: 130.86 | HE62: 11.03 | HF62: 192.38 | HG62: 296.4 | HH62: 184.5 | HI62: 324.79 | HJ62: 191.7 | HK62: 148.1 | HL62: 122.36 | HM62: 204.84 | HN62: 293.91 | HO62: 11.27 | HP62: 10.58 | HQ62: 11.34 | HR62: 10.94 | HS62: 11.24 | HT62: 248.22 | HU62: 325.87 | HV62: 212.48 | HW62: 369.58 | HX62: 190.87 | HY62: 367.88 | HZ62: 10.87 | IA62: 320.87 | IB62: 286.85 | IC62: 199.9 | ID62: 348.91 | IE62: 189.72 | IF62: 345.96 | IG62: 11.81 | IH62: 367.28 | II62: 240.44 | IJ62: 203.37 | IK62: 223.84 | IL62: 223.81 | IM62: 19.87 | IN62: 23.82 | IO62: 182.05 | IP62: 180.04 | IQ62: 206 | IR62: 183.02 | IS62: 218.81 | IT62: 119.12 | IU62: 160.48 | IV62: 141.19 | IW62: 218.42 | IX62: 345.7 | IY62: 207.33 | IZ62: 310.42 | JA62: 123.98 | JB62: 28.58 | JC62: 204.04 | JD62: 355.28 | JE62: 326.77 | JF62: 227.27 | JG62: 197.14 | JH62: 154.54 | JI62: 11.77 | JJ62: 190.99 | JK62: 196.74 | JL62: 158.83 | JM62: 165.7 | JN62: 182.45 | JO62: 13.28 | JP62: 10.69 | JQ62: 10.73 | JR62: 10.51 | JS62: 10.83 | JT62: 174.66 | JU62: 180.61 | JV62: 156.7 | JW62: 10.45 | JX62: 152.07 | JY62: 195.87 | JZ62: 260.35 | KA62: 199.26 | KB62: 183.56 | KC62: 187.74 | KD62: 10.33 | KE62: 311.47 | KF62: 196.45 | KG62: 225.54 | KH62: 403.49 | KI62: 304.88 | KJ62: 212.04 | KK62: 11.09 | KL62: 301.86 | KM62: 343.2 | KN62: 254.16 | KO62: 148.35 | KP62: 318.89 | KQ62: 153.79 | KR62: 11.81 | KS62: 166.5 | KT62: 274.93 | KU62: 206.1 | KV62: 241.75 | KW62: 312.01 | KX62: 170.03 | KY62: 12.06 | KZ62: 217.79 | LA62: 222.52 | LB62: 341.78 | LC62: 335.56 | LD62: 174.92 | LE62: 147.6 | LF62: 125.96 | LG62: 270.64 | LH62: 226.44 | LI62: 211.36 | LJ62: 199.01 | LK62: 315.17 | LL62: 181.62 | LM62: 11.52 | LN62: 181.8 | LO62: 401.43 | LP62: 373.21 | LQ62: 373.86 | LR62: 198.47 | LS62: 336.57 | LT62: 270.19 | LU62: 191.41 | LV62: 232.56 | LW62: 217 | LX62: 388.15 | LY62: 314.78 | LZ62: 13.49 | MA62: 12.18 | MB62: 313.88 | MC62: 307.23 | MD62: 212.76 | ME62: 304.2 | MF62: 229.57 | MG62: 18.11 | MH62: 19.4 | MI62: 210.78 | MJ62: 226.9 | MK62: 204.74 | ML62: 217.98 | MM62: 221.36 | MN62: 151.99 | MO62: 14.65 | MP62: 221.52 | MQ62: 229.47 | MR62: 232.74 | MS62: 246.53 | MT62: 362.78 | MU62: 13.57 | MV62: 231.7 | MW62: 158.83 | MX62: 259.06 | MY62: 230.35 | MZ62: 249.44 | NA62: 196.17 | NB62: 13.75 | NC62: 18.14 | ND62: 213.27 | NE62: 14 | NF62: 211.89 | NG62: 221.76 | NH62: 217.73 | NI62: 13.1 | NJ62: 12.57 | NK62: 14.14
B63: 1 | C63: 217 | D63: 69.58 | E63: =E62+1 -> 62 | F63: =F62 -> 1 | G63: =G39 -> 14 | H63: =H39+1 -> 3 | I63: ; | K63: 15.19 | L63: 209.04 | M63: 364.79 | N63: 508.39 | O63: 462.39 | P63: 17.22 | Q63: 14.93 | R63: 448.42 | S63: 493.77 | T63: 455.77 | U63: 432.68 | V63: 472.82 | W63: 302.79 | X63: 40.53 | Y63: 376.01 | Z63: 348.33 | AA63: 286.31 | AB63: 334.66 | AC63: 310.32 | AD63: 184.5 | AE63: 20.59 | AF63: 375.59 | AG63: 282.46 | AH63: 316.3 | AI63: 293.3 | AJ63: 326.02 | AK63: 132.48 | AL63: 119.59 | AM63: 248.11 | AN63: 413.17 | AO63: 267.71 | AP63: 386.35 | AQ63: 243.35 | AR63: 155.4 | AS63: 20.2 | AT63: 285.55 | AU63: 451.51 | AV63: 271.48 | AW63: 243.11 | AX63: 324.65 | AY63: 19.65 | AZ63: 18.75 | BA63: 459.55 | BB63: 288.94 | BC63: 19.44 | BD63: 13.61 | BE63: 14.94 | BF63: 15.08 | BG63: 14.51 | BH63: 273.06 | BI63: 446.25 | BJ63: 293.36 | BK63: 394.88 | BL63: 373.43 | BM63: 304.49 | BN63: 17.85 | BO63: 232.77 | BP63: 289.26 | BQ63: 399.41 | BR63: 146.63 | BS63: 258.23 | BT63: 143.71 | BU63: 16.2 | BV63: 213.48 | BW63: 405.07 | BX63: 394.27 | BY63: 433.51 | BZ63: 258.01 | CA63: 114.19 | CB63: 133.31 | CC63: 244.72 | CD63: 325.91 | CE63: 255.06 | CF63: 425.59 | CG63: 405.28 | CH63: 312.24 | CI63: 13.28 | CJ63: 452.62 | CK63: 261.61 | CL63: 247.85 | CM63: 409.29 | CN63: 522.76 | CO63: 135.98 | CP63: 139.61 | CQ63: 350.71 | CR63: 229.58 | CS63: 195.98 | CT63: 242.57 | CU63: 274.25 | CV63: 11.98 | CW63: 12.92 | CX63: 226.19 | CY63: 358.31 | CZ63: 246.28 | DA63: 261.79 | DB63: 308.1 | DC63: 305.14 | DD63: 343.84 | DE63: 247.92 | DF63: 254.84 | DG63: 244.23 | DH63: 347.15 | DI63: 259.74 | DJ63: 139.83 | DK63: 13.28 | DL63: 275.91 | DM63: 241.38 | DN63: 425.42 | DO63: 256.82 | DP63: 282 | DQ63: 193.81 | DR63: 128.33 | DS63: 288.12 | DT63: 220.29 | DU63: 290.59 | DV63: 438.62 | DW63: 258.34 | DX63: 235.41 | DY63: 12.88 | DZ63: 281.66 | EA63: 13.21 | EB63: 470.84 | EC63: 445 | ED63: 264.71 | EE63: 13.25 | EF63: 12.71 | EG63: 431.75 | EH63: 458.87 | EI63: 223.49 | EJ63: 253.22 | EK63: 251.38 | EL63: 20.84 | EM63: 13.28 | EN63: 231.04 | EO63: 253.22 | EP63: 201.2 | EQ63: 279.43 | ER63: 289.08 | ES63: 227.27 | ET63: 94.89 | EU63: 248.83 | EV63: 99.76 | EW63: 397.69 | EX63: 406.7 | EY63: 233.63 | EZ63: 143.26 | FA63: 12.6 | FB63: 259.1 | FC63: 227.96 | FD63: 334.76 | FE63: 386.38 | FF63: 204.99 | FG63: 12.71 | FH63: 12.7 | FI63: 250.81 | FJ63: 209.23 | FK63: 370.43 | FL63: 276.16 | FM63: 185.97 | FN63: 12.66 | FO63: 12.68 | FP63: 272.34 | FQ63: 228.95 | FR63: 286.96 | FS63: 218.13 | FT63: 222.77 | FU63: 93.88 | FV63: 12.28 | FW63: 350.85 | FX63: 268.93 | FY63: 366.45 | FZ63: 218.2 | GA63: 213.69 | GB63: 113.32 | GC63: 93.17 | GD63: 219.02 | GE63: 200.49 | GF63: 200.81 | GG63: 189.18 | GH63: 176.15 | GI63: 157.69 | GJ63: 12.07 | GK63: 234.68 | GL63: 256.28 | GM63: 422.21 | GN63: 342.86 | GO63: 376.41 | GP63: 232.78 | GQ63: 393.95 | GR63: 214.79 | GS63: 249.05 | GT63: 233.9 | GU63: 251.5 | GV63: 232.16 | GW63: 151.7 | GX63: 347.98 | GY63: 361.9 | GZ63: 268.41 | HA63: 202.49 | HB63: 231.84 | HC63: 223.35 | HD63: 176.79 | HE63: 11.56 | HF63: 242.07 | HG63: 346.14 | HH63: 211.36 | HI63: 236.73 | HJ63: 241.6 | HK63: 169.05 | HL63: 136.15 | HM63: 238.07 | HN63: 280.73 | HO63: 10.95 | HP63: 10.98 | HQ63: 12.67 | HR63: 11.27 | HS63: 12.85 | HT63: 384.55 | HU63: 319.03 | HV63: 308.37 | HW63: 386.67 | HX63: 209.37 | HY63: 399.57 | HZ63: 12.24 | IA63: 398.66 | IB63: 353.12 | IC63: 321.89 | ID63: 375.37 | IE63: 174.13 | IF63: 306.5 | IG63: 12.41 | IH63: 383.72 | II63: 246.49 | IJ63: 238.36 | IK63: 246.79 | IL63: 236.37 | IM63: 20.59 | IN63: 22.15 | IO63: 237.1 | IP63: 242.36 | IQ63: 198.72 | IR63: 195.7 | IS63: 338.58 | IT63: 163.87 | IU63: 162.68 | IV63: 220.54 | IW63: 280.8 | IX63: 361.66 | IY63: 220.13 | IZ63: 390.64 | JA63: 146.92 | JB63: 43.23 | JC63: 211.14 | JD63: 375.91 | JE63: 208.05 | JF63: 390.39 | JG63: 194 | JH63: 144.08 | JI63: 11.45 | JJ63: 197.1 | JK63: 229.32 | JL63: 184.14 | JM63: 162.04 | JN63: 192.24 | JO63: 11.82 | JP63: 10.8 | JQ63: 12.13 | JR63: 11.15 | JS63: 10.55 | JT63: 206.57 | JU63: 221.98 | JV63: 176.97 | JW63: 12.06 | JX63: 191.05 | JY63: 212.08 | JZ63: 257.44 | KA63: 266.11 | KB63: 218.34 | KC63: 214.52 | KD63: 11.71 | KE63: 377.31 | KF63: 225.43 | KG63: 347.19 | KH63: 412.09 | KI63: 264.86 | KJ63: 173.59 | KK63: 13.42 | KL63: 440.82 | KM63: 417.99 | KN63: 413.6 | KO63: 178.84 | KP63: 384.27 | KQ63: 211.73 | KR63: 12.96 | KS63: 198.49 | KT63: 236.62 | KU63: 212.62 | KV63: 271.95 | KW63: 456.45 | KX63: 182.19 | KY63: 13.35 | KZ63: 414.61 | LA63: 257.39 | LB63: 382.58 | LC63: 236.53 | LD63: 253.26 | LE63: 209.3 | LF63: 241.27 | LG63: 304.63 | LH63: 290.17 | LI63: 198.57 | LJ63: 233.07 | LK63: 371.56 | LL63: 202.53 | LM63: 13.28 | LN63: 249.6 | LO63: 386.06 | LP63: 328.14 | LQ63: 461.3 | LR63: 271.08 | LS63: 448.12 | LT63: 142.1 | LU63: 271.26 | LV63: 276.77 | LW63: 275.65 | LX63: 554.01 | LY63: 305.78 | LZ63: 13.64 | MA63: 15.62 | MB63: 365.37 | MC63: 415.51 | MD63: 221.63 | ME63: 417.57 | MF63: 231.63 | MG63: 115.8 | MH63: 14.61 | MI63: 243.86 | MJ63: 257.97 | MK63: 259.6 | ML63: 281.7 | MM63: 219.56 | MN63: 153.65 | MO63: 14.58 | MP63: 273.75 | MQ63: 273.3 | MR63: 256.17 | MS63: 257.68 | MT63: 412.74 | MU63: 13.71 | MV63: 232.67 | MW63: 219.03 | MX63: 296.89 | MY63: 273.06 | MZ63: 282.79 | NA63: 199.09 | NB63: 17.09 | NC63: 14.91 | ND63: 258.09 | NE63: 14.73 | NF63: 245.13 | NG63: 246.13 | NH63: 247.21 | NI63: 13.71 | NJ63: 13.54 | NK63: 12.71
B64: 2 | C64: 260.24 | D64: 93.89 | E64: =E63+1 -> 63 | F64: =F63 -> 1 | G64: =G40 -> 15 | H64: =H40+1 -> 3 | I64: ; | K64: 15.59 | L64: 265.79 | M64: 274.86 | N64: 428.62 | O64: 452.42 | P64: 15.88 | Q64: 15.26 | R64: 476.65 | S64: 471.93 | T64: 458.16 | U64: 389.09 | V64: 429.08 | W64: 351.24 | X64: 60.29 | Y64: 362.73 | Z64: 333.86 | AA64: 267.09 | AB64: 530.6 | AC64: 422.28 | AD64: 217.14 | AE64: 20.6 | AF64: 351.11 | AG64: 278.41 | AH64: 273.43 | AI64: 236.66 | AJ64: 432.87 | AK64: 132.53 | AL64: 111.62 | AM64: 250.16 | AN64: 470.12 | AO64: 343.34 | AP64: 473.51 | AQ64: 274.25 | AR64: 157.5 | AS64: 18.32 | AT64: 399.39 | AU64: 434.95 | AV64: 286.25 | AW64: 250.34 | AX64: 248.26 | AY64: 19.58 | AZ64: 17.63 | BA64: 413.72 | BB64: 250.86 | BC64: 17.42 | BD64: 14.55 | BE64: 13.9 | BF64: 14.28 | BG64: 13.82 | BH64: 262.76 | BI64: 400.03 | BJ64: 293.88 | BK64: 420.98 | BL64: 329.15 | BM64: 293.94 | BN64: 17.39 | BO64: 338.25 | BP64: 270.39 | BQ64: 416.58 | BR64: 312.12 | BS64: 259.73 | BT64: 136.94 | BU64: 13.28 | BV64: 345.91 | BW64: 250.42 | BX64: 347.98 | BY64: 378.43 | BZ64: 248.11 | CA64: 52.78 | CB64: 126.65 | CC64: 201.09 | CD64: 347.69 | CE64: 372.17 | CF64: 424.87 | CG64: 312.19 | CH64: 105.35 | CI64: 12.96 | CJ64: 324.87 | CK64: 226.36 | CL64: 261.65 | CM64: 238.67 | CN64: 406.05 | CO64: 138.93 | CP64: 134.75 | CQ64: 184.43 | CR64: 209.12 | CS64: 171.35 | CT64: 231.3 | CU64: 230.51 | CV64: 13.03 | CW64: 12.27 | CX64: 212.21 | CY64: 380.74 | CZ64: 224.28 | DA64: 268.98 | DB64: 337.46 | DC64: 298.87 | DD64: 337.65 | DE64: 235.33 | DF64: 226.18 | DG64: 245.7 | DH64: 221.17 | DI64: 225.76 | DJ64: 149.47 | DK64: 13.97 | DL64: 266.11 | DM64: 249.13 | DN64: 357.7 | DO64: 256.13 | DP64: 233.9 | DQ64: 328.5 | DR64: 125.46 | DS64: 257.47 | DT64: 193.39 | DU64: 266.87 | DV64: 411.78 | DW64: 195.95 | DX64: 231.88 | DY64: 13.64 | DZ64: 209.24 | EA64: 12.49 | EB64: 294.9 | EC64: 373.79 | ED64: 260.78 | EE64: 14.04 | EF64: 13.54 | EG64: 425.74 | EH64: 406.7 | EI64: 246.17 | EJ64: 247.67 | EK64: 262.58 | EL64: 89.72 | EM64: 12.59 | EN64: 223.49 | EO64: 234.94 | EP64: 236.27 | EQ64: 386.21 | ER64: 196.53 | ES64: 218.64 | ET64: 65.52 | EU64: 218.12 | EV64: 123.19 | EW64: 464.97 | EX64: 375.86 | EY64: 238.68 | EZ64: 145.66 | FA64: 13.5 | FB64: 227.74 | FC64: 204.56 | FD64: 354.78 | FE64: 317.41 | FF64: 216.58 | FG64: 13.69 | FH64: 11.88 | FI64: 313.69 | FJ64: 204.96 | FK64: 165.63 | FL64: 201.6 | FM64: 202.72 | FN64: 12.45 | FO64: 13.43 | FP64: 401.54 | FQ64: 190.58 | FR64: 280.33 | FS64: 274.4 | FT64: 178.55 | FU64: 67.14 | FV64: 12.71 | FW64: 325.41 | FX64: 153.79 | FY64: 371.56 | FZ64: 182.77 | GA64: 245.99 | GB64: 137.59 | GC64: 89.14 | GD64: 272.48 | GE64: 186.73 | GF64: 186.55 | GG64: 263.66 | GH64: 185.87 | GI64: 153.22 | GJ64: 12.09 | GK64: 247.96 | GL64: 213.84 | GM64: 393.41 | GN64: 332.83 | GO64: 413.22 | GP64: 178.06 | GQ64: 351.04 | GR64: 227.37 | GS64: 229.25 | GT64: 246.96 | GU64: 265.42 | GV64: 220.79 | GW64: 149.66 | GX64: 395.21 | GY64: 311.62 | GZ64: 199.37 | HA64: 235.94 | HB64: 227.7 | HC64: 226.73 | HD64: 175.97 | HE64: 11.89 | HF64: 225.42 | HG64: 406.55 | HH64: 197.1 | HI64: 183.71 | HJ64: 232.77 | HK64: 182.48 | HL64: 134.54 | HM64: 201.02 | HN64: 243.43 | HO64: 11.95 | HP64: 12.93 | HQ64: 11.4 | HR64: 11.59 | HS64: 13.03 | HT64: 230.22 | HU64: 384.22 | HV64: 375.76 | HW64: 384.3 | HX64: 238.65 | HY64: 319.32 | HZ64: 12.93 | IA64: 371.53 | IB64: 361.45 | IC64: 424.51 | ID64: 318.92 | IE64: 176.11 | IF64: 379.55 | IG64: 15.05 | IH64: 395.89 | II64: 214.92 | IJ64: 209.16 | IK64: 269.97 | IL64: 221.69 | IM64: 18.4 | IN64: 22.4 | IO64: 236.7 | IP64: 220.54 | IQ64: 162.5 | IR64: 190.8 | IS64: 199.76 | IT64: 171.9 | IU64: 163.51 | IV64: 165.56 | IW64: 397.4 | IX64: 219.78 | IY64: 219.2 | IZ64: 401.32 | JA64: 178.08 | JB64: 38.31 | JC64: 214.56 | JD64: 405.44 | JE64: 198.46 | JF64: 307.39 | JG64: 198.83 | JH64: 147.96 | JI64: 11.48 | JJ64: 217.8 | JK64: 210.03 | JL64: 163.32 | JM64: 190.95 | JN64: 167 | JO64: 13.11 | JP64: 10.98 | JQ64: 12.02 | JR64: 11.82 | JS64: 10.59 | JT64: 225.75 | JU64: 214.75 | JV64: 178.68 | JW64: 10.96 | JX64: 200.57 | JY64: 208.91 | JZ64: 220.64 | KA64: 230.4 | KB64: 216.18 | KC64: 201.56 | KD64: 11.49 | KE64: 367.49 | KF64: 229.03 | KG64: 421.31 | KH64: 423.32 | KI64: 207.29 | KJ64: 170.85 | KK64: 13.03 | KL64: 415.22 | KM64: 349.77 | KN64: 372.52 | KO64: 171.05 | KP64: 207.83 | KQ64: 271.44 | KR64: 11.99 | KS64: 196.05 | KT64: 191.75 | KU64: 412.95 | KV64: 274.47 | KW64: 280.18 | KX64: 168.78 | KY64: 12.06 | KZ64: 398.08 | LA64: 260.13 | LB64: 349.63 | LC64: 297 | LD64: 232.41 | LE64: 342.5 | LF64: 313.64 | LG64: 250.82 | LH64: 254.84 | LI64: 242.42 | LJ64: 236.09 | LK64: 233.79 | LL64: 206.51 | LM64: 11.88 | LN64: 239.79 | LO64: 377.35 | LP64: 270.68 | LQ64: 409.5 | LR64: 255.89 | LS64: 438.08 | LT64: 128.41 | LU64: 258.85 | LV64: 228.3 | LW64: 277.27 | LX64: 490.07 | LY64: 321.08 | LZ64: 14.93 | MA64: 12.45 | MB64: 288.48 | MC64: 546.09 | MD64: 226.86 | ME64: 370.68 | MF64: 243.15 | MG64: 117.55 | MH64: 14.52 | MI64: 232.67 | MJ64: 229.21 | MK64: 231.69 | ML64: 265.89 | MM64: 200.48 | MN64: 159.94 | MO64: 14.11 | MP64: 244.59 | MQ64: 289.26 | MR64: 241.02 | MS64: 273.56 | MT64: 414.75 | MU64: 17.03 | MV64: 255.63 | MW64: 203.5 | MX64: 253.04 | MY64: 278.35 | MZ64: 280.48 | NA64: 251.44 | NB64: 14.4 | NC64: 14.83 | ND64: 221.61 | NE64: 13.87 | NF64: 217.49 | NG64: 214.96 | NH64: 240.76 | NI64: 18.28 | NJ64: 15.58 | NK64: 14.25
... B77: 6 | C77: 18.58 | D77: 19.87 | E77: =E76+1 -> 76 | F77: =F76 -> 1 | G77: =G53 -> 4 | H77: =H53+1 -> 4 | I77: ; | K77: 13.86 | L77: 18.29 | M77: 18.47 | N77: 18.53 | O77: 16.38 | P77: 13.83 | Q77: 13.58 | R77: 18.68 | S77: 18.39 | T77: 18.35 | U77: 18.75 | V77: 18.61 | W77: 18.36 | X77: 18.22 | Y77: 18.57 | Z77: 18.5 | AA77: 148.03 | AB77: 262.4 | AC77: 128.23 | AD77: 133.89 | AE77: 16.6 | AF77: 153.79 | AG77: 156.27 | AH77: 158.08 | AI77: 155.95 | AJ77: 293.18 | AK77: 16.31 | AL77: 17.03 | AM77: 280.87 | AN77: 360.54 | AO77: 333.42 | AP77: 342 | AQ77: 160.63 | AR77: 156.57 | AS77: 16.53 | AT77: 217.11 | AU77: 150.09 | AV77: 125.09 | AW77: 275.51 | AX77: 329.08 | AY77: 15.84 | AZ77: 16.1 | BA77: 171.03 | BB77: 142.64 | BC77: 12.63 | BD77: 13.36 | BE77: 13.5 | BF77: 13.9 | BG77: 13.18 | BH77: 351.42 | BI77: 355.11 | BJ77: 308.42 | BK77: 174.82 | BL77: 349.24 | BM77: 292.5 | BN77: 16.88 | BO77: 22.92 | BP77: 23.76 | BQ77: 21.2 | BR77: 13.43 | BS77: 19.65 | BT77: 12.59 | BU77: 12.12 | BV77: 27 | BW77: 19.22 | BX77: 12.24 | BY77: 19.58 | BZ77: 14.96 | CA77: 12.24 | CB77: 15.23 | CC77: 17.92 | CD77: 15.31 | CE77: 15.91 | CF77: 14.9 | CG77: 14.66 | CH77: 11.99 | CI77: 12.42 | CJ77: 14.58 | CK77: 15.51 | CL77: 17.71 | CM77: 25.13 | CN77: 14.94 | CO77: 13.29 | CP77: 14.32 | CQ77: 14.76 | CR77: 16.06 | CS77: 14.51 | CT77: 13.94 | CU77: 15.16 | CV77: 11.88 | CW77: 11.08 | CX77: 16.2 | CY77: 14.51 | CZ77: 14.51 | DA77: 15.23 | DB77: 19.01 | DC77: 13.18 | DD77: 12.75 | DE77: 14.29 | DF77: 15.08 | DG77: 14.25 | DH77: 16.23 | DI77: 14.98 | DJ77: 12.05 | DK77: 12.39 | DL77: 14.91 | DM77: 14.36 | DN77: 14.15 | DO77: 14.22 | DP77: 13.94 | DQ77: 12.88 | DR77: 12.67 | DS77: 15.05 | DT77: 14.4 | DU77: 14.51 | DV77: 14.18 | DW77: 12.96 | DX77: 10.81 | DY77: 11.41 | DZ77: 13.46 | EA77: 11.48 | EB77: 14.61 | EC77: 14.15 | ED77: 14.11 | EE77: 12.06 | EF77: 11.84 | EG77: 16.2 | EH77: 14.98 | EI77: 14.22 | EJ77: 14.41 | EK77: 14.11 | EL77: 11.52 | EM77: 11.71 | EN77: 15.52 | EO77: 16.96 | EP77: 14.58 | EQ77: 14.73 | ER77: 14.32 | ES77: 12.1 | ET77: 13.94 | EU77: 14 | EV77: 12.16 | EW77: 13.71 | EX77: 15.62 | EY77: 14.69 | EZ77: 10.95 | FA77: 11.91 | FB77: 14.28 | FC77: 13.9 | FD77: 13.94 | FE77: 11.48 | FF77: 14.4 | FG77: 11.63 | FH77: 12.16 | FI77: 16.7 | FJ77: 15.69 | FK77: 11.95 | FL77: 13.47 | FM77: 14.39 | FN77: 11.24 | FO77: 11.4 | FP77: 14.69 | FQ77: 13.72 | FR77: 11.37 | FS77: 15.3 | FT77: 13.65 | FU77: 11.63 | FV77: 10.91 | FW77: 12.64 | FX77: 13.82 | FY77: 13.74 | FZ77: 15.34 | GA77: 13.57 | GB77: 10.87 | GC77: 11.19 | GD77: 11.84 | GE77: 15.55 | GF77: 11.59 | GG77: 13.46 | GH77: 12.89 | GI77: 11.88 | GJ77: 11.96 | GK77: 13.54 | GL77: 13.83 | GM77: 14.22 | GN77: 14.55 | GO77: 14.51 | GP77: 11.89 | GQ77: 11.64 | GR77: 13.32 | GS77: 13.11 | GT77: 11.74 | GU77: 11.05 | GV77: 10.69 | GW77: 11.12 | GX77: 11.34 | GY77: 13.8 | GZ77: 10.76 | HA77: 11.66 | HB77: 15.12 | HC77: 12.9 | HD77: 11.92 | HE77: 11.56 | HF77: 11.26 | HG77: 11.59 | HH77: 10.58 | HI77: 11.16 | HJ77: 11.41 | HK77: 10.72 | HL77: 11.81 | HM77: 10.88 | HN77: 11.69 | HO77: 10.62 | HP77: 11.3 | HQ77: 11.06 | HR77: 10.88 | HS77: 10.88 | HT77: 11.59 | HU77: 11.41 | HV77: 10.37 | HW77: 10.58 | HX77: 10.76 | HY77: 11.19 | HZ77: 11.02 | IA77: 12.31 | IB77: 10.96 | IC77: 12.1 | ID77: 11.38 | IE77: 10.95 | IF77: 11.28 | IG77: 10.58 | IH77: 10.23 | II77: 10.27 | IJ77: 11.92 | IK77: 11.64 | IL77: 10.99 | IM77: 11.06 | IN77: 12.63 | IO77: 11.04 | IP77: 11.85 | IQ77: 11.52 | IR77: 10.84 | IS77: 11.88 | IT77: 12.96 | IU77: 10.84 | IV77: 10.72 | IW77: 10.08 | IX77: 14.18 | IY77: 14.72 | IZ77: 15.99 | JA77: 12.05 | JB77: 11.05 | JC77: 10.3 | JD77: 13.03 | JE77: 13.36 | JF77: 17.16 | JG77: 10.64 | JH77: 11.18 | JI77: 10.84 | JJ77: 15.84 | JK77: 13.56 | JL77: 10.76 | JM77: 13.64 | JN77: 11.08 | JO77: 11.66 | JP77: 12.89 | JQ77: 10.37 | JR77: 10.98 | JS77: 9.83 | JT77: 11.69 | JU77: 12.46 | JV77: 10.23 | JW77: 10.41 | JX77: 11.53 | JY77: 15.44 | JZ77: 11.98 | KA77: 14.86 | KB77: 13.72 | KC77: 14.29 | KD77: 10.19 | KE77: 13.04 | KF77: 11.93 | KG77: 15 | KH77: 15.62 | KI77: 15.3 | KJ77: 10.76 | KK77: 11.06 | KL77: 14.62 | KM77: 14.91 | KN77: 14.69 | KO77: 14.63 | KP77: 263.48 | KQ77: 13.61 | KR77: 12.13 | KS77: 16.2 | KT77: 61.45 | KU77: 11.71 | KV77: 14.51 | KW77: 14.47 | KX77: 11.66 | KY77: 11.38 | KZ77: 15.41 | LA77: 14.5 | LB77: 15.55 | LC77: 14.01 | LD77: 15.34 | LE77: 14.55 | LF77: 11.6 | LG77: 15.12 | LH77: 14.15 | LI77: 10.72 | LJ77: 14.87 | LK77: 19.36 | LL77: 12.28 | LM77: 10.65 | LN77: 21.17 | LO77: 127.01 | LP77: 18.86 | LQ77: 15.04 | LR77: 15.98 | LS77: 13.54 | LT77: 11.81 | LU77: 15.91 | LV77: 15.26 | LW77: 14.87 | LX77: 14.9 | LY77: 16.74 | LZ77: 11.47 | MA77: 11.48 | MB77: 18.78 | MC77: 94.39 | MD77: 17.56 | ME77: 16.06 | MF77: 15.59 | MG77: 13.32 | MH77: 14.3 | MI77: 18.36 | MJ77: 15.55 | MK77: 15.88 | ML77: 15.96 | MM77: 16.02 | MN77: 15.13 | MO77: 14.11 | MP77: 18.03 | MQ77: 16.78 | MR77: 16.55 | MS77: 20.92 | MT77: 17.02 | MU77: 12.89 | MV77: 17.35 | MW77: 16.85 | MX77: 16.52 | MY77: 15.83 | MZ77: 15.63 | NA77: 17.6 | NB77: 13.28 | NC77: 15.78 | ND77: 15.3 | NE77: 13.93 | NF77: 14.72 | NG77: 15.08 | NH77: 19.4 | NI77: 13.75 | NJ77: 11.96 | NK77: 14.97
B78: 6 | C78: 18.5 | D78: 18.62 | E78: =E77+1 -> 77 | F78: =F77 -> 1 | G78: =G54 -> 5 | H78: =H54+1 -> 4 | I78: ;
B79: 6 | C79: 18.47 | D79: 17.93 | E79: =E78+1 -> 78 | F79: =F78 -> 1 | G79: =G55 -> 6 | H79: =H55+1 -> 4 | I79: ;
B80: 6 | C80: 18.46 | D80: 18.71 | E80: =E79+1 -> 79 | F80: =F79 -> 1 | G80: =G56 -> 7 | H80: =H56+1 -> 4 | I80: ;
B81: 6 | C81: 24.77 | D81: 18.98 | E81: =E80+1 -> 80 | F81: =F80 -> 1 | G81: =G57 -> 8 | H81: =H57+1 -> 4 | I81: ;
B82: 6 | C82: 458.89 | D82: 256.03 | E82: =E81+1 -> 81 | F82: =F81 -> 1 | G82: =G58 -> 9 | H82: =H58+1 -> 4 | I82: ;
B83: 6 | C83: 508.39 | D83: 195.62 | E83: =E82+1 -> 82 | F83: =F82 -> 1 | G83: =G59 -> 10 | H83: =H59+1 -> 4 | I83: ;
B84: 6 | C84: 428.62 | D84: 139.82 | E84: =E83+1 -> 83 | F84: =F83 -> 1 | G84: =G60 -> 11 | H84: =H60+1 -> 4 | I84: ;
B85: 6 | C85: 477.79 | D85: 240.98 | E85: =E84+1 -> 84 | F85: =F84 -> 1 | G85: =G61 -> 12 | H85: =H61+1 -> 4 | I85: ;
B86: 6 | C86: 36.65 | D86: 3.85 | E86: =E85+1 -> 85 | F86: =F85 -> 1 | G86: =G62 -> 13 | H86: =H62+1 -> 4 | I86: ;
B87: 6 | C87: 439.52 | D87: 148.25 | E87: =E86+1 -> 86 | F87: =F86 -> 1 | G87: =G63 -> 14 | H87: =H63+1 -> 4 | I87: ;
B88: 6 | C88: 476.39 | D88: 168.08 | E88: =E87+1 -> 87 | F88: =F87 -> 1 | G88: =G64 -> 15 | H88: =H64+1 -> 4 | I88: ;
B89: 6 | C89: 474.41 | D89: 181.98 | E89: =E88+1 -> 88 | F89: =F88 -> 1 | G89: =G65 -> 16 | H89: =H65+1 -> 4 | I89: ;
... B745: 2 | C745: 333.42 | D745: 170.35 | E745: =E744+1 -> 744 | F745: =F744 -> 1 | G745: =G721 -> 24 | H745: =H721+1 -> 31 | I745: ;
B746: 6 | C746: 324.72 | D746: 169.74 | E746: 1 | F746: =F745+1 -> 2 | G746: =G722 -> 1 | H746: 1 | I746: ;
B747: 6 | C747: 109.86 | D747: 70.27 | E747: =E746+1 -> 2 | F747: =F746 -> 2 | G747: =G723 -> 2 | H747: 1 | I747: ;
B748: 6 | C748: 24.98 | D748: 22.54 | E748: =E747+1 -> 3 | F748: =F747 -> 2 | G748: =G724 -> 3 | H748: 1 | I748: ;
B749: 6 | C749: 24.91 | D749: 21.78 | E749: =E748+1 -> 4 | F749: =F748 -> 2 | G749: =G725 -> 4 | H749: 1 | I749: ;
B750: 6 | C750: 22.11 | D750: 21.86 | E750: =E749+1 -> 5 | F750: =F749 -> 2 | G750: =G726 -> 5 | H750: 1 | I750: ;
B751: 6 | C751: 17.78 | D751: 17.14 | E751: =E750+1 -> 6 | F751: =F750 -> 2 | G751: =G727 -> 6 | H751: 1 | I751: ;
B752: 6 | C752: 17.71 | D752: 17.43 | E752: =E751+1 -> 7 | F752: =F751 -> 2 | G752: =G728 -> 7 | H752: 1 | I752: ;
B753: 6 | C753: 27.17 | D753: 20.46 | E753: =E752+1 -> 8 | F753: =F752 -> 2 | G753: =G729 -> 8 | H753: 1 | I753: ;
B754: 6 | C754: 442.26 | D754: 243.66 | E754: =E753+1 -> 9 | F754: =F753 -> 2 | G754: =G730 -> 9 | H754: 1 | I754: ;
B755: 6 | C755: 386.35 | D755: 145.44 | E755: =E754+1 -> 10 | F755: =F754 -> 2 | G755: =G731 -> 10 | H755: 1 | I755: ;
B756: 6 | C756: 473.51 | D756: 203.94 | E756: =E755+1 -> 11 | F756: =F755 -> 2 | G756: =G732 -> 11 | H756: 1 | I756: ;
B757: 6 | C757: 435.56 | D757: 242.24 | E757: =E756+1 -> 12 | F757: =F756 -> 2 | G757: =G733 -> 12 | H757: 1 | I757: ;
B758: 6 | C758: 62.65 | D758: 11.23 | E758: =E757+1 -> 13 | F758: =F757 -> 2 | G758: =G734 -> 13 | H758: 1 | I758: ;
... B769: 6 | C769: 342 | D769: 185.39 | E769: =E768+1 -> 24 | F769: =F768 -> 2 | G769: =G745 -> 24 | H769: 1 | I769: ;
B770: 6 | C770: 341.28 | D770: 186.98 | E770: =E769+1 -> 25 | F770: =F769 -> 2 | G770: =G746 -> 1 | H770: =H746+1 -> 2 | I770: ;
B771: 6 | C771: 39.42 | D771: 27.03 | E771: =E770+1 -> 26 | F771: =F770 -> 2 | G771: =G747 -> 2 | H771: =H747+1 -> 2 | I771: ;
B772: 6 | C772: 25.45 | D772: 20.34 | E772: =E771+1 -> 27 | F772: =F771 -> 2 | G772: =G748 -> 3 | H772: =H748+1 -> 2 | I772: ;
B773: 6 | C773: 25.45 | D773: 21.6 | E773: =E772+1 -> 28 | F773: =F772 -> 2 | G773: =G749 -> 4 | H773: =H749+1 -> 2 | I773: ;
B774: 6 | C774: 25.53 | D774: 21.99 | E774: =E773+1 -> 29 | F774: =F773 -> 2 | G774: =G750 -> 5 | H774: =H750+1 -> 2 | I774: ;
B775: 6 | C775: 23.11 | D775: 20.23 | E775: =E774+1 -> 30 | F775: =F774 -> 2 | G775: =G751 -> 6 | H775: =H751+1 -> 2 | I775: ;
B776: 6 | C776: 17.13 | D776: 17.99 | E776: =E775+1 -> 31 | F776: =F775 -> 2 | G776: =G752 -> 7 | H776: =H752+1 -> 2 | I776: ;
B777: 6 | C777: 26.11 | D777: 18.4 | E777: =E776+1 -> 32 | F777: =F776 -> 2 | G777: =G753 -> 8 | H777: =H753+1 -> 2 | I777: ;
B778: 6 | C778: 203.33 | D778: 108.07 | E778: =E777+1 -> 33 | F778: =F777 -> 2 | G778: =G754 -> 9 | H778: =H754+1 -> 2 | I778: ;
B779: 6 | C779: 243.35 | D779: 65.1 | E779: =E778+1 -> 34 | F779: =F778 -> 2 | G779: =G755 -> 10 | H779: =H755+1 -> 2 | I779: ;
B780: 6 | C780: 274.25 | D780: 90.48 | E780: =E779+1 -> 35 | F780: =F779 -> 2 | G780: =G756 -> 11 | H780: =H756+1 -> 2 | I780: ;
B781: 6 | C781: 272.33 | D781: 137.55 | E781: =E780+1 -> 36 | F781: =F780 -> 2 | G781: =G757 -> 12 | H781: =H757+1 -> 2 | I781: ;
... B1417: 2 | C1417: 21.2 | D1417: 22.75 | E1417: =E1416+1 -> 672 | F1417: =F1416 -> 2 | G1417: =G1393 -> 24 | H1417: =H1393+1 -> 28 | I1417: ;
B1418: 6 | C1418: 18.9 | D1418: 22.21 | E1418: 1 | F1418: 3 | G1418: =G1394 -> 1 | H1418: 1 | I1418: ;
B1419: 6 | C1419: 14.65 | D1419: 18.18 | E1419: =E1418+1 -> 2 | F1419: =F1418 -> 3 | G1419: =G1395 -> 2 | H1419: 1 | I1419: ;
B1420: 6 | C1420: 14.8 | D1420: 18.8 | E1420: =E1419+1 -> 3 | F1420: =F1419 -> 3 | G1420: =G1396 -> 3 | H1420: 1 | I1420: ;
B1421: 6 | C1421: 16.56 | D1421: 23.04 | E1421: =E1420+1 -> 4 | F1421: =F1420 -> 3 | G1421: =G1397 -> 4 | H1421: 1 | I1421: ;
B1422: 6 | C1422: 14.9 | D1422: 19.11 | E1422: =E1421+1 -> 5 | F1422: =F1421 -> 3 | G1422: =G1398 -> 5 | H1422: 1 | I1422: ;
...
